Workbook

Sheet Дотоод
C2: Хүний эрхийн зөрчилтэй холбоотой 7 хоног бүрийн мэдээ, мэдээллийн бүртгэлийн хүснэгт
E3: Монгол
A4: 2026.04.07 | L4: Улаанбаатар хот
A5: Д/д | B5: Мэдээллийн огноо | C5: Мэдээлэл дэх үйл явдал болсон хугацаа | D5: Мэдээллийн гарчиг | E5: Мэдээллийн товч утга | F5: Үйл явдал болсон байршил | G5: Хөндөгдсөн эрх | H5: Зөрчил үйлдсэн байж болзошгүй этгээд /хариуцагч/ | I5: Хариу арга хэмжээ авсан эсэх | J5: Эх сурвалж /дэлгэрэнгүй/ | K5: Холбоос | L5: Баталгаажуулалт | M5: Эрхийн ангилал (авто) | N5: Эрх — гараар засах | O5: ЭРХИЙН АНГИЛАЛ | P5: Нийгмийн бүлэг (авто) | Q5: Бүлэг — гараар засах | R5: НИЙГМИЙН БҮЛЭГ
A6: 2026.04.06-10
A7: 1 | B7: 2026.04.06 | C7: 2026.04 | D7: Хотын даргыг огцруулах өргөдөлд гарын үсэг цуглуулж байгаа “United info hub” сайт албан ёсных тул ХЭҮК-т хандахаар болжээ | E7: Хотын даргыг огцруулах өргөдөлтэй холбоотой иргэдийн гарын үсэг цуглуулах үйл ажиллагаанд саад учруулсан, хуулийн байгууллагаар “далайлгасан” нь эвлэлдэн нэгдэх эрхийн зөрчил гэж үзэн Хүний эрхийн Үндэсний Комисст хандах | F7: Улаанбаатар | G7: Иргэдийн улс төрийн оролцоо, үзэл бодлоо илэрхийлэх эрх зөрчигдсөн байж болзошгүй | H7: НЗД бөгөөд УБ хотын Захирагч Х.Нямбаатар | J7: United info hub цахим хуудас isee.mn цахим сайт | K7: https://isee.mn/n/89499 https://www.facebook.com/photo?fbid=1273857221519791&set=a.408757958029726 | M7: {=IF($G7="","",IFERROR(INDEX(Ангилал!$A$5:$A$22,MATCH(TRUE(),INDEX(ISNUMBER(SEARCH(Ангилал!$B$5:$B$22,$G7&" "&$D7))+ISNUMBER(SEARCH(Ангилал!$C$5:$C$22,$G7&" "&$D7))+IF(Ангилал!$D$5:$D$22="",0,ISNUMBER(SEARCH(Ангилал!$D$5:$D$22,$G7&" "&$D7)))+IF(Ангилал!$E$5:$E$22="",0,ISNUMBER(SEARCH(Ангилал!$E$5:$E$22,$G7&" "&$D7)))>0,0),0)),"Бусад"))} -> Үзэл бодлоо илэрхийлэх, мэдээллийн эрх | O7: =IF($G7="","",IF($N7<>"",$N7,$M7)) -> Үзэл бодлоо илэрхийлэх, мэдээллийн эрх | P7: {=IF($G7="","",IFERROR(INDEX(Ангилал!$G$5:$G$16,MATCH(TRUE(),INDEX(ISNUMBER(SEARCH(Ангилал!$H$5:$H$16,$G7&" "&$D7&" "&$E7))+ISNUMBER(SEARCH(Ангилал!$I$5:$I$16,$G7&" "&$D7&" "&$E7))+ISNUMBER(SEARCH(Ангилал!$J$5:$J$16,$G7&" "&$D7&" "&$E7))+ISNUMBER(SEARCH(Ангилал!$K$5:$K$16,$G7&" "&$D7&" "&$E7))>0,0),0)),"Ерөнхий нийт"))} -> Ерөнхий нийт | R7: =IF($G7="","",IF($Q7<>"",$Q7,$P7)) -> Ерөнхий нийт
A8: 2 | B8: 2026.04.09 | C8: 2026.04 | D8: Тоглоомын талбайн аюулгүй байдал: 10 тоглоомын талбай тутмын 6 нь хүүхдийн эрүүл мэнд, аюулгүй байдалд ноцтой эрсдэлтэй | E8: MNB World-ийн Facebook snippet-д улсын хэмжээнд 10 талбайн 6 нь хүүхдийн аюулгүй байдал, эрүүл мэндэд ноцтой эрсдэлтэй гэж дурдсан; өөр snippet-д Улаанбаатарын 9 дүүргийн талбайн 78% нь аюулгүй байдлын шаардлага хангахгүй гэжээ. | F8: Улаанбаатар | G8: Хүүхдийн амьд явах, аюулгүй байх, эрүүл орчинд байх эрх | H8: Орон нутгийн захиргаа, талбай хариуцагч байгууллага, хяналтын байгууллагууд | I8: . Эрсдэлийг олон нийтэд мэдээлсэн боловч авсан шийдвэр тодорхой бус байна. | J8: MNB world | K8: https://www.facebook.com/mnbworld/videos/six-out-of-every-10-playgrounds-across-the-country-pose-a-serious-risk-to-childr/925123123688279/ | M8: {=IF($G8="","",IFERROR(INDEX(Ангилал!$A$5:$A$22,MATCH(TRUE(),INDEX(ISNUMBER(SEARCH(Ангилал!$B$5:$B$22,$G8&" "&$D8))+ISNUMBER(SEARCH(Ангилал!$C$5:$C$22,$G8&" "&$D8))+IF(Ангилал!$D$5:$D$22="",0,ISNUMBER(SEARCH(Ангилал!$D$5:$D$22,$G8&" "&$D8)))+IF(Ангилал!$E$5:$E$22="",0,ISNUMBER(SEARCH(Ангилал!$E$5:$E$22,$G8&" "&$D8)))>0,0),0)),"Бусад"))} -> Хүүхдийн эрх | O8: =IF($G8="","",IF($N8<>"",$N8,$M8)) -> Хүүхдийн эрх | P8: {=IF($G8="","",IFERROR(INDEX(Ангилал!$G$5:$G$16,MATCH(TRUE(),INDEX(ISNUMBER(SEARCH(Ангилал!$H$5:$H$16,$G8&" "&$D8&" "&$E8))+ISNUMBER(SEARCH(Ангилал!$I$5:$I$16,$G8&" "&$D8&" "&$E8))+ISNUMBER(SEARCH(Ангилал!$J$5:$J$16,$G8&" "&$D8&" "&$E8))+ISNUMBER(SEARCH(Ангилал!$K$5:$K$16,$G8&" "&$D8&" "&$E8))>0,0),0)),"Ерөнхий нийт"))} -> Хүүхэд | R8: =IF($G8="","",IF($Q8<>"",$Q8,$P8)) -> Хүүхэд
A9: 3 | B9: 2026.04.03 | C9: 2026.04 | D9: Сургуулийн орчны аюулгүй байдал хангалтгүй | E9: Сургуулийн орчинд эрүүл ахуй, аюулгүй байдлын стандарт хангалтгүй байгааг мэдээлж, хүүхдийн эрүүл орчинд суралцах эрх зөрчигдөж болзошгүй | F9: Монгол Улс | G9: Хүүхдийн эрх, эрүүл аюулгүй орчинд суралцах эрх | H9: Сургууль, боловсролын байгууллага | J9: Facebook (MNB World) | K9: https://www.facebook.com/mnbworld/videos/news-mongolia-04032026-/2081325279112896/ | M9: {=IF($G9="","",IFERROR(INDEX(Ангилал!$A$5:$A$22,MATCH(TRUE(),INDEX(ISNUMBER(SEARCH(Ангилал!$B$5:$B$22,$G9&" "&$D9))+ISNUMBER(SEARCH(Ангилал!$C$5:$C$22,$G9&" "&$D9))+IF(Ангилал!$D$5:$D$22="",0,ISNUMBER(SEARCH(Ангилал!$D$5:$D$22,$G9&" "&$D9)))+IF(Ангилал!$E$5:$E$22="",0,ISNUMBER(SEARCH(Ангилал!$E$5:$E$22,$G9&" "&$D9)))>0,0),0)),"Бусад"))} -> Хүүхдийн эрх | O9: =IF($G9="","",IF($N9<>"",$N9,$M9)) -> Хүүхдийн эрх | P9: {=IF($G9="","",IFERROR(INDEX(Ангилал!$G$5:$G$16,MATCH(TRUE(),INDEX(ISNUMBER(SEARCH(Ангилал!$H$5:$H$16,$G9&" "&$D9&" "&$E9))+ISNUMBER(SEARCH(Ангилал!$I$5:$I$16,$G9&" "&$D9&" "&$E9))+ISNUMBER(SEARCH(Ангилал!$J$5:$J$16,$G9&" "&$D9&" "&$E9))+ISNUMBER(SEARCH(Ангилал!$K$5:$K$16,$G9&" "&$D9&" "&$E9))>0,0),0)),"Ерөнхий нийт"))} -> Хүүхэд | R9: =IF($G9="","",IF($Q9<>"",$Q9,$P9)) -> Хүүхэд
A10: 4 | B10: 2026.04 | C10: 2026.04 | D10: Иргэдийн пост устгах, censorship асуудал | E10: Зарим хэрэглэгчид пост устгагдсан, account хязгаарлагдсан талаар мэдээлсэн. Үзэл бодлоо илэрхийлэх эрх зөрчигдөж болзошгүй | F10: Онлайн орчин | G10: Үзэл бодлоо илэрхийлэх эрх | H10: Платформ болон зохицуулалт | J10: Facebook / Twitter хэрэглэгчид | K10: #censorship хаштагууд | M10: {=IF($G10="","",IFERROR(INDEX(Ангилал!$A$5:$A$22,MATCH(TRUE(),INDEX(ISNUMBER(SEARCH(Ангилал!$B$5:$B$22,$G10&" "&$D10))+ISNUMBER(SEARCH(Ангилал!$C$5:$C$22,$G10&" "&$D10))+IF(Ангилал!$D$5:$D$22="",0,ISNUMBER(SEARCH(Ангилал!$D$5:$D$22,$G10&" "&$D10)))+IF(Ангилал!$E$5:$E$22="",0,ISNUMBER(SEARCH(Ангилал!$E$5:$E$22,$G10&" "&$D10)))>0,0),0)),"Бусад"))} -> Үзэл бодлоо илэрхийлэх, мэдээллийн эрх | O10: =IF($G10="","",IF($N10<>"",$N10,$M10)) -> Үзэл бодлоо илэрхийлэх, мэдээллийн эрх | P10: {=IF($G10="","",IFERROR(INDEX(Ангилал!$G$5:$G$16,MATCH(TRUE(),INDEX(ISNUMBER(SEARCH(Ангилал!$H$5:$H$16,$G10&" "&$D10&" "&$E10))+ISNUMBER(SEARCH(Ангилал!$I$5:$I$16,$G10&" "&$D10&" "&$E10))+ISNUMBER(SEARCH(Ангилал!$J$5:$J$16,$G10&" "&$D10&" "&$E10))+ISNUMBER(SEARCH(Ангилал!$K$5:$K$16,$G10&" "&$D10&" "&$E10))>0,0),0)),"Ерөнхий нийт"))} -> Ерөнхий нийт | R10: =IF($G10="","",IF($Q10<>"",$Q10,$P10)) -> Ерөнхий нийт
A11: 2026.04.13-17 | M11: {=IF($G11="","",IFERROR(INDEX(Ангилал!$A$5:$A$22,MATCH(TRUE(),INDEX(ISNUMBER(SEARCH(Ангилал!$B$5:$B$22,$G11&" "&$D11))+ISNUMBER(SEARCH(Ангилал!$C$5:$C$22,$G11&" "&$D11))+IF(Ангилал!$D$5:$D$22="",0,ISNUMBER(SEARCH(Ангилал!$D$5:$D$22,$G11&" "&$D11)))+IF(Ангилал!$E$5:$E$22="",0,ISNUMBER(SEARCH(Ангилал!$E$5:$E$22,$G11&" "&$D11)))>0,0),0)),"Бусад"))} | O11: =IF($G11="","",IF($N11<>"",$N11,$M11)) | P11: {=IF($G11="","",IFERROR(INDEX(Ангилал!$G$5:$G$16,MATCH(TRUE(),INDEX(ISNUMBER(SEARCH(Ангилал!$H$5:$H$16,$G11&" "&$D11&" "&$E11))+ISNUMBER(SEARCH(Ангилал!$I$5:$I$16,$G11&" "&$D11&" "&$E11))+ISNUMBER(SEARCH(Ангилал!$J$5:$J$16,$G11&" "&$D11&" "&$E11))+ISNUMBER(SEARCH(Ангилал!$K$5:$K$16,$G11&" "&$D11&" "&$E11))>0,0),0)),"Ерөнхий нийт"))} | R11: =IF($G11="","",IF($Q11<>"",$Q11,$P11))
A12: 5 | B12: 2026.04.15 | C12: 2026-04-10 2026-04-15 | D12: Сэтгүүлч Л.Баяржаргалын цагдан хорих шийдвэрийг цуцалсангүй | E12: “Нэгүүн.мн” сайтын сэтгүүлч Л.Баяржаргалыг 2026.04.10-наас нэг сарын хугацаатай цагдан хорьсон бөгөөд өмгөөлөгчийн гаргасан хүчингүй болгуулах хүсэлтийг шүүх 2026.04.14-нд хүлээн авахаас татгалзсан. | F12: Улаанбаатар хот | G12: Үзэл бодлоо илэрхийлэх, хэвлэн нийтлэх эрх, хувийн халдашгүй, чөлөөтэй байх эрх, шударга шүүхийн баталгаа | H12: БЗД-ийн прокурорын байгууллага, анхан шатны шүүх, мөрдөн шалгах байгууллага | I12: Шүүх өмгөөлөгчийн хүсэлтийг 2026.04.14-нд хэлэлцээд хүлээн авахаас татгалзсан, цагдан хорих арга хэмжээ хэвээр үлдсэн. | J12: GoGo.mn (2026.04.15) шүүхийн шийдвэрийн үргэлжлэл iKon.mn (2026.04.10) анхны цагдан хорих шийдвэр | K12: https://gogo.mn/r/d36x0g https://ikon.mn/n/3mpa | M12: {=IF($G12="","",IFERROR(INDEX(Ангилал!$A$5:$A$22,MATCH(TRUE(),INDEX(ISNUMBER(SEARCH(Ангилал!$B$5:$B$22,$G12&" "&$D12))+ISNUMBER(SEARCH(Ангилал!$C$5:$C$22,$G12&" "&$D12))+IF(Ангилал!$D$5:$D$22="",0,ISNUMBER(SEARCH(Ангилал!$D$5:$D$22,$G12&" "&$D12)))+IF(Ангилал!$E$5:$E$22="",0,ISNUMBER(SEARCH(Ангилал!$E$5:$E$22,$G12&" "&$D12)))>0,0),0)),"Бусад"))} -> Амьд явах, халдашгүй байх эрх | O12: =IF($G12="","",IF($N12<>"",$N12,$M12)) -> Амьд явах, халдашгүй байх эрх | P12: {=IF($G12="","",IFERROR(INDEX(Ангилал!$G$5:$G$16,MATCH(TRUE(),INDEX(ISNUMBER(SEARCH(Ангилал!$H$5:$H$16,$G12&" "&$D12&" "&$E12))+ISNUMBER(SEARCH(Ангилал!$I$5:$I$16,$G12&" "&$D12&" "&$E12))+ISNUMBER(SEARCH(Ангилал!$J$5:$J$16,$G12&" "&$D12&" "&$E12))+ISNUMBER(SEARCH(Ангилал!$K$5:$K$16,$G12&" "&$D12&" "&$E12))>0,0),0)),"Ерөнхий нийт"))} -> Хоригдол, саатуулагдсан хүн | R12: =IF($G12="","",IF($Q12<>"",$Q12,$P12)) -> Хоригдол, саатуулагдсан хүн
A13: 6 | B13: 2026.04.16 | C13: 2026-04-16 11:20 | D13: СӨХ-ийн ажилчид ба оршин суугчдын маргааны үеэр настай хүнийг зодсон байж болзошгүй хэрэг | E13: Сонгинохайрхан дүүргийн 13-р хорооны 11-р байрны үүдэнд настай хүнийг зодсон гэх дуудлага 2026.04.16-нд бүртгэгдсэн. Шалгалтаар тус байрны СӨХ-ийн ажилчид болон оршин суугчдын хооронд маргаан үүсч, улмаар иргэдийн хооронд зодоон болсон байж болзошгүй нөхцөл тогтоогдсон. | F13: Улаанбаатар хот, Сонгинохайрхан дүүрэг, 13-р хороо | G13: Бие махбодын халдашгүй байдал, аюулгүй амьдрах эрх, ахмад настны хамгаалалт | H13: Тухайн маргаанд оролцсон иргэд / СӨХ-ийн ажилчид (албан ёсоор тогтоогдоогүй) | I13: Цагдаагийн байгууллага хэргийн шалтгаан, нөхцөлийг тогтоох шалгалтыг үргэлжлүүлж байгаа. | J13: iSee.mn | K13: https://isee.mn/n/89972 | M13: {=IF($G13="","",IFERROR(INDEX(Ангилал!$A$5:$A$22,MATCH(TRUE(),INDEX(ISNUMBER(SEARCH(Ангилал!$B$5:$B$22,$G13&" "&$D13))+ISNUMBER(SEARCH(Ангилал!$C$5:$C$22,$G13&" "&$D13))+IF(Ангилал!$D$5:$D$22="",0,ISNUMBER(SEARCH(Ангилал!$D$5:$D$22,$G13&" "&$D13)))+IF(Ангилал!$E$5:$E$22="",0,ISNUMBER(SEARCH(Ангилал!$E$5:$E$22,$G13&" "&$D13)))>0,0),0)),"Бусад"))} -> Амьд явах, халдашгүй байх эрх | O13: =IF($G13="","",IF($N13<>"",$N13,$M13)) -> Амьд явах, халдашгүй байх эрх | P13: {=IF($G13="","",IFERROR(INDEX(Ангилал!$G$5:$G$16,MATCH(TRUE(),INDEX(ISNUMBER(SEARCH(Ангилал!$H$5:$H$16,$G13&" "&$D13&" "&$E13))+ISNUMBER(SEARCH(Ангилал!$I$5:$I$16,$G13&" "&$D13&" "&$E13))+ISNUMBER(SEARCH(Ангилал!$J$5:$J$16,$G13&" "&$D13&" "&$E13))+ISNUMBER(SEARCH(Ангилал!$K$5:$K$16,$G13&" "&$D13&" "&$E13))>0,0),0)),"Ерөнхий нийт"))} -> Ахмад настан | R13: =IF($G13="","",IF($Q13<>"",$Q13,$P13)) -> Ахмад настан
A14: 7 | B14: 2026.04.16 | C14: 2026-04-14 | D14: Туулын хурдны замын төслийн хүрээнд усны эх үүсвэрт эрсдэл, иргэдийг зураг авахыг хориглосон гэх гомдол | E14: Экологич болон иргэд Туулын төвлөрсөн усны эх үүсвэрийн ойролцоо шөнийн тээвэрлэлт, хүнд даацын хөдөлгөөн, байгаль орчинд хохирол учруулж болзошгүй нөхцөл байгааг мэдээлсэн. Мөн “хориотой бүс” гэх үндэслэлээр иргэдийг зураг авахыг хориглож, харин компанид шаардлага тавихгүй байна гэж ялгавартай хандлагын шинжтэй гомдол гаргасан. | F14: Хан-Уул дүүрэг, Туул голын ундны усны эх үүсвэр орчим | G14: Эрүүл, аюулгүй орчинд амьдрах эрх, мэдээлэл авах, иргэний оролцооны эрх, тэгш харьцах эрх | H14: Төслийн хэрэгжүүлэгч компани, хотын төслийн болон хяналтын холбогдох албан тушаалтнууд | I14: БОУАӨ-ийн яам төслийн ажлыг хуульд нийцүүлэх хүртэл түр зогсоосон, Засгийн газар сайдад шалгалт хийж, зөрчил тогтоогдвол арга хэмжээ авахыг үүрэг болгосон. | J14: Mongolcontent/CMSG иргэний гомдол, экологичийн байр суурь | K14: https://cmsg.mongolcontent.mn/r/ljem49 https://ubn.mn/p/96325 | M14: {=IF($G14="","",IFERROR(INDEX(Ангилал!$A$5:$A$22,MATCH(TRUE(),INDEX(ISNUMBER(SEARCH(Ангилал!$B$5:$B$22,$G14&" "&$D14))+ISNUMBER(SEARCH(Ангилал!$C$5:$C$22,$G14&" "&$D14))+IF(Ангилал!$D$5:$D$22="",0,ISNUMBER(SEARCH(Ангилал!$D$5:$D$22,$G14&" "&$D14)))+IF(Ангилал!$E$5:$E$22="",0,ISNUMBER(SEARCH(Ангилал!$E$5:$E$22,$G14&" "&$D14)))>0,0),0)),"Бусад"))} -> Эрүүл, аюулгүй орчинд амьдрах эрх | O14: =IF($G14="","",IF($N14<>"",$N14,$M14)) -> Эрүүл, аюулгүй орчинд амьдрах эрх | P14: {=IF($G14="","",IFERROR(INDEX(Ангилал!$G$5:$G$16,MATCH(TRUE(),INDEX(ISNUMBER(SEARCH(Ангилал!$H$5:$H$16,$G14&" "&$D14&" "&$E14))+ISNUMBER(SEARCH(Ангилал!$I$5:$I$16,$G14&" "&$D14&" "&$E14))+ISNUMBER(SEARCH(Ангилал!$J$5:$J$16,$G14&" "&$D14&" "&$E14))+ISNUMBER(SEARCH(Ангилал!$K$5:$K$16,$G14&" "&$D14&" "&$E14))>0,0),0)),"Ерөнхий нийт"))} -> Ерөнхий нийт | R14: =IF($G14="","",IF($Q14<>"",$Q14,$P14)) -> Ерөнхий нийт
A15: 8 | B15: 2026.04.16 | C15: Үргэлжилсэн 2026-04-16-нд нийтлэгдсэн | D15: Туул голын эрэгт “Шүгдэн”-гийн бумба зэрэг зүйлс олноор хаягдаж, голын ай сав бохирдож байна | E15: Сурвалжилгад Туул голын эрэг, хөвөөнд шашны зан үйлийн шинжтэй “Шүгдэн”-гийн бумба болон бусад зүйлс олноор хаягдаж, усны сав газар бохирдож буйг баримтжуулсан. Иргэдийн итгэл үнэмшлийн нэрээр гол ус, байгаль орчныг бохирдуулж буй практик нь нийтийн эрүүл, аюулгүй орчны эрхтэй зөрчилдөх эрсдэлтэй гэж асуудал хөндсөн. | F15: Улаанбаатар хот орчмын Туул голын эрэг, ай сав | G15: Эрүүл, аюулгүй орчинд амьдрах эрх, мэдээлэл авах, иргэний оролцооны эрх, тэгш харьцах эрх | H15: Хог, зан үйлийн зүйлсийг хаяж буй этгээдүүд, хяналт, цэвэрлэгээ сул байгаа эрх бүхий байгууллагууд | I15: Нийтлэлд тодорхой авсан арга хэмжээ дурдагдаагүй, асуудал нийтэд анхааруулгын хэлбэрээр тавигдсан. | J15: iSee.mn сурвалжилга | K15: https://isee.mn/n/89935 | M15: {=IF($G15="","",IFERROR(INDEX(Ангилал!$A$5:$A$22,MATCH(TRUE(),INDEX(ISNUMBER(SEARCH(Ангилал!$B$5:$B$22,$G15&" "&$D15))+ISNUMBER(SEARCH(Ангилал!$C$5:$C$22,$G15&" "&$D15))+IF(Ангилал!$D$5:$D$22="",0,ISNUMBER(SEARCH(Ангилал!$D$5:$D$22,$G15&" "&$D15)))+IF(Ангилал!$E$5:$E$22="",0,ISNUMBER(SEARCH(Ангилал!$E$5:$E$22,$G15&" "&$D15)))>0,0),0)),"Бусад"))} -> Эрүүл, аюулгүй орчинд амьдрах эрх | O15: =IF($G15="","",IF($N15<>"",$N15,$M15)) -> Эрүүл, аюулгүй орчинд амьдрах эрх | P15: {=IF($G15="","",IFERROR(INDEX(Ангилал!$G$5:$G$16,MATCH(TRUE(),INDEX(ISNUMBER(SEARCH(Ангилал!$H$5:$H$16,$G15&" "&$D15&" "&$E15))+ISNUMBER(SEARCH(Ангилал!$I$5:$I$16,$G15&" "&$D15&" "&$E15))+ISNUMBER(SEARCH(Ангилал!$J$5:$J$16,$G15&" "&$D15&" "&$E15))+ISNUMBER(SEARCH(Ангилал!$K$5:$K$16,$G15&" "&$D15&" "&$E15))>0,0),0)),"Ерөнхий нийт"))} -> Ерөнхий нийт | R15: =IF($G15="","",IF($Q15<>"",$Q15,$P15)) -> Ерөнхий нийт
A16: 9 | B16: 2026.04.16 | C16: 2026 оны 4-р сар | D16: Баянголд 9.2 кг мөнгөн ус хадгалж байсан | E16: Экологийн цагдаагийн албанаас Баянгол дүүрэгт худалдах зорилгоор хадгалж байсан 9.2 кг мөнгөн усыг илрүүлж хураан авчээ. Мөнгөн ус нь хүн, ураг, нярайд онцгой аюултай тул ийм тохиолдол нь эрүүл, аюулгүй орчинд амьдрах эрх болон эрүүл мэндийн эрхэд ноцтой эрсдэл үүсгэх шинжтэй. | F16: Баянгол дүүрэг | G16: Эрүүл, аюулгүй орчинд амьдрах эрх | H16: Мөнгөн ус хууль бусаар хадгалж байсан нэр бүхий этгээдүүд | I16: Экологийн цагдаагийн алба эд мөрийн баримтаар хураан авч, мөрдөн шалгах ажиллагаа явуулж байна. | J16: UBN Экологийн цагдаагийн мэдээлэл | K16: https://ubn.mn/p/96450 | M16: {=IF($G16="","",IFERROR(INDEX(Ангилал!$A$5:$A$22,MATCH(TRUE(),INDEX(ISNUMBER(SEARCH(Ангилал!$B$5:$B$22,$G16&" "&$D16))+ISNUMBER(SEARCH(Ангилал!$C$5:$C$22,$G16&" "&$D16))+IF(Ангилал!$D$5:$D$22="",0,ISNUMBER(SEARCH(Ангилал!$D$5:$D$22,$G16&" "&$D16)))+IF(Ангилал!$E$5:$E$22="",0,ISNUMBER(SEARCH(Ангилал!$E$5:$E$22,$G16&" "&$D16)))>0,0),0)),"Бусад"))} -> Эрүүл, аюулгүй орчинд амьдрах эрх | O16: =IF($G16="","",IF($N16<>"",$N16,$M16)) -> Эрүүл, аюулгүй орчинд амьдрах эрх | P16: {=IF($G16="","",IFERROR(INDEX(Ангилал!$G$5:$G$16,MATCH(TRUE(),INDEX(ISNUMBER(SEARCH(Ангилал!$H$5:$H$16,$G16&" "&$D16&" "&$E16))+ISNUMBER(SEARCH(Ангилал!$I$5:$I$16,$G16&" "&$D16&" "&$E16))+ISNUMBER(SEARCH(Ангилал!$J$5:$J$16,$G16&" "&$D16&" "&$E16))+ISNUMBER(SEARCH(Ангилал!$K$5:$K$16,$G16&" "&$D16&" "&$E16))>0,0),0)),"Ерөнхий нийт"))} -> Ерөнхий нийт | R16: =IF($G16="","",IF($Q16<>"",$Q16,$P16)) -> Ерөнхий нийт
A17: 2026.04.20-24 | M17: {=IF($G17="","",IFERROR(INDEX(Ангилал!$A$5:$A$22,MATCH(TRUE(),INDEX(ISNUMBER(SEARCH(Ангилал!$B$5:$B$22,$G17&" "&$D17))+ISNUMBER(SEARCH(Ангилал!$C$5:$C$22,$G17&" "&$D17))+IF(Ангилал!$D$5:$D$22="",0,ISNUMBER(SEARCH(Ангилал!$D$5:$D$22,$G17&" "&$D17)))+IF(Ангилал!$E$5:$E$22="",0,ISNUMBER(SEARCH(Ангилал!$E$5:$E$22,$G17&" "&$D17)))>0,0),0)),"Бусад"))} | O17: =IF($G17="","",IF($N17<>"",$N17,$M17)) | P17: {=IF($G17="","",IFERROR(INDEX(Ангилал!$G$5:$G$16,MATCH(TRUE(),INDEX(ISNUMBER(SEARCH(Ангилал!$H$5:$H$16,$G17&" "&$D17&" "&$E17))+ISNUMBER(SEARCH(Ангилал!$I$5:$I$16,$G17&" "&$D17&" "&$E17))+ISNUMBER(SEARCH(Ангилал!$J$5:$J$16,$G17&" "&$D17&" "&$E17))+ISNUMBER(SEARCH(Ангилал!$K$5:$K$16,$G17&" "&$D17&" "&$E17))>0,0),0)),"Ерөнхий нийт"))} | R17: =IF($G17="","",IF($Q17<>"",$Q17,$P17))
A18: 10 | B18: 2026.04.23 | C18: 2026.04.23 | D18: Оюутнууд ажил хийх эрхгүй байдаг юм уу | E18: Оюутнууд ажил хийх эрхгүй байдаг юм уу Оюутны дотуур байрны жижүүр шөнө унтах ёстой байдаг юм уу (Шөнө байнга л хаалга тогших чимээ) Шөнийн 2 цаг хавьцаа энэ охин хаалга тогшоод бараг хагас цаг гадаа жижүүр нь сэрсэн бололтой оруулахгүй гэж хэрэлдээд энэ охин учирлаж хэлээд гуйгаад ч оруулсангүй охин аргаа бараад яваад өглөө.Ийм хүйтэн хар шөнө охин хүүхдийг яаа гэж байгаа юм бол | F18: БГД-25 хороо Оюутны өргөө II | G18: Аюулгүй байх эрх. амь нас, эрүүл мэндэд эрсдэл учруулсан, хүнлэг бус, үл хайхрах харьцаа | H18: Оюутны өргөө II жижүүр | K18: https://www.facebook.com/groups/574571992993421/permalink/2540288836421717/?mibextid=wwXIfr&rdid=jJCliaxQsr6Ynik4# | M18: {=IF($G18="","",IFERROR(INDEX(Ангилал!$A$5:$A$22,MATCH(TRUE(),INDEX(ISNUMBER(SEARCH(Ангилал!$B$5:$B$22,$G18&" "&$D18))+ISNUMBER(SEARCH(Ангилал!$C$5:$C$22,$G18&" "&$D18))+IF(Ангилал!$D$5:$D$22="",0,ISNUMBER(SEARCH(Ангилал!$D$5:$D$22,$G18&" "&$D18)))+IF(Ангилал!$E$5:$E$22="",0,ISNUMBER(SEARCH(Ангилал!$E$5:$E$22,$G18&" "&$D18)))>0,0),0)),"Бусад"))} -> Эрүүдэн шүүлт, хүнлэг бус харьцаа | O18: =IF($G18="","",IF($N18<>"",$N18,$M18)) -> Эрүүдэн шүүлт, хүнлэг бус харьцаа | P18: {=IF($G18="","",IFERROR(INDEX(Ангилал!$G$5:$G$16,MATCH(TRUE(),INDEX(ISNUMBER(SEARCH(Ангилал!$H$5:$H$16,$G18&" "&$D18&" "&$E18))+ISNUMBER(SEARCH(Ангилал!$I$5:$I$16,$G18&" "&$D18&" "&$E18))+ISNUMBER(SEARCH(Ангилал!$J$5:$J$16,$G18&" "&$D18&" "&$E18))+ISNUMBER(SEARCH(Ангилал!$K$5:$K$16,$G18&" "&$D18&" "&$E18))>0,0),0)),"Ерөнхий нийт"))} -> Хүүхэд | R18: =IF($G18="","",IF($Q18<>"",$Q18,$P18)) -> Хүүхэд
A19: 2026.04.27-05.01 | M19: {=IF($G19="","",IFERROR(INDEX(Ангилал!$A$5:$A$22,MATCH(TRUE(),INDEX(ISNUMBER(SEARCH(Ангилал!$B$5:$B$22,$G19&" "&$D19))+ISNUMBER(SEARCH(Ангилал!$C$5:$C$22,$G19&" "&$D19))+IF(Ангилал!$D$5:$D$22="",0,ISNUMBER(SEARCH(Ангилал!$D$5:$D$22,$G19&" "&$D19)))+IF(Ангилал!$E$5:$E$22="",0,ISNUMBER(SEARCH(Ангилал!$E$5:$E$22,$G19&" "&$D19)))>0,0),0)),"Бусад"))} | O19: =IF($G19="","",IF($N19<>"",$N19,$M19)) | P19: {=IF($G19="","",IFERROR(INDEX(Ангилал!$G$5:$G$16,MATCH(TRUE(),INDEX(ISNUMBER(SEARCH(Ангилал!$H$5:$H$16,$G19&" "&$D19&" "&$E19))+ISNUMBER(SEARCH(Ангилал!$I$5:$I$16,$G19&" "&$D19&" "&$E19))+ISNUMBER(SEARCH(Ангилал!$J$5:$J$16,$G19&" "&$D19&" "&$E19))+ISNUMBER(SEARCH(Ангилал!$K$5:$K$16,$G19&" "&$D19&" "&$E19))>0,0),0)),"Ерөнхий нийт"))} | R19: =IF($G19="","",IF($Q19<>"",$Q19,$P19))
A20: 11 | B20: 2026.04.27 | C20: 2026-04-27 | D20: Ц.Мөнхтуяа: Манай жолооч осол гаргасан, мөргүүлсэн хүн зүгээр л байсан | E20: УИХ-ын гишүүн Ц.Мөнхтуяа өчигдөр зам тээврийн осол гаргасан.Тодруулбал, төрийн ордны баруун талд мотоциклтой зорчигчийг “Lexus" маркийн хар өнгийн машин мөргөсөн осол гаргасан юм. | F20: 2026 оны 4 дүгээр сарын 27-ны өдөр 12:30 цагийн орчим Төрийн ордны баруун талын замд гарсан. | G20: Хүнийг аюултай нөхцөл байдалд үлдээсэн | H20: УИХ-ын гишүүн Ц.Мөнхтуяа, түүний жолооч | I20: Мөргүүлсэн мотоциклтой иргэн зүгээр байсан, уучлал гуйгаад явсан гэж Ц.Мөнхтуяа гишүүн мэдэгдсэн. Зам тээврийн ослын хэргийн газар цагдаа нар ажиллаж байна. | J20: social орчин | K20: https://www.instagram.com/reels/DXoE3toFKao/ | M20: {=IF($G20="","",IFERROR(INDEX(Ангилал!$A$5:$A$22,MATCH(TRUE(),INDEX(ISNUMBER(SEARCH(Ангилал!$B$5:$B$22,$G20&" "&$D20))+ISNUMBER(SEARCH(Ангилал!$C$5:$C$22,$G20&" "&$D20))+IF(Ангилал!$D$5:$D$22="",0,ISNUMBER(SEARCH(Ангилал!$D$5:$D$22,$G20&" "&$D20)))+IF(Ангилал!$E$5:$E$22="",0,ISNUMBER(SEARCH(Ангилал!$E$5:$E$22,$G20&" "&$D20)))>0,0),0)),"Бусад"))} -> Бусад | O20: =IF($G20="","",IF($N20<>"",$N20,$M20)) -> Бусад | P20: {=IF($G20="","",IFERROR(INDEX(Ангилал!$G$5:$G$16,MATCH(TRUE(),INDEX(ISNUMBER(SEARCH(Ангилал!$H$5:$H$16,$G20&" "&$D20&" "&$E20))+ISNUMBER(SEARCH(Ангилал!$I$5:$I$16,$G20&" "&$D20&" "&$E20))+ISNUMBER(SEARCH(Ангилал!$J$5:$J$16,$G20&" "&$D20&" "&$E20))+ISNUMBER(SEARCH(Ангилал!$K$5:$K$16,$G20&" "&$D20&" "&$E20))>0,0),0)),"Ерөнхий нийт"))} -> Ерөнхий нийт | R20: =IF($G20="","",IF($Q20<>"",$Q20,$P20)) -> Ерөнхий нийт
A21: 12 | B21: 2026.04.29 | C21: 2026-04 | D21: Бид ялагдав… | E21: Шүүхийн Ерөнхий зөвлөл гэж байгууллага бий. ( ШЕЗ) Тэндэхийн ажилтан нэгэн залуу бүсгүйн гомдлыг Хүний эрхийн үндэсний комисс нь “ Энэ хүчирхийлэл биш. Харин ажлын байрны найрсаг харилцаа байнаа” гэсэн дүгнэлт гаргаж доромжлов.Одоо гадагшаа хандахаас даа. | F21: ШЕЗ | G21: Ажлын байрны бэлгийн дарамт | H21: ШЕЗ, ХҮЭК | J21: Сэтгүүлч Ganchimeg Badamdorj | K21: https://www.facebook.com/story.php?story_fbid=4443773159237570&id=100008147898597&mibextid=wwXIfr&rdid=3spAwJ1uPs49eTQp# | M21: {=IF($G21="","",IFERROR(INDEX(Ангилал!$A$5:$A$22,MATCH(TRUE(),INDEX(ISNUMBER(SEARCH(Ангилал!$B$5:$B$22,$G21&" "&$D21))+ISNUMBER(SEARCH(Ангилал!$C$5:$C$22,$G21&" "&$D21))+IF(Ангилал!$D$5:$D$22="",0,ISNUMBER(SEARCH(Ангилал!$D$5:$D$22,$G21&" "&$D21)))+IF(Ангилал!$E$5:$E$22="",0,ISNUMBER(SEARCH(Ангилал!$E$5:$E$22,$G21&" "&$D21)))>0,0),0)),"Бусад"))} -> Хүчирхийлэл, бэлгийн дарамтаас ангид байх | O21: =IF($G21="","",IF($N21<>"",$N21,$M21)) -> Хүчирхийлэл, бэлгийн дарамтаас ангид байх | P21: {=IF($G21="","",IFERROR(INDEX(Ангилал!$G$5:$G$16,MATCH(TRUE(),INDEX(ISNUMBER(SEARCH(Ангилал!$H$5:$H$16,$G21&" "&$D21&" "&$E21))+ISNUMBER(SEARCH(Ангилал!$I$5:$I$16,$G21&" "&$D21&" "&$E21))+ISNUMBER(SEARCH(Ангилал!$J$5:$J$16,$G21&" "&$D21&" "&$E21))+ISNUMBER(SEARCH(Ангилал!$K$5:$K$16,$G21&" "&$D21&" "&$E21))>0,0),0)),"Ерөнхий нийт"))} -> Ажилчид, хөдөлмөр эрхлэгчид | R21: =IF($G21="","",IF($Q21<>"",$Q21,$P21)) -> Ажилчид, хөдөлмөр эрхлэгчид
A22: 13 | B22: 2026.04.29 | C22: 2026-04-29 | D22: Хугацаат цэргийн албан хаагч өөрийгөө боомилж амиа хорлосон хэргийг шалгаж байна. | E22: Хилийн цэргийн дугаар ангид хугацаат цэргийн алба хааж байсан байлдагч амь насаа алдсан харамсалтай хэрэг гарлаа. Уг хэрэг энэ сарын 22-ны өдөр бүртгэгдсэн байна. Цагдаагийн ерөнхий газраас өгсөн мэдээллээр, 2026 оны дөрөвдүгээр сарын 22-ны өглөөний 07:50 цагт Төв аймгийн Мөнгөнморьт сумын нутаг, "Харзтайн ам" гэх газарт малын сууринд үүрэг гүйцэтгэж байсан цэрэг боомилсон байдалтай нас барсан гэх дуудлага иржээ. | F22: Урьдчилсан байдлаар амь хохирогч нь Багануур дүүрэг дэх Хилийн цэргийн дугаар ангид алба хааж байсан байлдагч болох нь тогтоогджээ. | G22: Амьд явах эрх, Хүний халдашгүй, чөлөөтэй байх эрх, Эрүүдэн шүүх, хүнлэг бус харьцаанаас ангид байх эрх, Хөдөлмөрийн болон албаны аюулгүй нөхцөлд байх эрх, Нэр төр, алдар хүндийн халдашгүй байдал | I22: Одоогоор цагдаагийн байгууллагаас хэргийн шалтгаан нөхцөлийг тодруулахаар мөрдөн шалгах ажиллагааг эхлүүлээд байна. | J22: newsroom.mn | K22: https://www.facebook.com/photo?fbid=122168961038663314&set=a.122108145662663314 | M22: {=IF($G22="","",IFERROR(INDEX(Ангилал!$A$5:$A$22,MATCH(TRUE(),INDEX(ISNUMBER(SEARCH(Ангилал!$B$5:$B$22,$G22&" "&$D22))+ISNUMBER(SEARCH(Ангилал!$C$5:$C$22,$G22&" "&$D22))+IF(Ангилал!$D$5:$D$22="",0,ISNUMBER(SEARCH(Ангилал!$D$5:$D$22,$G22&" "&$D22)))+IF(Ангилал!$E$5:$E$22="",0,ISNUMBER(SEARCH(Ангилал!$E$5:$E$22,$G22&" "&$D22)))>0,0),0)),"Бусад"))} -> Эрүүдэн шүүлт, хүнлэг бус харьцаа | O22: =IF($G22="","",IF($N22<>"",$N22,$M22)) -> Эрүүдэн шүүлт, хүнлэг бус харьцаа | P22: {=IF($G22="","",IFERROR(INDEX(Ангилал!$G$5:$G$16,MATCH(TRUE(),INDEX(ISNUMBER(SEARCH(Ангилал!$H$5:$H$16,$G22&" "&$D22&" "&$E22))+ISNUMBER(SEARCH(Ангилал!$I$5:$I$16,$G22&" "&$D22&" "&$E22))+ISNUMBER(SEARCH(Ангилал!$J$5:$J$16,$G22&" "&$D22&" "&$E22))+ISNUMBER(SEARCH(Ангилал!$K$5:$K$16,$G22&" "&$D22&" "&$E22))>0,0),0)),"Ерөнхий нийт"))} -> Ерөнхий нийт | R22: =IF($G22="","",IF($Q22<>"",$Q22,$P22)) -> Ерөнхий нийт
A23: 14 | B23: 2026.04.30 | C23: 2026-04 | D23: Зангиа зүүсэнгүй гээд ангийн багш нь хайч бариад хайчлаад явуулсан байх юм. Бас арай л муухай санагдлаа. Хүүхэд хайчилсан бол юу ч хэлэхгүй ээ. Багш нь хүүхдүүдийнхээ шүү. Багшийн ёс зүй, энэрэх хайрлах сэтгэл хаана байна | E23: Зангиа зүүсэнгүй гээд ангийн багш нь хайч бариад хайчлаад явуулсан байх юм. Бас арай л муухай санагдлаа. Хүүхэд хайчилсан бол юу ч хэлэхгүй ээ. Багш нь хүүхдүүдийнхээ шүү. Багшийн ёс зүй, энэрэх хайрлах сэтгэл хаана байна | F23: ЕБС | G23: Хүүхдийн эрхийн тухай хууль "7.1.Хүүхэд гэмт хэрэг, зөрчил, хүчирхийлэл, бие махбодийн шийтгэл, сэтгэл санааны дарамт, үл хайхрах байдал болон мөлжлөгийн аливаа хэлбэрээс нийгмийн бүх орчинд хамгаалагдах эрхтэй", Сургуулийн өмнөх болон ерөнхий боловсролын сургалтын байгууллагын багш, ажилтны мэргэжлийн ёс зүйн дүрмийн 4.2.2.Суралцагчид бие махбодийн шийтгэл, сэтгэл санааны дарамт үзүүлэх, хүчээр албадахаас татгалзах;. | H23: ЕБС-ийн багш | I23: - | J23: twitter | K23: https://x.com/zulegchin_zul/status/2049675579117670498/photo/1 | M23: {=IF($G23="","",IFERROR(INDEX(Ангилал!$A$5:$A$22,MATCH(TRUE(),INDEX(ISNUMBER(SEARCH(Ангилал!$B$5:$B$22,$G23&" "&$D23))+ISNUMBER(SEARCH(Ангилал!$C$5:$C$22,$G23&" "&$D23))+IF(Ангилал!$D$5:$D$22="",0,ISNUMBER(SEARCH(Ангилал!$D$5:$D$22,$G23&" "&$D23)))+IF(Ангилал!$E$5:$E$22="",0,ISNUMBER(SEARCH(Ангилал!$E$5:$E$22,$G23&" "&$D23)))>0,0),0)),"Бусад"))} -> Хүүхдийн эрх | O23: =IF($G23="","",IF($N23<>"",$N23,$M23)) -> Хүүхдийн эрх | P23: {=IF($G23="","",IFERROR(INDEX(Ангилал!$G$5:$G$16,MATCH(TRUE(),INDEX(ISNUMBER(SEARCH(Ангилал!$H$5:$H$16,$G23&" "&$D23&" "&$E23))+ISNUMBER(SEARCH(Ангилал!$I$5:$I$16,$G23&" "&$D23&" "&$E23))+ISNUMBER(SEARCH(Ангилал!$J$5:$J$16,$G23&" "&$D23&" "&$E23))+ISNUMBER(SEARCH(Ангилал!$K$5:$K$16,$G23&" "&$D23&" "&$E23))>0,0),0)),"Ерөнхий нийт"))} -> Хүүхэд | R23: =IF($G23="","",IF($Q23<>"",$Q23,$P23)) -> Хүүхэд
A24: 2026.05.04-08 | M24: {=IF($G24="","",IFERROR(INDEX(Ангилал!$A$5:$A$22,MATCH(TRUE(),INDEX(ISNUMBER(SEARCH(Ангилал!$B$5:$B$22,$G24&" "&$D24))+ISNUMBER(SEARCH(Ангилал!$C$5:$C$22,$G24&" "&$D24))+IF(Ангилал!$D$5:$D$22="",0,ISNUMBER(SEARCH(Ангилал!$D$5:$D$22,$G24&" "&$D24)))+IF(Ангилал!$E$5:$E$22="",0,ISNUMBER(SEARCH(Ангилал!$E$5:$E$22,$G24&" "&$D24)))>0,0),0)),"Бусад"))} | O24: =IF($G24="","",IF($N24<>"",$N24,$M24)) | P24: {=IF($G24="","",IFERROR(INDEX(Ангилал!$G$5:$G$16,MATCH(TRUE(),INDEX(ISNUMBER(SEARCH(Ангилал!$H$5:$H$16,$G24&" "&$D24&" "&$E24))+ISNUMBER(SEARCH(Ангилал!$I$5:$I$16,$G24&" "&$D24&" "&$E24))+ISNUMBER(SEARCH(Ангилал!$J$5:$J$16,$G24&" "&$D24&" "&$E24))+ISNUMBER(SEARCH(Ангилал!$K$5:$K$16,$G24&" "&$D24&" "&$E24))>0,0),0)),"Ерөнхий нийт"))} | R24: =IF($G24="","",IF($Q24<>"",$Q24,$P24))
A25: 15 | B25: 2026.05.03 | C25: 2026-05-03 | D25: БОДЬ”-ИЙН БОСС, ОФФТЕЙКИЙН ХААН, АТГ-ЫН АЛДУУЛ Д.БАЯСГАЛАН | E25: Санзай хотхонд оршин суудаг зарим иргэний гэрийн хаягийг дроноор зураг авч нийтэд мэдээлсэн. | F25: social орчин | G25: Халдашгүй байдал, хүний хувийн мэдээлэл хамгаалалт | H25: Цахим сайтууд | J25: social орчин | K25: https://www.facebook.com/photo?fbid=1534570931563990&set=pcb.1534571024897314 | M25: {=IF($G25="","",IFERROR(INDEX(Ангилал!$A$5:$A$22,MATCH(TRUE(),INDEX(ISNUMBER(SEARCH(Ангилал!$B$5:$B$22,$G25&" "&$D25))+ISNUMBER(SEARCH(Ангилал!$C$5:$C$22,$G25&" "&$D25))+IF(Ангилал!$D$5:$D$22="",0,ISNUMBER(SEARCH(Ангилал!$D$5:$D$22,$G25&" "&$D25)))+IF(Ангилал!$E$5:$E$22="",0,ISNUMBER(SEARCH(Ангилал!$E$5:$E$22,$G25&" "&$D25)))>0,0),0)),"Бусад"))} -> Амьд явах, халдашгүй байх эрх | O25: =IF($G25="","",IF($N25<>"",$N25,$M25)) -> Амьд явах, халдашгүй байх эрх | P25: {=IF($G25="","",IFERROR(INDEX(Ангилал!$G$5:$G$16,MATCH(TRUE(),INDEX(ISNUMBER(SEARCH(Ангилал!$H$5:$H$16,$G25&" "&$D25&" "&$E25))+ISNUMBER(SEARCH(Ангилал!$I$5:$I$16,$G25&" "&$D25&" "&$E25))+ISNUMBER(SEARCH(Ангилал!$J$5:$J$16,$G25&" "&$D25&" "&$E25))+ISNUMBER(SEARCH(Ангилал!$K$5:$K$16,$G25&" "&$D25&" "&$E25))>0,0),0)),"Ерөнхий нийт"))} -> Ерөнхий нийт | R25: =IF($G25="","",IF($Q25<>"",$Q25,$P25)) -> Ерөнхий нийт
A26: 16 | B26: 2026.05.04 | C26: 2026-05-04 | D26: Шүүх үнэхээр болохгүй байна. | E26: Justice Delayed Is Justice Denied гэдэг үг бий. Үгчилж орчуулбал “Хойшлогдсон шудрага ёс бол үгүйсгэгдсэн шудрага ёс” буюу “Хэрэг маргааныг хугацаанд нь шийдээгүй бол огт шийдээгүйгээс ялгаагүй” агуулгатай. Аливаа асуудлыг үнэн зөвөөр шийдэх нь чухал боловч цаг хугацаанд нь шийдэх нь түүнээс дутуугүй чухал. Үүн дээр манай шүүхийнхэн фэйлдэж байгаа. | F26: Шүүх | G26: Шударга шүүхээр шүүлгэх | H26: Шүүх | K26: https://www.facebook.com/story.php?story_fbid=966537989670660&id=100089434025594&mibextid=wwXIfr&rdid=uOiUtvncs4i01o6e# | M26: {=IF($G26="","",IFERROR(INDEX(Ангилал!$A$5:$A$22,MATCH(TRUE(),INDEX(ISNUMBER(SEARCH(Ангилал!$B$5:$B$22,$G26&" "&$D26))+ISNUMBER(SEARCH(Ангилал!$C$5:$C$22,$G26&" "&$D26))+IF(Ангилал!$D$5:$D$22="",0,ISNUMBER(SEARCH(Ангилал!$D$5:$D$22,$G26&" "&$D26)))+IF(Ангилал!$E$5:$E$22="",0,ISNUMBER(SEARCH(Ангилал!$E$5:$E$22,$G26&" "&$D26)))>0,0),0)),"Бусад"))} -> Шударга шүүхээр шүүлгэх эрх | O26: =IF($G26="","",IF($N26<>"",$N26,$M26)) -> Шударга шүүхээр шүүлгэх эрх | P26: {=IF($G26="","",IFERROR(INDEX(Ангилал!$G$5:$G$16,MATCH(TRUE(),INDEX(ISNUMBER(SEARCH(Ангилал!$H$5:$H$16,$G26&" "&$D26&" "&$E26))+ISNUMBER(SEARCH(Ангилал!$I$5:$I$16,$G26&" "&$D26&" "&$E26))+ISNUMBER(SEARCH(Ангилал!$J$5:$J$16,$G26&" "&$D26&" "&$E26))+ISNUMBER(SEARCH(Ангилал!$K$5:$K$16,$G26&" "&$D26&" "&$E26))>0,0),0)),"Ерөнхий нийт"))} -> Ерөнхий нийт | R26: =IF($G26="","",IF($Q26<>"",$Q26,$P26)) -> Ерөнхий нийт
A27: 17 | B27: 2026.05.03 | C27: 2026.05.03 | D27: “Сэтгүүлчид дуугарахгүй бол хүний эрхийн зөрчил улам газар авч, нийгэм уруудна” | E27: News.mn болон X/Facebook дээр хэвлэл мэдээллийн эрх чөлөө, сэтгүүлчдийн эрхийн зөрчил, айлган сүрдүүлэх, биед халдах, дарамт шахалтын талаар ярилцлага/мэдээ түгсэн. Нийтлэлд Монголд сэтгүүлчдийн эрхийн зөрчил, ажлын нөхцөлд мэдэгдэхүйц өөрчлөлт гараагүй гэж дурдсан. | F27: Улаанбаатар хот / Монгол Улс | G27: Үзэл бодлоо илэрхийлэх эрх; хэвлэлийн эрх чөлөө; аюулгүй ажиллах эрх | H27: Төрийн болон төрийн бус этгээд, албан тушаалтан байж болзошгүй (нийтлэлд ерөнхийлсөн) | I27: Шууд арга хэмжээ ; асуудал олон нийтэд мэдээлэгдсэн | J27: News.mn, News.mn, Facebook, Twitter | K27: https://x.com/News_mn/status/2050820114447212810 | M27: {=IF($G27="","",IFERROR(INDEX(Ангилал!$A$5:$A$22,MATCH(TRUE(),INDEX(ISNUMBER(SEARCH(Ангилал!$B$5:$B$22,$G27&" "&$D27))+ISNUMBER(SEARCH(Ангилал!$C$5:$C$22,$G27&" "&$D27))+IF(Ангилал!$D$5:$D$22="",0,ISNUMBER(SEARCH(Ангилал!$D$5:$D$22,$G27&" "&$D27)))+IF(Ангилал!$E$5:$E$22="",0,ISNUMBER(SEARCH(Ангилал!$E$5:$E$22,$G27&" "&$D27)))>0,0),0)),"Бусад"))} -> Үзэл бодлоо илэрхийлэх, мэдээллийн эрх | O27: =IF($G27="","",IF($N27<>"",$N27,$M27)) -> Үзэл бодлоо илэрхийлэх, мэдээллийн эрх | P27: {=IF($G27="","",IFERROR(INDEX(Ангилал!$G$5:$G$16,MATCH(TRUE(),INDEX(ISNUMBER(SEARCH(Ангилал!$H$5:$H$16,$G27&" "&$D27&" "&$E27))+ISNUMBER(SEARCH(Ангилал!$I$5:$I$16,$G27&" "&$D27&" "&$E27))+ISNUMBER(SEARCH(Ангилал!$J$5:$J$16,$G27&" "&$D27&" "&$E27))+ISNUMBER(SEARCH(Ангилал!$K$5:$K$16,$G27&" "&$D27&" "&$E27))>0,0),0)),"Ерөнхий нийт"))} -> Сэтгүүлч, хүний эрхийн хамгаалагч | R27: =IF($G27="","",IF($Q27<>"",$Q27,$P27)) -> Сэтгүүлч, хүний эрхийн хамгаалагч
A28: 18 | B28: 2026.05.06 | C28: 2026.05.06 | D28: Хүний эрх зөрчсөн Увс аймгийн Засаг даргын орлогч С.Анхбаяр ажлаа хийж явна | E28: Eguur.mn болон X/Facebook дээр С.Анхбаярыг ХЭҮК-оос хүний эрх зөрчсөн гэж дүгнэсэн ч ажил үүргээ гүйцэтгэж байгаа талаар мэдээлсэн. Аймгийн Засаг дарга албан ёсоор ажилдаа ирсний дараа сонсгол явуулж, асуудлыг хэлэлцэнэ гэж дурдсан. | F28: Увс аймаг Наранбулаг сум | G28: Хүний нэр төр, халдашгүй байдал, төрийн албан тушаалтны зүй бус үйлдлээс хамгаалуулах эрх | H28: Увс аймгийн Засаг даргын орлогч С.Анхбаяр | I28: ХЭҮК дүгнэлт гаргасан. ймгийн Засаг дарга сонсгол явуулж хэлэлцэнэ гэж мэдээлсэн, хариуцлагын шийдвэр гараагүй | J28: Eguur.mn, Facebook, Twitter | K28: https://x.com/Eguur_mn/status/2051542289936433336 | M28: {=IF($G28="","",IFERROR(INDEX(Ангилал!$A$5:$A$22,MATCH(TRUE(),INDEX(ISNUMBER(SEARCH(Ангилал!$B$5:$B$22,$G28&" "&$D28))+ISNUMBER(SEARCH(Ангилал!$C$5:$C$22,$G28&" "&$D28))+IF(Ангилал!$D$5:$D$22="",0,ISNUMBER(SEARCH(Ангилал!$D$5:$D$22,$G28&" "&$D28)))+IF(Ангилал!$E$5:$E$22="",0,ISNUMBER(SEARCH(Ангилал!$E$5:$E$22,$G28&" "&$D28)))>0,0),0)),"Бусад"))} -> Амьд явах, халдашгүй байх эрх | O28: =IF($G28="","",IF($N28<>"",$N28,$M28)) -> Амьд явах, халдашгүй байх эрх | P28: {=IF($G28="","",IFERROR(INDEX(Ангилал!$G$5:$G$16,MATCH(TRUE(),INDEX(ISNUMBER(SEARCH(Ангилал!$H$5:$H$16,$G28&" "&$D28&" "&$E28))+ISNUMBER(SEARCH(Ангилал!$I$5:$I$16,$G28&" "&$D28&" "&$E28))+ISNUMBER(SEARCH(Ангилал!$J$5:$J$16,$G28&" "&$D28&" "&$E28))+ISNUMBER(SEARCH(Ангилал!$K$5:$K$16,$G28&" "&$D28&" "&$E28))>0,0),0)),"Ерөнхий нийт"))} -> Ерөнхий нийт | R28: =IF($G28="","",IF($Q28<>"",$Q28,$P28)) -> Ерөнхий нийт
A29: 19 | B29: 2026.05.07 | C29: 2026 оны 4 дүгээр сарын статистик, 2026.05.07-нд нийтлэгдсэн | D29: 2026 оны 04 дүгээр сард 840,017 зөрчил бүртгэгджээ | E29: MNB болон GoGo-д УЕПГ-ын мэдээлэлд үндэслэн улсын хэмжээнд 2026 оны 4 дүгээр сард 840,017 зөрчил бүртгэгдсэн, 89.3 хувь нь нийслэлд бүртгэгдсэн, олон нийтийн газарт зүй бусаар биеэ авч явах зөрчил 14,104 болж өссөн талаар мэдээлсэн. | F29: Улаанбаатар хот давамгай | G29: Аюулгүй орчинд амьдрах эрх, нийтийн хэв журам, хохирол нөхөн төлүүлэх эрх | H29: Зөрчил гаргасан хувь хүн, хуулийн этгээдүүд | I29: Цагдаа, Гааль, Татвар, ГИХГ зэрэг эрх бүхий байгууллагууд зөрчил шалган шийдвэрлэх ажиллагаа явуулсан. Шүүхээс 0.4 хувьд шийтгэл оногдуулсан | J29: MNB, GoGo, УЕПГ-ын мэдээлэл | K29: https://www.mnb.mn/i/345409 | M29: {=IF($G29="","",IFERROR(INDEX(Ангилал!$A$5:$A$22,MATCH(TRUE(),INDEX(ISNUMBER(SEARCH(Ангилал!$B$5:$B$22,$G29&" "&$D29))+ISNUMBER(SEARCH(Ангилал!$C$5:$C$22,$G29&" "&$D29))+IF(Ангилал!$D$5:$D$22="",0,ISNUMBER(SEARCH(Ангилал!$D$5:$D$22,$G29&" "&$D29)))+IF(Ангилал!$E$5:$E$22="",0,ISNUMBER(SEARCH(Ангилал!$E$5:$E$22,$G29&" "&$D29)))>0,0),0)),"Бусад"))} -> Бусад | O29: =IF($G29="","",IF($N29<>"",$N29,$M29)) -> Бусад | P29: {=IF($G29="","",IFERROR(INDEX(Ангилал!$G$5:$G$16,MATCH(TRUE(),INDEX(ISNUMBER(SEARCH(Ангилал!$H$5:$H$16,$G29&" "&$D29&" "&$E29))+ISNUMBER(SEARCH(Ангилал!$I$5:$I$16,$G29&" "&$D29&" "&$E29))+ISNUMBER(SEARCH(Ангилал!$J$5:$J$16,$G29&" "&$D29&" "&$E29))+ISNUMBER(SEARCH(Ангилал!$K$5:$K$16,$G29&" "&$D29&" "&$E29))>0,0),0)),"Ерөнхий нийт"))} -> Ерөнхий нийт | R29: =IF($G29="","",IF($Q29<>"",$Q29,$P29)) -> Ерөнхий нийт
A30: 2026.05.11-15 | M30: {=IF($G30="","",IFERROR(INDEX(Ангилал!$A$5:$A$22,MATCH(TRUE(),INDEX(ISNUMBER(SEARCH(Ангилал!$B$5:$B$22,$G30&" "&$D30))+ISNUMBER(SEARCH(Ангилал!$C$5:$C$22,$G30&" "&$D30))+IF(Ангилал!$D$5:$D$22="",0,ISNUMBER(SEARCH(Ангилал!$D$5:$D$22,$G30&" "&$D30)))+IF(Ангилал!$E$5:$E$22="",0,ISNUMBER(SEARCH(Ангилал!$E$5:$E$22,$G30&" "&$D30)))>0,0),0)),"Бусад"))} | O30: =IF($G30="","",IF($N30<>"",$N30,$M30)) | P30: {=IF($G30="","",IFERROR(INDEX(Ангилал!$G$5:$G$16,MATCH(TRUE(),INDEX(ISNUMBER(SEARCH(Ангилал!$H$5:$H$16,$G30&" "&$D30&" "&$E30))+ISNUMBER(SEARCH(Ангилал!$I$5:$I$16,$G30&" "&$D30&" "&$E30))+ISNUMBER(SEARCH(Ангилал!$J$5:$J$16,$G30&" "&$D30&" "&$E30))+ISNUMBER(SEARCH(Ангилал!$K$5:$K$16,$G30&" "&$D30&" "&$E30))>0,0),0)),"Ерөнхий нийт"))} | R30: =IF($G30="","",IF($Q30<>"",$Q30,$P30))
A31: 20 | B31: 2026.05.12 | C31: 2026-05-11 | D31: Өдөр шөнөгүй дуу чимээнд галзуурлаа. | E31: Онцгой байдлын Серена дохионоос илүү дугарах юи. Тайван амьдарчмаар байна. Амралтын өдөрч түчигнэчихийн. | F31: ХУД, Шилтгээн хотхоны урд АПУ ХХК-ийн зүүн талд | G31: Эрүүл, аюулгүй орчинд амьдрах эрх, Хүүхдийн эрүүл өсөж хөгжих эрх.Зохистой амьжиргааны түвшинд амьдрах эрх Хууль тогтоомжоор тогтоосон хэм хэмжээгээр хамгаалуулах эрх | H31: Камдер" ХХК | J31: twitter | K31: https://x.com/erdeneundaroyu/status/2053941920666362041 | M31: {=IF($G31="","",IFERROR(INDEX(Ангилал!$A$5:$A$22,MATCH(TRUE(),INDEX(ISNUMBER(SEARCH(Ангилал!$B$5:$B$22,$G31&" "&$D31))+ISNUMBER(SEARCH(Ангилал!$C$5:$C$22,$G31&" "&$D31))+IF(Ангилал!$D$5:$D$22="",0,ISNUMBER(SEARCH(Ангилал!$D$5:$D$22,$G31&" "&$D31)))+IF(Ангилал!$E$5:$E$22="",0,ISNUMBER(SEARCH(Ангилал!$E$5:$E$22,$G31&" "&$D31)))>0,0),0)),"Бусад"))} -> Хүүхдийн эрх | O31: =IF($G31="","",IF($N31<>"",$N31,$M31)) -> Хүүхдийн эрх | P31: {=IF($G31="","",IFERROR(INDEX(Ангилал!$G$5:$G$16,MATCH(TRUE(),INDEX(ISNUMBER(SEARCH(Ангилал!$H$5:$H$16,$G31&" "&$D31&" "&$E31))+ISNUMBER(SEARCH(Ангилал!$I$5:$I$16,$G31&" "&$D31&" "&$E31))+ISNUMBER(SEARCH(Ангилал!$J$5:$J$16,$G31&" "&$D31&" "&$E31))+ISNUMBER(SEARCH(Ангилал!$K$5:$K$16,$G31&" "&$D31&" "&$E31))>0,0),0)),"Ерөнхий нийт"))} -> Хүүхэд | R31: =IF($G31="","",IF($Q31<>"",$Q31,$P31)) -> Хүүхэд
A32: 21 | B32: 2026.05.12 | C32: 2026-05-12 | D32: ШӨНИЙН “ОРИЛСОН ЯНДАН”-Г ЗОГСООХОД НЭГДЭЭРЭЙ | J32: facebook | K32: https://shorturl.at/sgJwW | M32: {=IF($G32="","",IFERROR(INDEX(Ангилал!$A$5:$A$22,MATCH(TRUE(),INDEX(ISNUMBER(SEARCH(Ангилал!$B$5:$B$22,$G32&" "&$D32))+ISNUMBER(SEARCH(Ангилал!$C$5:$C$22,$G32&" "&$D32))+IF(Ангилал!$D$5:$D$22="",0,ISNUMBER(SEARCH(Ангилал!$D$5:$D$22,$G32&" "&$D32)))+IF(Ангилал!$E$5:$E$22="",0,ISNUMBER(SEARCH(Ангилал!$E$5:$E$22,$G32&" "&$D32)))>0,0),0)),"Бусад"))} | O32: =IF($G32="","",IF($N32<>"",$N32,$M32)) | P32: {=IF($G32="","",IFERROR(INDEX(Ангилал!$G$5:$G$16,MATCH(TRUE(),INDEX(ISNUMBER(SEARCH(Ангилал!$H$5:$H$16,$G32&" "&$D32&" "&$E32))+ISNUMBER(SEARCH(Ангилал!$I$5:$I$16,$G32&" "&$D32&" "&$E32))+ISNUMBER(SEARCH(Ангилал!$J$5:$J$16,$G32&" "&$D32&" "&$E32))+ISNUMBER(SEARCH(Ангилал!$K$5:$K$16,$G32&" "&$D32&" "&$E32))>0,0),0)),"Ерөнхий нийт"))} | R32: =IF($G32="","",IF($Q32<>"",$Q32,$P32))
A33: 22 | B33: 2026.05.12 | C33: 2026-05-12 | D33: БЗД-ийн Цагдаагийн 1-р хэлтсийн мэдүүлэг авах өрөө хүүхдийн эрх зөрчиж байгаа тухай | E33: БЗД-ийн Цагдаагийн 1-р хэлтсийн мэдүүлэг авах өрөөний цус нөж, эвлэрхий хэмхэрхий сандалнуудыг солиулж хүүхдийн эрхийг хангуулах | F33: БЗД-ийн Ц1Х-ийн мэдүүлаг авах өрөө | H33: БЗД-ийн Цагдаагийн 1 дүгээр хэлтэс | J33: facebook | K33: https://www.facebook.com/share/v/15niYiD3REY/?mibextid=wwXIfr | M33: {=IF($G33="","",IFERROR(INDEX(Ангилал!$A$5:$A$22,MATCH(TRUE(),INDEX(ISNUMBER(SEARCH(Ангилал!$B$5:$B$22,$G33&" "&$D33))+ISNUMBER(SEARCH(Ангилал!$C$5:$C$22,$G33&" "&$D33))+IF(Ангилал!$D$5:$D$22="",0,ISNUMBER(SEARCH(Ангилал!$D$5:$D$22,$G33&" "&$D33)))+IF(Ангилал!$E$5:$E$22="",0,ISNUMBER(SEARCH(Ангилал!$E$5:$E$22,$G33&" "&$D33)))>0,0),0)),"Бусад"))} | O33: =IF($G33="","",IF($N33<>"",$N33,$M33)) | P33: {=IF($G33="","",IFERROR(INDEX(Ангилал!$G$5:$G$16,MATCH(TRUE(),INDEX(ISNUMBER(SEARCH(Ангилал!$H$5:$H$16,$G33&" "&$D33&" "&$E33))+ISNUMBER(SEARCH(Ангилал!$I$5:$I$16,$G33&" "&$D33&" "&$E33))+ISNUMBER(SEARCH(Ангилал!$J$5:$J$16,$G33&" "&$D33&" "&$E33))+ISNUMBER(SEARCH(Ангилал!$K$5:$K$16,$G33&" "&$D33&" "&$E33))>0,0),0)),"Ерөнхий нийт"))} | R33: =IF($G33="","",IF($Q33<>"",$Q33,$P33))
A34: 23 | B34: 2026.05.14 | C34: 2026-05-14 | D34: Хан-Уул дүүрэг, ажил хийж бгаа ганц ч хүн алга. Хүүхэд хөгшид нүхэнд унаж хөл гараа хугалахаар л бна | E34: Хан-Уул дүүрэг, ажил хийж бгаа ганц ч хүн алга. Хүүхэд хөгшид нүхэнд унаж хөл гараа хугалахаар л бна | F34: ХУД | G34: Эрүүл аюулгүй орчинд амьдрах эрх, Амь нас, бие махбодын халдашгүй байдлын эрх, Хөгжлийн бэрхшээлтэй хүний эрх, Чөлөөтэй зорчих эрх | J34: twitter | K34: https://x.com/ariukaaboby/status/2054789815020007486 | M34: {=IF($G34="","",IFERROR(INDEX(Ангилал!$A$5:$A$22,MATCH(TRUE(),INDEX(ISNUMBER(SEARCH(Ангилал!$B$5:$B$22,$G34&" "&$D34))+ISNUMBER(SEARCH(Ангилал!$C$5:$C$22,$G34&" "&$D34))+IF(Ангилал!$D$5:$D$22="",0,ISNUMBER(SEARCH(Ангилал!$D$5:$D$22,$G34&" "&$D34)))+IF(Ангилал!$E$5:$E$22="",0,ISNUMBER(SEARCH(Ангилал!$E$5:$E$22,$G34&" "&$D34)))>0,0),0)),"Бусад"))} -> Амьд явах, халдашгүй байх эрх | O34: =IF($G34="","",IF($N34<>"",$N34,$M34)) -> Амьд явах, халдашгүй байх эрх | P34: {=IF($G34="","",IFERROR(INDEX(Ангилал!$G$5:$G$16,MATCH(TRUE(),INDEX(ISNUMBER(SEARCH(Ангилал!$H$5:$H$16,$G34&" "&$D34&" "&$E34))+ISNUMBER(SEARCH(Ангилал!$I$5:$I$16,$G34&" "&$D34&" "&$E34))+ISNUMBER(SEARCH(Ангилал!$J$5:$J$16,$G34&" "&$D34&" "&$E34))+ISNUMBER(SEARCH(Ангилал!$K$5:$K$16,$G34&" "&$D34&" "&$E34))>0,0),0)),"Ерөнхий нийт"))} -> Хөгжлийн бэрхшээлтэй иргэд | R34: =IF($G34="","",IF($Q34<>"",$Q34,$P34)) -> Хөгжлийн бэрхшээлтэй иргэд
A35: 24 | B35: 2026.05.14 | C35: 2026-05-14 | D35: Иргэний сэрэмжлүүлэг | E35: Өчигдөр орой нөхөртэйгөө хоолоо шингээгээд алхахаар гарсан юм. Кино үйлдвэрийн явган хүний гарцан дээр бүх машин улаан гэрлээрээ зогсчихсон, хүмүүс ногоон гэрлээрээ гарч байсан. Бид 2 ч бас гарцаар гарах гээд алхтал ардаас маш хурдтай, ямар ч чимээгүй явдаг мотоцикл/скүүтер шиг юм шууд дайраад зугтаагаад алга болсон… | F35: УБ хот | G35: Амьд явах болон бие махбодын халдашгүй байдлын эрх, Чөлөөтэй зорчих эрх, Хүртээмжтэй, аюулгүй хот, орчинд амьдрах эрх | J35: twitter | K35: https://x.com/XGerlee/status/2054819313547346201 | M35: {=IF($G35="","",IFERROR(INDEX(Ангилал!$A$5:$A$22,MATCH(TRUE(),INDEX(ISNUMBER(SEARCH(Ангилал!$B$5:$B$22,$G35&" "&$D35))+ISNUMBER(SEARCH(Ангилал!$C$5:$C$22,$G35&" "&$D35))+IF(Ангилал!$D$5:$D$22="",0,ISNUMBER(SEARCH(Ангилал!$D$5:$D$22,$G35&" "&$D35)))+IF(Ангилал!$E$5:$E$22="",0,ISNUMBER(SEARCH(Ангилал!$E$5:$E$22,$G35&" "&$D35)))>0,0),0)),"Бусад"))} -> Амьд явах, халдашгүй байх эрх | O35: =IF($G35="","",IF($N35<>"",$N35,$M35)) -> Амьд явах, халдашгүй байх эрх | P35: {=IF($G35="","",IFERROR(INDEX(Ангилал!$G$5:$G$16,MATCH(TRUE(),INDEX(ISNUMBER(SEARCH(Ангилал!$H$5:$H$16,$G35&" "&$D35&" "&$E35))+ISNUMBER(SEARCH(Ангилал!$I$5:$I$16,$G35&" "&$D35&" "&$E35))+ISNUMBER(SEARCH(Ангилал!$J$5:$J$16,$G35&" "&$D35&" "&$E35))+ISNUMBER(SEARCH(Ангилал!$K$5:$K$16,$G35&" "&$D35&" "&$E35))>0,0),0)),"Ерөнхий нийт"))} -> Ерөнхий нийт | R35: =IF($G35="","",IF($Q35<>"",$Q35,$P35)) -> Ерөнхий нийт
A36: 2026.05.18-22 | M36: {=IF($G36="","",IFERROR(INDEX(Ангилал!$A$5:$A$22,MATCH(TRUE(),INDEX(ISNUMBER(SEARCH(Ангилал!$B$5:$B$22,$G36&" "&$D36))+ISNUMBER(SEARCH(Ангилал!$C$5:$C$22,$G36&" "&$D36))+IF(Ангилал!$D$5:$D$22="",0,ISNUMBER(SEARCH(Ангилал!$D$5:$D$22,$G36&" "&$D36)))+IF(Ангилал!$E$5:$E$22="",0,ISNUMBER(SEARCH(Ангилал!$E$5:$E$22,$G36&" "&$D36)))>0,0),0)),"Бусад"))} | O36: =IF($G36="","",IF($N36<>"",$N36,$M36)) | P36: {=IF($G36="","",IFERROR(INDEX(Ангилал!$G$5:$G$16,MATCH(TRUE(),INDEX(ISNUMBER(SEARCH(Ангилал!$H$5:$H$16,$G36&" "&$D36&" "&$E36))+ISNUMBER(SEARCH(Ангилал!$I$5:$I$16,$G36&" "&$D36&" "&$E36))+ISNUMBER(SEARCH(Ангилал!$J$5:$J$16,$G36&" "&$D36&" "&$E36))+ISNUMBER(SEARCH(Ангилал!$K$5:$K$16,$G36&" "&$D36&" "&$E36))>0,0),0)),"Ерөнхий нийт"))} | R36: =IF($G36="","",IF($Q36<>"",$Q36,$P36))
A37: 25 | B37: 2026.05.16 | D37: Тавхан настай айлын жаахан хүүхдийг хөлийг нь дөрөөтэй нь хүлж хурдан морь унуулаад, хүүхэд мориноосоо унаж гэмтэлийн эмнэлэгт 14 хоноод, эх нялхаст эмчлүүлж байна. Одоо ч бие нь сайнгүй. | E37: Тавхан настай айлын жаахан хүүхдийг хөлийг нь дөрөөтэй нь хүлж хурдан морь унуулаад, хүүхэд мориноосоо унаж гэмтэлийн эмнэлэгт 14 хоноод, эх нялхаст эмчлүүлж байна. Одоо ч бие нь сайнгүй. Нөгөө олон хүний эрх, хүүхдийн эрх хамгаалагчид ажлаа хийгээч!!! | F37: УБ хот | G37: Амьд явах, эсэн мэнд өсөж хөгжих эрх, Аливаа хэлбэрийн хүчирхийлэл, хайхрамжгүй хандлагаас ангид байх эрх,Хөдөлмөрийн мөлжлөг, хүүхдийн хөдөлмөрийн тэвчишгүй хэлбэрээс хамгаалуулах эрх,Хүүхдийн язгуур ашиг сонирхлыг нэн тэргүүнд тавих зарчмын зөрчил | J37: facebook | K37: https://www.facebook.com/100001721631371/posts/27112941285013226/?rdid=10Bqt5i9Iswj0y8s# | M37: {=IF($G37="","",IFERROR(INDEX(Ангилал!$A$5:$A$22,MATCH(TRUE(),INDEX(ISNUMBER(SEARCH(Ангилал!$B$5:$B$22,$G37&" "&$D37))+ISNUMBER(SEARCH(Ангилал!$C$5:$C$22,$G37&" "&$D37))+IF(Ангилал!$D$5:$D$22="",0,ISNUMBER(SEARCH(Ангилал!$D$5:$D$22,$G37&" "&$D37)))+IF(Ангилал!$E$5:$E$22="",0,ISNUMBER(SEARCH(Ангилал!$E$5:$E$22,$G37&" "&$D37)))>0,0),0)),"Бусад"))} -> Хүүхдийн эрх | O37: =IF($G37="","",IF($N37<>"",$N37,$M37)) -> Хүүхдийн эрх | P37: {=IF($G37="","",IFERROR(INDEX(Ангилал!$G$5:$G$16,MATCH(TRUE(),INDEX(ISNUMBER(SEARCH(Ангилал!$H$5:$H$16,$G37&" "&$D37&" "&$E37))+ISNUMBER(SEARCH(Ангилал!$I$5:$I$16,$G37&" "&$D37&" "&$E37))+ISNUMBER(SEARCH(Ангилал!$J$5:$J$16,$G37&" "&$D37&" "&$E37))+ISNUMBER(SEARCH(Ангилал!$K$5:$K$16,$G37&" "&$D37&" "&$E37))>0,0),0)),"Ерөнхий нийт"))} -> Хүүхэд | R37: =IF($G37="","",IF($Q37<>"",$Q37,$P37)) -> Хүүхэд
A38: 26 | B38: 2026.05.16 | D38: Зодуулсан гэх цэргийн аав: Хүүг минь зодчихоод ар гэрт нь хэлэхгүй хагалгаанд оруулах гэж байсныг мэдлээ. Генералын хүү гэж өөрийгөө хэлдэг залуу цэргүүдийг "Хаана цохиулахаа өөрөө сонго" гэж дарамталж байгаад зоддог гэдгийг сонсоод шоконд ороод байна | E38: Дорнод аймагт байрлах Хил хамгаалах ерөнхий газрын 132 дугаар ангийн салааны захирагч Т нь долоон цэргийг зодож, хоёр цэргийн биеийн байдал хүндэрч, хагалгаанд орохоор болжээ. Энэ талаар зодуулсан гэх цэргийн аав С.Мөнхбатаас тодрууллаа. Тэрбээр “Миний хүү их сургуулийн гуравдугаар дамжаанд суралцаж байсан. Энэ жил өөрийн хүсэлтээр цэрэгт явахаар болсон. Манай хүүтэй хамт СХД-ээс цэрэгт татагдсан долоон хүүхдийг бүгдийг нь зодсон. Нэг хүүхдийн эрүү хугарч, өнөөдөр хагалгаанд орж байна. Эрүүл саруул гэж оношлоод авч явсан хүүхдүүдийг өөрийгөө генералын хүү хэмээн томордог, ‘Хаана цохиулахаа өөрөө сонго’ хэмээн дарамталдаг тус ангийн салааны захирагч Тэмүүжин гэх залууд маш их гомдолтой байна. Миний хүүгээс хэдхэн ах залуу байна лээ. Зодуулсан хүүхдүүдийн эцэг эх камерын бичлэг үзэх гэсэн боловч “Камер ажиллахгүй, бичлэг байхгүй” гэж хэлсэн. Мөн цэрэгт тэнцэж, тангараг өргөхөөр очсон долоон хүүхдийн хоёрыг нь сэтгэцийн өвчтэй хэмээн цэргээс халж байна. Нэг нь бүр Америкаас цэрэгт явахаар ирсэн хүүхэд байгаа. Миний хүүг зодчихоод Дорнод аймагт гэрийнхэнд нь хэлэлгүй хагалгаанд оруулах гэж байсныг хүү маань өөрөө эсэргүүцэж байж, өчигдөр Улаанбаатар хотод ирэхэд нь би мэдсэн. Эмч нар бөөр нь тус газраа өшиглүүлснээс үрийн суваг нь хаагдсан, хагалгаанд орж нээх шаардлагатай гэсэн. Нарийн мэргэжлийн хэллэгийг нь сайн мэдэхгүй байна. Эрүүл саруул хүү минь эх орноо хамгаална гэж яваад үргүй болох хэмжээнд хүрээд ирнэ гэж даанч санасангүй” хэмээлээ | F38: Хил хамгаалах ерөнхий газрын 132 дугаар анги | G38: Эрүү шүүлт, хүнлэг бус, хэрцгий харьцаанаас ангид байх эрх, Амьд явах, биеийн халдашгүй байдалд эзэн байх эрх, Эрүүл мэндээ хамгаалуулах, эмнэлгийн тусламж авах эрх, Сэтгэл зүйн хүчирхийлэлд өртөхгүй байх эрх | H38: Хил хамгаалах ерөнхий газрын 132 дугаар ангийн салааны захирагч | J38: facebook | K38: https://www.facebook.com/100063933908097/posts/1480690020738781/?rdid=wiL07pClem4g2rpw# | M38: {=IF($G38="","",IFERROR(INDEX(Ангилал!$A$5:$A$22,MATCH(TRUE(),INDEX(ISNUMBER(SEARCH(Ангилал!$B$5:$B$22,$G38&" "&$D38))+ISNUMBER(SEARCH(Ангилал!$C$5:$C$22,$G38&" "&$D38))+IF(Ангилал!$D$5:$D$22="",0,ISNUMBER(SEARCH(Ангилал!$D$5:$D$22,$G38&" "&$D38)))+IF(Ангилал!$E$5:$E$22="",0,ISNUMBER(SEARCH(Ангилал!$E$5:$E$22,$G38&" "&$D38)))>0,0),0)),"Бусад"))} -> Эрүүдэн шүүлт, хүнлэг бус харьцаа | O38: =IF($G38="","",IF($N38<>"",$N38,$M38)) -> Эрүүдэн шүүлт, хүнлэг бус харьцаа | P38: {=IF($G38="","",IFERROR(INDEX(Ангилал!$G$5:$G$16,MATCH(TRUE(),INDEX(ISNUMBER(SEARCH(Ангилал!$H$5:$H$16,$G38&" "&$D38&" "&$E38))+ISNUMBER(SEARCH(Ангилал!$I$5:$I$16,$G38&" "&$D38&" "&$E38))+ISNUMBER(SEARCH(Ангилал!$J$5:$J$16,$G38&" "&$D38&" "&$E38))+ISNUMBER(SEARCH(Ангилал!$K$5:$K$16,$G38&" "&$D38&" "&$E38))>0,0),0)),"Ерөнхий нийт"))} -> Хүүхэд | R38: =IF($G38="","",IF($Q38<>"",$Q38,$P38)) -> Хүүхэд
A39: 27 | B39: 2026.05.18 | C39: 2024 | D39: Хүүхдийнх нь дэргэд ээжийг нь хүчиндсэн этгээдүүдийн хэргийг Булганыхан шийдвэрлэж чадахгүй 2 дахь жилтэйгээ золгож байна | E39: Ноцтой нь, хэрэг гараад 1 жид 9 сарын хугацаа өнгөрч байхад хэрэг эцэслэгдээгүй, хохирогч бүсгүй нэр төр, сэтгэл санаа, эрүүл мэндээрээ хохирсон хэвээр байна. Уг хэрэгт мөрдөгч, прокурорууд хэд, хэд солигджээ. | F39: Булган аймаг 3 булаг сум | H39: Сэжигтнүүд Гурванбулаг сумын харьяатэрхэлсэн тодорхой ажилгүй 30 настай Б.Одонбат, 20 настай Б.Бат-Эрдэнэ | I39: Шүүхээс хэрэгтнүүдийг баривчлах захирамжийг 2026.02 дугаар сард гаргаж, Б.Одонбатыг баривчилсан бол Б.Бат-Эрдэнэ нь Япон руу гарч сураггүй болжээ. Хуулийнхан Интерполоор эрэн сурвалжилна гэж мэдэгдэж байсан ч өнөөдөр хүртэл хүнд гэмт хэрэгт сэжиглэгдэж байгаа этгээдийн сургийг гаргаж чадаагүй байна. Уг хэрэгт холбогдох шүүх хурал 2026.05.27-нд болохоор товлосон. | J39: Tsahiur.mn, сэтгүүлч Б.Энхзаяа, 2026-05-18 | K39: https://tsahiur.mn/n/s/27019 | M39: {=IF($G39="","",IFERROR(INDEX(Ангилал!$A$5:$A$22,MATCH(TRUE(),INDEX(ISNUMBER(SEARCH(Ангилал!$B$5:$B$22,$G39&" "&$D39))+ISNUMBER(SEARCH(Ангилал!$C$5:$C$22,$G39&" "&$D39))+IF(Ангилал!$D$5:$D$22="",0,ISNUMBER(SEARCH(Ангилал!$D$5:$D$22,$G39&" "&$D39)))+IF(Ангилал!$E$5:$E$22="",0,ISNUMBER(SEARCH(Ангилал!$E$5:$E$22,$G39&" "&$D39)))>0,0),0)),"Бусад"))} | O39: =IF($G39="","",IF($N39<>"",$N39,$M39)) | P39: {=IF($G39="","",IFERROR(INDEX(Ангилал!$G$5:$G$16,MATCH(TRUE(),INDEX(ISNUMBER(SEARCH(Ангилал!$H$5:$H$16,$G39&" "&$D39&" "&$E39))+ISNUMBER(SEARCH(Ангилал!$I$5:$I$16,$G39&" "&$D39&" "&$E39))+ISNUMBER(SEARCH(Ангилал!$J$5:$J$16,$G39&" "&$D39&" "&$E39))+ISNUMBER(SEARCH(Ангилал!$K$5:$K$16,$G39&" "&$D39&" "&$E39))>0,0),0)),"Ерөнхий нийт"))} | R39: =IF($G39="","",IF($Q39<>"",$Q39,$P39))
A40: 28 | B40: 2026.05.19 | C40: 2026-05-18 | D40: Хоолны газрын хана нурааж байсан 15 настай хүүхэд амиа алджээ | E40: Нийслэлийн Баянгол дүүргийн III, IV хороололд байрлах “Кимбаб Чонгүг” сүлжээ хоолны газрын дотор заслын ажилд хичээлийн цагаар, хөдөлмөрийн аюулгүй байдал хангагдаагүй нөхцөлд оролцуулсан, ЕБС-ийн 15 настай Т гэгч сурагч хана нурааж байх үед түүнд дарагдан амь насаа алдсан. Урьдчилсан байдлаар насанд хүрээгүй хүүхдээр хууль бусаар хөдөлмөр эрхлүүлсэн, ажлын байрны аюулгүй байдал зөрчигдсөн нь тогтоогджээ. | F40: Баянгол дүүрэг, III, IV хороолол | G40: Амьд явах эрх; Хүүхдийн эрх (хамгаалуулах, хөдөлмөрийн мөлжлөгөөс ангид байх); Боловсрол эзэмших эрх; Хөдөлмөрийн аюулгүй, эрүүл ахуйн шаардлагад нийцсэн нөхцөлд ажиллах эрх | H40: “Кимбаб Чонгүг” сүлжээ хоолны газрын эзэн/ажил олгогч, Засварын ажил гүйцэтгэгч этгээд; Хүүхдийн асран хамгаалагч | I40: Баянгол дүүргийн цагдаагийн хэлтэс эрүүгийн хэрэг үүсгэн шалгаж эхэлсэн. Хүүхдээр хууль бусаар хөдөлмөр эрхлүүлсэн, хөдөлмөрийн аюулгүй байдал алдагдсан эсэхэд мөрдөн шалгах ажиллагаа үргэлжилж байна. | J40: News.MN, сэтгүүлч А.Тамир, 2026-05-19 | K40: https://news.mn/r/2867418/ | M40: {=IF($G40="","",IFERROR(INDEX(Ангилал!$A$5:$A$22,MATCH(TRUE(),INDEX(ISNUMBER(SEARCH(Ангилал!$B$5:$B$22,$G40&" "&$D40))+ISNUMBER(SEARCH(Ангилал!$C$5:$C$22,$G40&" "&$D40))+IF(Ангилал!$D$5:$D$22="",0,ISNUMBER(SEARCH(Ангилал!$D$5:$D$22,$G40&" "&$D40)))+IF(Ангилал!$E$5:$E$22="",0,ISNUMBER(SEARCH(Ангилал!$E$5:$E$22,$G40&" "&$D40)))>0,0),0)),"Бусад"))} -> Хүүхдийн эрх | O40: =IF($G40="","",IF($N40<>"",$N40,$M40)) -> Хүүхдийн эрх | P40: {=IF($G40="","",IFERROR(INDEX(Ангилал!$G$5:$G$16,MATCH(TRUE(),INDEX(ISNUMBER(SEARCH(Ангилал!$H$5:$H$16,$G40&" "&$D40&" "&$E40))+ISNUMBER(SEARCH(Ангилал!$I$5:$I$16,$G40&" "&$D40&" "&$E40))+ISNUMBER(SEARCH(Ангилал!$J$5:$J$16,$G40&" "&$D40&" "&$E40))+ISNUMBER(SEARCH(Ангилал!$K$5:$K$16,$G40&" "&$D40&" "&$E40))>0,0),0)),"Ерөнхий нийт"))} -> Хүүхэд | R40: =IF($G40="","",IF($Q40<>"",$Q40,$P40)) -> Хүүхэд
A41: 29 | B41: 2026.05.19 | C41: 2026-04-10-нээс 2026-05-19 | D41: Жолооны үнэмлэхгүй сурагчдын 262 цахилгаан мотоциклыг журамлажээ | E41: Тээврийн цагдаагийн алба болон Урьдчилан сэргийлэх хэлтсийн мэдээлснээр, дөрөвдүгээр сарын 10-наас хойш Улаанбаатар хотод 16 нас хүрээгүй хүүхдүүд цахилгаан скүүтер, мопед жолоодсон 160 гаруй зөрчил илрүүлж, хөдөлгөөнд оролцсон ЕБС-ийн сурагчдын 262 цахилгаан мотоциклыг түр саатуулан журамласан. Эцэг эх, асран хамгаалагч нарт нь 440 торгуулийн арга хэмжээ тооцсон. Энэ хугацаанд хоёр дугуйт тээврийн хэрэгсэлтэй холбоотой 78 осол бүртгэгджээ. | F41: Улаанбаатар хот (нийслэлийн нийт нутаг дэвсгэр) | G41: Хүүхдийн амьд явах, эрүүл, аюулгүй орчинд өсөх эрх; Хүүхдийг осол, эрсдэлээс хамгаалуулах эрх; Хөдөлгөөний аюулгүй байдлаар хангагдах эрх | H41: Эцэг эх, асран хамгаалагч (хүүхдэд цахилгаан скүүтер, мопед унуулсан); Скүүтер түрээслүүлэх үйлчилгээ эрхлэх аж ахуйн нэгжүүд (E-Mongolia системд бүртгүүлээгүй, эвдрэлтэй техник хэрэгсэл нийлүүлсэн) | I41: Тээврийн цагдаагийн алба түрээсийн долоон ААН-д долоон албан мэдэгдэл хүргүүлж, хоёр ААН-д Зөрчлийн тухай хуулиар хариуцлага тооцох албан мэдэгдэл өгсөн. Нийслэлийн 317 ерөнхий боловсролын сургуульд зөвлөмж, аудио шторк хүргүүлж, 150 нийтийн цагдаа гудамж замд ажиллаж байна. Сургуулийн орчинд 30 цагдаагийн алба хаагч эргүүлийн үүрэг гүйцэтгэж байна. | J41: News.MN, сэтгүүлч А.Тамир, 2026-05-19 | K41: https://news.mn/r/2867369/ | M41: {=IF($G41="","",IFERROR(INDEX(Ангилал!$A$5:$A$22,MATCH(TRUE(),INDEX(ISNUMBER(SEARCH(Ангилал!$B$5:$B$22,$G41&" "&$D41))+ISNUMBER(SEARCH(Ангилал!$C$5:$C$22,$G41&" "&$D41))+IF(Ангилал!$D$5:$D$22="",0,ISNUMBER(SEARCH(Ангилал!$D$5:$D$22,$G41&" "&$D41)))+IF(Ангилал!$E$5:$E$22="",0,ISNUMBER(SEARCH(Ангилал!$E$5:$E$22,$G41&" "&$D41)))>0,0),0)),"Бусад"))} -> Хүүхдийн эрх | O41: =IF($G41="","",IF($N41<>"",$N41,$M41)) -> Хүүхдийн эрх | P41: {=IF($G41="","",IFERROR(INDEX(Ангилал!$G$5:$G$16,MATCH(TRUE(),INDEX(ISNUMBER(SEARCH(Ангилал!$H$5:$H$16,$G41&" "&$D41&" "&$E41))+ISNUMBER(SEARCH(Ангилал!$I$5:$I$16,$G41&" "&$D41&" "&$E41))+ISNUMBER(SEARCH(Ангилал!$J$5:$J$16,$G41&" "&$D41&" "&$E41))+ISNUMBER(SEARCH(Ангилал!$K$5:$K$16,$G41&" "&$D41&" "&$E41))>0,0),0)),"Ерөнхий нийт"))} -> Хүүхэд | R41: =IF($G41="","",IF($Q41<>"",$Q41,$P41)) -> Хүүхэд
A42: 30 | B42: 2026.05.20 | D42: УИХ-ын гишүүн У.Отгонбаяр, О.Алтангэрэл, Н.Батсүмбэрэл, Ж.Бат-Эрдэнэ, Ш.Бямбасүрэн, М.Ганхүлэг, Ц.Даваасүрэн, Х.Жангабыл нарын гишүүд хаврын морин уралдааныг аймаг, нийслэлд жил бүр зохион байгуулах хуулийн төсөл санаачилжээ. | E42: УИХ-ын гишүүн У.Отгонбаяр, О.Алтангэрэл, Н.Батсүмбэрэл, Ж.Бат-Эрдэнэ, Ш.Бямбасүрэн, М.Ганхүлэг, Ц.Даваасүрэн, Х.Жангабыл нарын гишүүд хаврын морин уралдааныг аймаг, нийслэлд жил бүр зохион байгуулах хуулийн төсөл санаачилжээ. | G42: Хүүхдийн амьд явах, эрүүл, аюулгүй орчинд өсөх эрх; Хүүхдийг осол, эрсдэлээс хамгаалуулах эрх; Хөдөлгөөний аюулгүй байдлаар хангагдах эрх | H42: УИХ-ын гишүүн У.Отгонбаяр, О.Алтангэрэл, Н.Батсүмбэрэл, Ж.Бат-Эрдэнэ, Ш.Бямбасүрэн, М.Ганхүлэг, Ц.Даваасүрэн, Х.Жангабыл | J42: facebook | K42: https://www.facebook.com/story.php?story_fbid=1305486858425685&id=100068931495575&rdid=GVLdPVqWwb5hxmeS# | M42: {=IF($G42="","",IFERROR(INDEX(Ангилал!$A$5:$A$22,MATCH(TRUE(),INDEX(ISNUMBER(SEARCH(Ангилал!$B$5:$B$22,$G42&" "&$D42))+ISNUMBER(SEARCH(Ангилал!$C$5:$C$22,$G42&" "&$D42))+IF(Ангилал!$D$5:$D$22="",0,ISNUMBER(SEARCH(Ангилал!$D$5:$D$22,$G42&" "&$D42)))+IF(Ангилал!$E$5:$E$22="",0,ISNUMBER(SEARCH(Ангилал!$E$5:$E$22,$G42&" "&$D42)))>0,0),0)),"Бусад"))} -> Хүүхдийн эрх | O42: =IF($G42="","",IF($N42<>"",$N42,$M42)) -> Хүүхдийн эрх | P42: {=IF($G42="","",IFERROR(INDEX(Ангилал!$G$5:$G$16,MATCH(TRUE(),INDEX(ISNUMBER(SEARCH(Ангилал!$H$5:$H$16,$G42&" "&$D42&" "&$E42))+ISNUMBER(SEARCH(Ангилал!$I$5:$I$16,$G42&" "&$D42&" "&$E42))+ISNUMBER(SEARCH(Ангилал!$J$5:$J$16,$G42&" "&$D42&" "&$E42))+ISNUMBER(SEARCH(Ангилал!$K$5:$K$16,$G42&" "&$D42&" "&$E42))>0,0),0)),"Ерөнхий нийт"))} -> Хүүхэд | R42: =IF($G42="","",IF($Q42<>"",$Q42,$P42)) -> Хүүхэд
A43: 31 | B43: 2026.05.20 | D43: БНСУ-д ажиллахаар явсан монгол эмэгтэй ажлын байрны дарамтанд өртөж, холбогдох хүмүүст энэ талаараа хэлсээр байсан ч тусламж авч чадаагүй. Эцэст нь Солонгосын гудамжинд галзуурсан байдалтай нүцгэн явж байхыг нь цагдаа нар олж, Монгол руу албадан буцаажээ | F43: БНСУ | G43: Хөдөлмөрлөх таатай, аюулгүй нөхцөл бүрдүүлэх эрх, Эрүү шүүлт, хүнлэг бус, нэр төрийг доромжилсон харьцаанаас ангид байх эрх, Эрүүл мэндээ хамгаалуулах эрх, ялангуяа сэтгэцийн эрүүл мэнд, Консулын туслалцаа авах эрх | H43: Могнгол Улсаас БНСУ-д суух элчин сайдын яам, ажил олгогч | J43: Tsahiur.mn | K43: https://www.facebook.com/Tsahiur.mn/videos/%D0%B0%D1%81%D1%83%D1%83%D0%B4%D0%BB%D1%8B%D0%BD-%D0%BC%D3%A9%D1%80%D3%A9%D3%A9%D1%80-%D0%B1%D0%BD%D1%81%D1%83-%D0%B4-%D0%B0%D0%B6%D0%B8%D0%BB%D0%BB%D0%B0%D1%85%D0%B0%D0%B0%D1%80-%D1%8F%D0%B2%D1%81%D0%B0%D0%BD-%D0%BC%D0%BE%D0%BD%D0%B3%D0%BE%D0%BB-%D1%8D%D0%BC%D1%8D%D0%B3%D1%82%D1%8D%D0%B9-%D0%B0%D0%B6%D0%BB%D1%8B%D0%BD-%D0%B1%D0%B0%D0%B9%D1%80%D0%BD%D1%8B-%D0%B4%D0%B0%D1%80%D0%B0%D0%BC%D1%82%D0%B0%D0%BD%D0%B4-%D3%A9%D1%80/1535035791631959/?mibextid=wwXIfr&rdid=r47l6Zb4Hmu8qgJJ | M43: {=IF($G43="","",IFERROR(INDEX(Ангилал!$A$5:$A$22,MATCH(TRUE(),INDEX(ISNUMBER(SEARCH(Ангилал!$B$5:$B$22,$G43&" "&$D43))+ISNUMBER(SEARCH(Ангилал!$C$5:$C$22,$G43&" "&$D43))+IF(Ангилал!$D$5:$D$22="",0,ISNUMBER(SEARCH(Ангилал!$D$5:$D$22,$G43&" "&$D43)))+IF(Ангилал!$E$5:$E$22="",0,ISNUMBER(SEARCH(Ангилал!$E$5:$E$22,$G43&" "&$D43)))>0,0),0)),"Бусад"))} -> Эрүүдэн шүүлт, хүнлэг бус харьцаа | O43: =IF($G43="","",IF($N43<>"",$N43,$M43)) -> Эрүүдэн шүүлт, хүнлэг бус харьцаа | P43: {=IF($G43="","",IFERROR(INDEX(Ангилал!$G$5:$G$16,MATCH(TRUE(),INDEX(ISNUMBER(SEARCH(Ангилал!$H$5:$H$16,$G43&" "&$D43&" "&$E43))+ISNUMBER(SEARCH(Ангилал!$I$5:$I$16,$G43&" "&$D43&" "&$E43))+ISNUMBER(SEARCH(Ангилал!$J$5:$J$16,$G43&" "&$D43&" "&$E43))+ISNUMBER(SEARCH(Ангилал!$K$5:$K$16,$G43&" "&$D43&" "&$E43))>0,0),0)),"Ерөнхий нийт"))} -> Эмэгтэйчүүд | R43: =IF($G43="","",IF($Q43<>"",$Q43,$P43)) -> Эмэгтэйчүүд
A44: 32 | B44: 2026.05.20 | C44: 2026-05-19 | D44: 15 настай хүү цооногт унасан гөлөг аврах гэж байгаад амиа алджээ | E44: Хүүгийн ээж: Хүү минь 08:00 цагт хичээлдээ очоод, 10:20 цагт завсарласан байна лээ. Энэ цагийнх нь завсарлагаа 10-20 минут үргэлжилдэг, их завсарлагаа байдаг юм уу даа. Тэгээд нөгөө ангийнхаа найзалдаг хүүтэй сургуулиасаа урагш 500 метр орчим гүйсэн. Тэнд нь цэвэр, бохир усны гэмээр шугам хоолой, далан, цооног байдаг. Ямар ч хашаа хороо, камер, орж болохгүй гэсэн тэмдэглэгээ байхгүй. Хүү минь найзтайгаа гүйгээд очиход цооногт нь жижигхэн нохойн гөлөг живэх гээд тарчилж байсан юм шиг байна лээ. Тэгээд жижигхэн гөлгийг аврахын тулд өмд, гутлаа тайлаад, утсаа хажууд нь тавиад, цооног руу орсон байгаа юм. Магадгүй сургуулийнх нь тэндээс нохойн гөлөгний гасалж байгаа сонсогдсон байх. Эсвэл хүүхэд л юм болохоор тэнд юу байгааг сонирхоод очсон байж мэдэх юм. Найз нь үлдээд, хүү минь цооног руу орсон ч хөлгүй учраас живчихсэн гэсэн. Хүүг минь гарч ирэхгүй болохоор нь найз нь хар хурдаараа гүйгээд, аврах ангийнхнаас тусламж гуйсан гэсэн. Аврагчдыг очих үед миний хүү хэдийн амьсгал хураачихсан байсан гэсэн. | G44: Хүүхдийн амьд явах, эрүүл, аюулгүй орчинд өсөх эрх, Хүүхдийг осол, эрсдэлээс хамгаалуулах эрх, Хүүхдийн тэргүүн ач холбогдол ба аюулгүй орчинд хамгаалуулах эрх, Сурч боловсрох эрхийн нэг бүрэлдэхүүн болох сургуулийн хариуцлага, хичээлийн цаг дахь хүүхдийн аюулгүй байдлыг хангах үүрэг | J44: facebook | K44: https://www.facebook.com/100063933908097/posts/1485016500306133/?mibextid=wwXIfr&rdid=ZOSUnUcvvLd0t953# | M44: {=IF($G44="","",IFERROR(INDEX(Ангилал!$A$5:$A$22,MATCH(TRUE(),INDEX(ISNUMBER(SEARCH(Ангилал!$B$5:$B$22,$G44&" "&$D44))+ISNUMBER(SEARCH(Ангилал!$C$5:$C$22,$G44&" "&$D44))+IF(Ангилал!$D$5:$D$22="",0,ISNUMBER(SEARCH(Ангилал!$D$5:$D$22,$G44&" "&$D44)))+IF(Ангилал!$E$5:$E$22="",0,ISNUMBER(SEARCH(Ангилал!$E$5:$E$22,$G44&" "&$D44)))>0,0),0)),"Бусад"))} -> Хүүхдийн эрх | O44: =IF($G44="","",IF($N44<>"",$N44,$M44)) -> Хүүхдийн эрх | P44: {=IF($G44="","",IFERROR(INDEX(Ангилал!$G$5:$G$16,MATCH(TRUE(),INDEX(ISNUMBER(SEARCH(Ангилал!$H$5:$H$16,$G44&" "&$D44&" "&$E44))+ISNUMBER(SEARCH(Ангилал!$I$5:$I$16,$G44&" "&$D44&" "&$E44))+ISNUMBER(SEARCH(Ангилал!$J$5:$J$16,$G44&" "&$D44&" "&$E44))+ISNUMBER(SEARCH(Ангилал!$K$5:$K$16,$G44&" "&$D44&" "&$E44))>0,0),0)),"Ерөнхий нийт"))} -> Хүүхэд | R44: =IF($G44="","",IF($Q44<>"",$Q44,$P44)) -> Хүүхэд
A45: 33 | B45: 2026.05.21 | D45: "Дүү минь бяртай, том биетэй. Ганц хүн аминд нь хүрч чадахгүй, бүлэглэл байсан уу гэдгийг шалгаж байгаа" | E45: Баянхонгор аймаг дахь Зэвсэгт хүчний 339 дүгээр ангид хугацаат цэргийн албан хаагч зодуулсан байдалтай амиа алдсан хэрэг гараад байгааг бид өмнө нь мэдээлсэн. Тэрээр 2025 намар цэрэгт татагдсан бөгөөд камергүй өрөөнд авч орон зодсон, үүнийг харсан цэргүүд мэдүүлэг өгсөн гэгдэж байгаа юм. | F45: Баянхонгор аймаг, Зэвсэгт хүчний 339 дүгээр анги | G45: Эрүү шүүлт, хүнлэг бус, хэрцгий харьцаанаас ангид байх эрх, Амьд явах, биеийн халдашгүй байдалд эзэн байх эрх, Эрүүл мэндээ хамгаалуулах, эмнэлгийн тусламж авах эрх, Сэтгэл зүйн хүчирхийлэлд өртөхгүй байх эрх | H45: Зэвсэгт хүчний 339 дүгээр ангийн дарга, салаан дарга гэх мэт | J45: Tsahiur.mn, сэтгүүлч Б.Энхзаяа, 2026-05-21 | K45: https://tsahiur.mn/n/s/27043?fbclid=IwdGRjcAR7VfJleHRuA2FlbQIxMQBzcnRjBmFwcF9pZAo2NjI4NTY4Mzc5AAEe8xCjz4Kz2JBAfrN0zqy8iewvRQTictPZTj4VKvaP-sjeV06lijcuf3ic4PQ_aem_lNZLVDJpjS7KDclMwFuA1A | M45: {=IF($G45="","",IFERROR(INDEX(Ангилал!$A$5:$A$22,MATCH(TRUE(),INDEX(ISNUMBER(SEARCH(Ангилал!$B$5:$B$22,$G45&" "&$D45))+ISNUMBER(SEARCH(Ангилал!$C$5:$C$22,$G45&" "&$D45))+IF(Ангилал!$D$5:$D$22="",0,ISNUMBER(SEARCH(Ангилал!$D$5:$D$22,$G45&" "&$D45)))+IF(Ангилал!$E$5:$E$22="",0,ISNUMBER(SEARCH(Ангилал!$E$5:$E$22,$G45&" "&$D45)))>0,0),0)),"Бусад"))} -> Эрүүдэн шүүлт, хүнлэг бус харьцаа | O45: =IF($G45="","",IF($N45<>"",$N45,$M45)) -> Эрүүдэн шүүлт, хүнлэг бус харьцаа | P45: {=IF($G45="","",IFERROR(INDEX(Ангилал!$G$5:$G$16,MATCH(TRUE(),INDEX(ISNUMBER(SEARCH(Ангилал!$H$5:$H$16,$G45&" "&$D45&" "&$E45))+ISNUMBER(SEARCH(Ангилал!$I$5:$I$16,$G45&" "&$D45&" "&$E45))+ISNUMBER(SEARCH(Ангилал!$J$5:$J$16,$G45&" "&$D45&" "&$E45))+ISNUMBER(SEARCH(Ангилал!$K$5:$K$16,$G45&" "&$D45&" "&$E45))>0,0),0)),"Ерөнхий нийт"))} -> Ерөнхий нийт | R45: =IF($G45="","",IF($Q45<>"",$Q45,$P45)) -> Ерөнхий нийт
A46: 34 | B46: 2026.05.21 | D46: Цас их орсон Увс аймгийн Түргэн суманд нялх хүүхэдтэй, жирэмсэн эмчийг дуудлагад явган явуулсан хэмээн цахим сүлжээнд нийтэлсэн иргэнтэй холбогдож энэ талаар тодрууллаа | E46: Н.Мягмарбат “Дуудлагад явсан эмч миний дүү. Жирэмсэн тухайн өдөр хүүхдийг нь харах хүнгүй байсан байна лээ. Манай суманд гурван өдөр цас орсон. Явган битгий хэл машинтай явахад ч хүндрэлтэй байсан. Над руу залгаад ‘Алхаж чадахгүй байна, ирээд аваач’ гэхээр нь би очсон. Эмнэлэгт нь хүргэж өгөхөд түргэн тусламжийн хоёр машин хашаан дотор байсан. Эмнэлгийн даргатай уулзахад ‘Дотоод ажлын зохион байгуулалт, буруу зөрүү ойлголцол гарсан байна’ гэж хэлсэн. Ямар ч асуудал байлаа гэсэн жирэмсэн хүнийг түргэн тусламжийн машин байсаар байхад явган явуулсанд нь бухимдаж байна. Өнөөдөр Эрүүл мэндийн газраас манай суманд ирж ажиллана гэсэн” хэмээлээ. | F46: Увс аймаг, Түргэн сум | G46: Жирэмсэн ажилтны тусгай хамгаалал бүхий хөдөлмөрлөх аюулгүй нөхцөлийн эрх, Эх, хүүхдийг тусгайлан хамгаалах төрийн үүрэг, Жендэрт суурилсан болон жирэмсний шинж байдлаар ялгаварлан гадуурхалтад өртөхгүй байх эрх, Амь нас, эрүүл мэнд, биеийн халдашгүй байдлын эрх, нөхөн үржихүйн эрүүл мэндээ хамгаалуулах эрх | H46: Увс аймаг, Түргэн сумын эмнэлэгийн удирдлага | J46: Tsahiur.mn | K46: https://www.facebook.com/story.php?story_fbid=1485197123621404&id=100063933908097&post_id=100063933908097_1485197123621404&rdid=ezRetvfLchdAzBgv# | M46: {=IF($G46="","",IFERROR(INDEX(Ангилал!$A$5:$A$22,MATCH(TRUE(),INDEX(ISNUMBER(SEARCH(Ангилал!$B$5:$B$22,$G46&" "&$D46))+ISNUMBER(SEARCH(Ангилал!$C$5:$C$22,$G46&" "&$D46))+IF(Ангилал!$D$5:$D$22="",0,ISNUMBER(SEARCH(Ангилал!$D$5:$D$22,$G46&" "&$D46)))+IF(Ангилал!$E$5:$E$22="",0,ISNUMBER(SEARCH(Ангилал!$E$5:$E$22,$G46&" "&$D46)))>0,0),0)),"Бусад"))} -> Хүүхдийн эрх | O46: =IF($G46="","",IF($N46<>"",$N46,$M46)) -> Хүүхдийн эрх | P46: {=IF($G46="","",IFERROR(INDEX(Ангилал!$G$5:$G$16,MATCH(TRUE(),INDEX(ISNUMBER(SEARCH(Ангилал!$H$5:$H$16,$G46&" "&$D46&" "&$E46))+ISNUMBER(SEARCH(Ангилал!$I$5:$I$16,$G46&" "&$D46&" "&$E46))+ISNUMBER(SEARCH(Ангилал!$J$5:$J$16,$G46&" "&$D46&" "&$E46))+ISNUMBER(SEARCH(Ангилал!$K$5:$K$16,$G46&" "&$D46&" "&$E46))>0,0),0)),"Ерөнхий нийт"))} -> Хүүхэд | R46: =IF($G46="","",IF($Q46<>"",$Q46,$P46)) -> Хүүхэд
A47: 2026.05.25-29 | M47: {=IF($G47="","",IFERROR(INDEX(Ангилал!$A$5:$A$22,MATCH(TRUE(),INDEX(ISNUMBER(SEARCH(Ангилал!$B$5:$B$22,$G47&" "&$D47))+ISNUMBER(SEARCH(Ангилал!$C$5:$C$22,$G47&" "&$D47))+IF(Ангилал!$D$5:$D$22="",0,ISNUMBER(SEARCH(Ангилал!$D$5:$D$22,$G47&" "&$D47)))+IF(Ангилал!$E$5:$E$22="",0,ISNUMBER(SEARCH(Ангилал!$E$5:$E$22,$G47&" "&$D47)))>0,0),0)),"Бусад"))} | O47: =IF($G47="","",IF($N47<>"",$N47,$M47)) | P47: {=IF($G47="","",IFERROR(INDEX(Ангилал!$G$5:$G$16,MATCH(TRUE(),INDEX(ISNUMBER(SEARCH(Ангилал!$H$5:$H$16,$G47&" "&$D47&" "&$E47))+ISNUMBER(SEARCH(Ангилал!$I$5:$I$16,$G47&" "&$D47&" "&$E47))+ISNUMBER(SEARCH(Ангилал!$J$5:$J$16,$G47&" "&$D47&" "&$E47))+ISNUMBER(SEARCH(Ангилал!$K$5:$K$16,$G47&" "&$D47&" "&$E47))>0,0),0)),"Ерөнхий нийт"))} | R47: =IF($G47="","",IF($Q47<>"",$Q47,$P47))
A48: 35 | B48: 2026.05.26 | D48: Асуудлын мөрөөр | E48: Оюутан охиныг массажистаар ажилд аваад 3 хоногийн хугацаанд 10 гаруй хүнтэй бэлгийн харилцаанд оруулж, тэндээс нь гаргахгүй хорьж, зодож гэмтээсэн үйлдэл гарлаа. Энэ нь "биеэ үнэлэлтийг зохион байгуулсан" гэмт хэргийн шинжтэй байна. | F48: Улаанбаатар хот | G48: Хүний халдашгүй, чөлөөтэй байх эрх, Хөдөлмөрлөх эрх, Хүний нэр төр, алдар хүндийн эрх, Эрүүдэн шүүх, хүнлэг бус харьцаанаас ангид байх эрх | J48: tsahiur.news | K48: https://shorturl.at/RyTTF | M48: {=IF($G48="","",IFERROR(INDEX(Ангилал!$A$5:$A$22,MATCH(TRUE(),INDEX(ISNUMBER(SEARCH(Ангилал!$B$5:$B$22,$G48&" "&$D48))+ISNUMBER(SEARCH(Ангилал!$C$5:$C$22,$G48&" "&$D48))+IF(Ангилал!$D$5:$D$22="",0,ISNUMBER(SEARCH(Ангилал!$D$5:$D$22,$G48&" "&$D48)))+IF(Ангилал!$E$5:$E$22="",0,ISNUMBER(SEARCH(Ангилал!$E$5:$E$22,$G48&" "&$D48)))>0,0),0)),"Бусад"))} -> Эрүүдэн шүүлт, хүнлэг бус харьцаа | O48: =IF($G48="","",IF($N48<>"",$N48,$M48)) -> Эрүүдэн шүүлт, хүнлэг бус харьцаа | P48: {=IF($G48="","",IFERROR(INDEX(Ангилал!$G$5:$G$16,MATCH(TRUE(),INDEX(ISNUMBER(SEARCH(Ангилал!$H$5:$H$16,$G48&" "&$D48&" "&$E48))+ISNUMBER(SEARCH(Ангилал!$I$5:$I$16,$G48&" "&$D48&" "&$E48))+ISNUMBER(SEARCH(Ангилал!$J$5:$J$16,$G48&" "&$D48&" "&$E48))+ISNUMBER(SEARCH(Ангилал!$K$5:$K$16,$G48&" "&$D48&" "&$E48))>0,0),0)),"Ерөнхий нийт"))} -> Ерөнхий нийт | R48: =IF($G48="","",IF($Q48<>"",$Q48,$P48)) -> Ерөнхий нийт
A49: 36 | B49: 2026.05.27 | C49: 202-05-26 | D49: 15 настай таван сурагч автомашин жолоодон осолдож, хоёр нь амиа алджээ | E49: Дархан-Уул аймгийн нутаг дэвсгэрт энэ 26-ны өдөр 15 настай таван сурагч эцэг эхийн зөвшөөрөлгүй тээврийн хэрэгсэл жолоодож осол гаргажээ. Ослын улмаас нэг сурагч газар дээрээ амиа алдсан бол, нэг нь эмнэлэгт хүргэгдсэнийхээ дараа нас барсан байна. | F49: Дархан-Уул аймаг | G49: Амьд явах эрх, Хүүхдийн хамгаалуулах эрх, Хүүхдийн дээд ашиг сонирхлын зарчим, | I49: Одоогийн байдлаар ослын шалтгаан нөхцөлийг тогтоохоор цагдаагийн байгууллагаас мөрдөн шалгах ажиллагаа явуулж байна. | J49: eguur.mn | K49: https://eguur.mn/676309/ | M49: {=IF($G49="","",IFERROR(INDEX(Ангилал!$A$5:$A$22,MATCH(TRUE(),INDEX(ISNUMBER(SEARCH(Ангилал!$B$5:$B$22,$G49&" "&$D49))+ISNUMBER(SEARCH(Ангилал!$C$5:$C$22,$G49&" "&$D49))+IF(Ангилал!$D$5:$D$22="",0,ISNUMBER(SEARCH(Ангилал!$D$5:$D$22,$G49&" "&$D49)))+IF(Ангилал!$E$5:$E$22="",0,ISNUMBER(SEARCH(Ангилал!$E$5:$E$22,$G49&" "&$D49)))>0,0),0)),"Бусад"))} -> Хүүхдийн эрх | O49: =IF($G49="","",IF($N49<>"",$N49,$M49)) -> Хүүхдийн эрх | P49: {=IF($G49="","",IFERROR(INDEX(Ангилал!$G$5:$G$16,MATCH(TRUE(),INDEX(ISNUMBER(SEARCH(Ангилал!$H$5:$H$16,$G49&" "&$D49&" "&$E49))+ISNUMBER(SEARCH(Ангилал!$I$5:$I$16,$G49&" "&$D49&" "&$E49))+ISNUMBER(SEARCH(Ангилал!$J$5:$J$16,$G49&" "&$D49&" "&$E49))+ISNUMBER(SEARCH(Ангилал!$K$5:$K$16,$G49&" "&$D49&" "&$E49))>0,0),0)),"Ерөнхий нийт"))} -> Хүүхэд | R49: =IF($G49="","",IF($Q49<>"",$Q49,$P49)) -> Хүүхэд
A50: 37 | B50: 2026.05.28 | C50: 2026-05-27 | D50: А.Дашням: 30 метрийн гүн нүхэнд унасан гурван настай хүүхдийг аврах ажиллагаа үргэлжилж байна | E50: Өчигдөр 12:40 цагт Төв аймгийн Заамар сумын Хайлааст гуравдугаар багийн Ар наймган гэх газарт гурван настай эмэгтэй хүүхэд гүний цооногт унасан гэх мэдээлэл Төв аймгийн онцгой байдлын газарт ирсэн. Алба хаагчдыг очиход 30-50 метрийн гүн хуучин өрмийн цооногт гурван настай хүүхэд санамсаргүй байдлаар унасан байсан. Аврах баг бүрэлдэхүүн могойн нүд камер ашиглаж үзэхэд хөлөөрөө ороод гацсан байдалтай хариу өгөөгүй. Тухайн үед амьсгалж байсан чимээ гарч байсан. Улмаар аврах баг тактикийн түвшинд бугуйлдаж гаргах ажлыг зохион байгуулж үзсэн боловч хөшөөд гарах боломжгүй байсан. Тиймээс дөрвөн метрийн зайтай шатлан ухах ажлыг өчигдрөөс хойш эхлүүлээд байна. | F50: Төв аймгийн Заамар сумын Хайлааст 3-р багийн Ар наймган гэх газарт | G50: Амьд явах эрх, Хүүхдийн хамгаалуулах эрх, Хүүхдийн дээд ашиг сонирхлын зарчим, Аюулгүй орчинд амьдрах эрх | H50: Цооног эзэмшигч/ашиглагч аж ахуйн нэгж,хяналт тавих үүрэгтэй орон нутгийн захиргаа | I50: Онцгой байдлын газар, цагдаа, уул уурхайн яам, уурхай зэргээс нийт 100 орчим хүн хүч гарч, хүнд зориулалтын 20 гаруй техник хэрэгсэлтэйгээр ажиллаж байна. | J50: ikon.mn П.Сайнжаргал 2026.05.28 | K50: https://ikon.mn/n/3nun | M50: {=IF($G50="","",IFERROR(INDEX(Ангилал!$A$5:$A$22,MATCH(TRUE(),INDEX(ISNUMBER(SEARCH(Ангилал!$B$5:$B$22,$G50&" "&$D50))+ISNUMBER(SEARCH(Ангилал!$C$5:$C$22,$G50&" "&$D50))+IF(Ангилал!$D$5:$D$22="",0,ISNUMBER(SEARCH(Ангилал!$D$5:$D$22,$G50&" "&$D50)))+IF(Ангилал!$E$5:$E$22="",0,ISNUMBER(SEARCH(Ангилал!$E$5:$E$22,$G50&" "&$D50)))>0,0),0)),"Бусад"))} -> Хүүхдийн эрх | O50: =IF($G50="","",IF($N50<>"",$N50,$M50)) -> Хүүхдийн эрх | P50: {=IF($G50="","",IFERROR(INDEX(Ангилал!$G$5:$G$16,MATCH(TRUE(),INDEX(ISNUMBER(SEARCH(Ангилал!$H$5:$H$16,$G50&" "&$D50&" "&$E50))+ISNUMBER(SEARCH(Ангилал!$I$5:$I$16,$G50&" "&$D50&" "&$E50))+ISNUMBER(SEARCH(Ангилал!$J$5:$J$16,$G50&" "&$D50&" "&$E50))+ISNUMBER(SEARCH(Ангилал!$K$5:$K$16,$G50&" "&$D50&" "&$E50))>0,0),0)),"Ерөнхий нийт"))} -> Хүүхэд | R50: =IF($G50="","",IF($Q50<>"",$Q50,$P50)) -> Хүүхэд
A51: 2026.05.31-06.05 | M51: {=IF($G51="","",IFERROR(INDEX(Ангилал!$A$5:$A$22,MATCH(TRUE(),INDEX(ISNUMBER(SEARCH(Ангилал!$B$5:$B$22,$G51&" "&$D51))+ISNUMBER(SEARCH(Ангилал!$C$5:$C$22,$G51&" "&$D51))+IF(Ангилал!$D$5:$D$22="",0,ISNUMBER(SEARCH(Ангилал!$D$5:$D$22,$G51&" "&$D51)))+IF(Ангилал!$E$5:$E$22="",0,ISNUMBER(SEARCH(Ангилал!$E$5:$E$22,$G51&" "&$D51)))>0,0),0)),"Бусад"))} | O51: =IF($G51="","",IF($N51<>"",$N51,$M51)) | P51: {=IF($G51="","",IFERROR(INDEX(Ангилал!$G$5:$G$16,MATCH(TRUE(),INDEX(ISNUMBER(SEARCH(Ангилал!$H$5:$H$16,$G51&" "&$D51&" "&$E51))+ISNUMBER(SEARCH(Ангилал!$I$5:$I$16,$G51&" "&$D51&" "&$E51))+ISNUMBER(SEARCH(Ангилал!$J$5:$J$16,$G51&" "&$D51&" "&$E51))+ISNUMBER(SEARCH(Ангилал!$K$5:$K$16,$G51&" "&$D51&" "&$E51))>0,0),0)),"Ерөнхий нийт"))} | R51: =IF($G51="","",IF($Q51<>"",$Q51,$P51))
A52: 38 | B52: 2026.05.31 | C52: 2026-05-24 | D52: Хогийн цэгийн эрэг нурж 13 настай хүү шороонд дарагдаж нас барав | E52: Дорноговь аймгийн Өргөн суманд хогийн цэг дээр тоглож байсан 6 дугаар ангийн 13 настай эрэгтэй хүүхэд эрэг нурсны улмаас шороонд дарагдаж, амь насаа алдсан ноцтой осол бүртгэгдэж, олон нийтийн сүлжээгээр иргэдийг бухимдуулав. Орон нутагт хүүхдийн аюулгүй тоглох орчин байхгүй, хогийн цэгийн хамгаалалт хангалтгүй байгааг илтгэв. | F52: Дорноговь аймаг, Өргөн сум | G52: Амьд явах эрх, Хүүхдийн хамгаалагдах эрх, Эрүүл, аюулгүй орчинд амьдрах эрх | H52: Өргөн сумын Засаг даргын тамгын газар, Тохижилт үйлчилгээний хэлтэс | I52: Аймгийн Цагдаагийн газраас хэрэг бүртгэлт хийж байна. Дорноговь аймгийн хэмжээнд уул уурхайн олборлолтыг түр зогсоож, нөхөн сэргээлт хийхийг үүрэгдсэн. Уг нүхийг нэн даруй булж аюулгүй болгохыг даалгасан. | J52: isee.mn | K52: https://isee.mn/n/91447 | M52: {=IF($G52="","",IFERROR(INDEX(Ангилал!$A$5:$A$22,MATCH(TRUE(),INDEX(ISNUMBER(SEARCH(Ангилал!$B$5:$B$22,$G52&" "&$D52))+ISNUMBER(SEARCH(Ангилал!$C$5:$C$22,$G52&" "&$D52))+IF(Ангилал!$D$5:$D$22="",0,ISNUMBER(SEARCH(Ангилал!$D$5:$D$22,$G52&" "&$D52)))+IF(Ангилал!$E$5:$E$22="",0,ISNUMBER(SEARCH(Ангилал!$E$5:$E$22,$G52&" "&$D52)))>0,0),0)),"Бусад"))} -> Хүүхдийн эрх | O52: =IF($G52="","",IF($N52<>"",$N52,$M52)) -> Хүүхдийн эрх | P52: {=IF($G52="","",IFERROR(INDEX(Ангилал!$G$5:$G$16,MATCH(TRUE(),INDEX(ISNUMBER(SEARCH(Ангилал!$H$5:$H$16,$G52&" "&$D52&" "&$E52))+ISNUMBER(SEARCH(Ангилал!$I$5:$I$16,$G52&" "&$D52&" "&$E52))+ISNUMBER(SEARCH(Ангилал!$J$5:$J$16,$G52&" "&$D52&" "&$E52))+ISNUMBER(SEARCH(Ангилал!$K$5:$K$16,$G52&" "&$D52&" "&$E52))>0,0),0)),"Ерөнхий нийт"))} -> Хүүхэд | R52: =IF($G52="","",IF($Q52<>"",$Q52,$P52)) -> Хүүхэд
A53: 39 | B53: 2026.06.01 | C53: 2026.06.01 | D53: Олон улсын хүүхдийн эрхийг хамгаалах өдрөөр хүүхдийн эрх зөрчигдсөн асуудлууд | E53: Баярын талбай болон паркт олон цагаар дараалалд зогсоож хүүхдийг туйлдуулах, төв талбай дээр олон тооны хүүхэд төөрөх, баярын бэлгэнд хугацаа нь дууссан чанаргүй хүнсний бүтээгдэхүүн багтсан тухай иргэд шүүмжлэв. | F53: Улаанбаатар хот, Сүхбаатарын талбай, Хүүхдийн парк | G53: Хүүхдийн эрх, Эрүүл аюулгүй орчинд амьдрах, чанартай тусламж үйлчилгээ авах эрх | H53: Зохион байгуулагч аж ахуйн нэгжүүд, холбогдох төрийн хяналтын байгууллагууд | I53: Цагдаагийн байгууллагаас төөрсөн хүүхдүүдийг эрэн сурвалжлах, хүнсний чанарт шалгалт оруулахаар ажиллаж байгаагаа мэдэгдсэн. | J53: Facebook, Threads сүлжээн дэх эцэг эхчүүдийн гомдол, зурагт мэдээллүүд | M53: {=IF($G53="","",IFERROR(INDEX(Ангилал!$A$5:$A$22,MATCH(TRUE(),INDEX(ISNUMBER(SEARCH(Ангилал!$B$5:$B$22,$G53&" "&$D53))+ISNUMBER(SEARCH(Ангилал!$C$5:$C$22,$G53&" "&$D53))+IF(Ангилал!$D$5:$D$22="",0,ISNUMBER(SEARCH(Ангилал!$D$5:$D$22,$G53&" "&$D53)))+IF(Ангилал!$E$5:$E$22="",0,ISNUMBER(SEARCH(Ангилал!$E$5:$E$22,$G53&" "&$D53)))>0,0),0)),"Бусад"))} -> Хүүхдийн эрх | O53: =IF($G53="","",IF($N53<>"",$N53,$M53)) -> Хүүхдийн эрх | P53: {=IF($G53="","",IFERROR(INDEX(Ангилал!$G$5:$G$16,MATCH(TRUE(),INDEX(ISNUMBER(SEARCH(Ангилал!$H$5:$H$16,$G53&" "&$D53&" "&$E53))+ISNUMBER(SEARCH(Ангилал!$I$5:$I$16,$G53&" "&$D53&" "&$E53))+ISNUMBER(SEARCH(Ангилал!$J$5:$J$16,$G53&" "&$D53&" "&$E53))+ISNUMBER(SEARCH(Ангилал!$K$5:$K$16,$G53&" "&$D53&" "&$E53))>0,0),0)),"Ерөнхий нийт"))} -> Хүүхэд | R53: =IF($G53="","",IF($Q53<>"",$Q53,$P53)) -> Хүүхэд
A54: 40 | B54: 2026.06.02 | C54: 2026-05-02-ны байдлаар | D54: Прокурорын байгууллагын мэдээлснээр хүүхдийн эрхтэй холбоотой зөрчил өндөр түвшинд байна. | E54: “Хүүхдийн эрхийг зөрчих” зөрчил 2026 оны 5 дугаар сарын 20-ны өдрийн байдлаар улсын хэмжээнд нийт 3213 бүртгэгдсэн нь өмнөх оны мөн үеэс 191 буюу 5.6 хувиар буурчээ. “Хүүхдийн бие махбодод халдсан, эсхүл үл хайхарсан, эсхүл хүүхдийн дэргэд архидан согтуурсан, мансуурсан, хүчирхийлэл үйлдсэн” зөрчил 3020 бүртгэгдсэн нь хүүхдийн эрхийг зөрчих нийт зөрчлийн 94 хувийг эзэлж байна. | F54: Улсын хэмжээнд | G54: Эрүүл аюулгүй орчинд амьдрах эрх, хүүхдийн эрх | I54: Хяналт шалгалт үргэлжилж байгаа | J54: Монгол Улсын Ерөнхий прокурорын газар | K54: https://prosecutor.mn/post/113353 | M54: {=IF($G54="","",IFERROR(INDEX(Ангилал!$A$5:$A$22,MATCH(TRUE(),INDEX(ISNUMBER(SEARCH(Ангилал!$B$5:$B$22,$G54&" "&$D54))+ISNUMBER(SEARCH(Ангилал!$C$5:$C$22,$G54&" "&$D54))+IF(Ангилал!$D$5:$D$22="",0,ISNUMBER(SEARCH(Ангилал!$D$5:$D$22,$G54&" "&$D54)))+IF(Ангилал!$E$5:$E$22="",0,ISNUMBER(SEARCH(Ангилал!$E$5:$E$22,$G54&" "&$D54)))>0,0),0)),"Бусад"))} -> Хүүхдийн эрх | O54: =IF($G54="","",IF($N54<>"",$N54,$M54)) -> Хүүхдийн эрх | P54: {=IF($G54="","",IFERROR(INDEX(Ангилал!$G$5:$G$16,MATCH(TRUE(),INDEX(ISNUMBER(SEARCH(Ангилал!$H$5:$H$16,$G54&" "&$D54&" "&$E54))+ISNUMBER(SEARCH(Ангилал!$I$5:$I$16,$G54&" "&$D54&" "&$E54))+ISNUMBER(SEARCH(Ангилал!$J$5:$J$16,$G54&" "&$D54&" "&$E54))+ISNUMBER(SEARCH(Ангилал!$K$5:$K$16,$G54&" "&$D54&" "&$E54))>0,0),0)),"Ерөнхий нийт"))} -> Хүүхэд | R54: =IF($G54="","",IF($Q54<>"",$Q54,$P54)) -> Хүүхэд
A55: 41 | B55: 2026.06.05 | D55: Хүүхдэд зориулсан "Буузан тоглоом" харшил, амьсгал боогдох эрсдэл үүсгэж байна | E55: Хүүхдийн эрүүл мэнд, аюулгүй байдалд эрсдэл учруулж болзошгүй бүтээгдэхүүний талаар сэрэмжлүүлэг гаргасан. | F55: Улсын хэмжээнд | G55: Эрүүл аюулгүй орчинд амьдрах эрх, хүүхдийн эрх | H55: Импортлогч, худалдаалагч байгууллага | I55: Мэргэжлийн байгууллагууд анхааруулга гаргасан | J55: ikon.mn П.Сайнжаргал 2026.06.05 | K55: https://ikon.mn/n/3o0x | M55: {=IF($G55="","",IFERROR(INDEX(Ангилал!$A$5:$A$22,MATCH(TRUE(),INDEX(ISNUMBER(SEARCH(Ангилал!$B$5:$B$22,$G55&" "&$D55))+ISNUMBER(SEARCH(Ангилал!$C$5:$C$22,$G55&" "&$D55))+IF(Ангилал!$D$5:$D$22="",0,ISNUMBER(SEARCH(Ангилал!$D$5:$D$22,$G55&" "&$D55)))+IF(Ангилал!$E$5:$E$22="",0,ISNUMBER(SEARCH(Ангилал!$E$5:$E$22,$G55&" "&$D55)))>0,0),0)),"Бусад"))} -> Хүүхдийн эрх | O55: =IF($G55="","",IF($N55<>"",$N55,$M55)) -> Хүүхдийн эрх | P55: {=IF($G55="","",IFERROR(INDEX(Ангилал!$G$5:$G$16,MATCH(TRUE(),INDEX(ISNUMBER(SEARCH(Ангилал!$H$5:$H$16,$G55&" "&$D55&" "&$E55))+ISNUMBER(SEARCH(Ангилал!$I$5:$I$16,$G55&" "&$D55&" "&$E55))+ISNUMBER(SEARCH(Ангилал!$J$5:$J$16,$G55&" "&$D55&" "&$E55))+ISNUMBER(SEARCH(Ангилал!$K$5:$K$16,$G55&" "&$D55&" "&$E55))>0,0),0)),"Ерөнхий нийт"))} -> Хүүхэд | R55: =IF($G55="","",IF($Q55<>"",$Q55,$P55)) -> Хүүхэд
A56: 2026.06.08-06.12 | M56: {=IF($G56="","",IFERROR(INDEX(Ангилал!$A$5:$A$22,MATCH(TRUE(),INDEX(ISNUMBER(SEARCH(Ангилал!$B$5:$B$22,$G56&" "&$D56))+ISNUMBER(SEARCH(Ангилал!$C$5:$C$22,$G56&" "&$D56))+IF(Ангилал!$D$5:$D$22="",0,ISNUMBER(SEARCH(Ангилал!$D$5:$D$22,$G56&" "&$D56)))+IF(Ангилал!$E$5:$E$22="",0,ISNUMBER(SEARCH(Ангилал!$E$5:$E$22,$G56&" "&$D56)))>0,0),0)),"Бусад"))} | O56: =IF($G56="","",IF($N56<>"",$N56,$M56)) | P56: {=IF($G56="","",IFERROR(INDEX(Ангилал!$G$5:$G$16,MATCH(TRUE(),INDEX(ISNUMBER(SEARCH(Ангилал!$H$5:$H$16,$G56&" "&$D56&" "&$E56))+ISNUMBER(SEARCH(Ангилал!$I$5:$I$16,$G56&" "&$D56&" "&$E56))+ISNUMBER(SEARCH(Ангилал!$J$5:$J$16,$G56&" "&$D56&" "&$E56))+ISNUMBER(SEARCH(Ангилал!$K$5:$K$16,$G56&" "&$D56&" "&$E56))>0,0),0)),"Ерөнхий нийт"))} | R56: =IF($G56="","",IF($Q56<>"",$Q56,$P56))
A57: 42 | B57: 2026.06.10 | D57: Нийслэлийн 21-р сургуулийн 10 дугаар ангийн сурагчид өнгөрсөн шөнө бүлэглэн сурагчдыг зодож, нэгнийх нь хамрыг хугалсан хэрэг гарчээ | E57: 21-р сургуулийн сурагчид өмнө нь мөн үе тэнгийн дээрэлхэлт хийж, Шангри-лад сурагчид зодсон хэрэгт холбогдож, хуулийн шатанд яваа юм. Тэгвэл тус сургуульд дахин энэ төрлийн хэрэг гарлаа. | F57: БЗД-6 хороо | G57: Халдашгүй байх эрх, Хүчирхийлэл, харгис хэрцгий, хүнлэг бус харьцаанаас ангид байх эрх Хүүхдийн эрх, Эрүүл мэндээ хамгаалуулах эрх, Аюулгүй орчинд суралцах эрх, Хүний нэр төр, алдар хүндийг хүндэтгүүлэх эрх, Хүүхдийн хөгжих эрх | J57: tsahiur.mn | K57: https://www.facebook.com/story.php?story_fbid=1504861694988280&id=100063933908097&mibextid=wwXIfr&rdid=9Kz2ryKqlRG6I9xI# | M57: {=IF($G57="","",IFERROR(INDEX(Ангилал!$A$5:$A$22,MATCH(TRUE(),INDEX(ISNUMBER(SEARCH(Ангилал!$B$5:$B$22,$G57&" "&$D57))+ISNUMBER(SEARCH(Ангилал!$C$5:$C$22,$G57&" "&$D57))+IF(Ангилал!$D$5:$D$22="",0,ISNUMBER(SEARCH(Ангилал!$D$5:$D$22,$G57&" "&$D57)))+IF(Ангилал!$E$5:$E$22="",0,ISNUMBER(SEARCH(Ангилал!$E$5:$E$22,$G57&" "&$D57)))>0,0),0)),"Бусад"))} -> Эрүүдэн шүүлт, хүнлэг бус харьцаа | O57: =IF($G57="","",IF($N57<>"",$N57,$M57)) -> Эрүүдэн шүүлт, хүнлэг бус харьцаа | P57: {=IF($G57="","",IFERROR(INDEX(Ангилал!$G$5:$G$16,MATCH(TRUE(),INDEX(ISNUMBER(SEARCH(Ангилал!$H$5:$H$16,$G57&" "&$D57&" "&$E57))+ISNUMBER(SEARCH(Ангилал!$I$5:$I$16,$G57&" "&$D57&" "&$E57))+ISNUMBER(SEARCH(Ангилал!$J$5:$J$16,$G57&" "&$D57&" "&$E57))+ISNUMBER(SEARCH(Ангилал!$K$5:$K$16,$G57&" "&$D57&" "&$E57))>0,0),0)),"Ерөнхий нийт"))} -> Хүүхэд | R57: =IF($G57="","",IF($Q57<>"",$Q57,$P57)) -> Хүүхэд
A58: 43 | B58: 2026.06.10 | D58: Ахынхаа регистрийг ашиглаад хувь хүний нууц задруулсан гэмт хэрэгтэн болов | E58: Бусдын регистрийн дугаар дахин давтагдашгүй бөгөөд тухайн хүний шууд болон шууд бусаар тодорхойлох мэдээлэлд хамаардаг. Иргэн Б.А-ийн дээрх үйлдлийг Хувь хүний хуулиар хамгаалагдсан нууцыг олж мэдсэн хүн өөрийнх нь зөвшөөрөлгүйгээр задруулсан гэж үзэх үндэслэл болжээ. | F58: Төв аймаг | G58: Хүний хувийн нууц | H58: Ахынхаа мэдээллийг задрулсан Б.А | I58: Төв аймаг дахь Сум дундын анхан шатны шүүхээс 4,350,000 төгрөгөөр торгох ялаар шийтгэсэн. | J58: gogo.mn | K58: https://gogo.mn/r/e04j6d | M58: {=IF($G58="","",IFERROR(INDEX(Ангилал!$A$5:$A$22,MATCH(TRUE(),INDEX(ISNUMBER(SEARCH(Ангилал!$B$5:$B$22,$G58&" "&$D58))+ISNUMBER(SEARCH(Ангилал!$C$5:$C$22,$G58&" "&$D58))+IF(Ангилал!$D$5:$D$22="",0,ISNUMBER(SEARCH(Ангилал!$D$5:$D$22,$G58&" "&$D58)))+IF(Ангилал!$E$5:$E$22="",0,ISNUMBER(SEARCH(Ангилал!$E$5:$E$22,$G58&" "&$D58)))>0,0),0)),"Бусад"))} -> Хувийн нууц, халдашгүй байдал | O58: =IF($G58="","",IF($N58<>"",$N58,$M58)) -> Хувийн нууц, халдашгүй байдал | P58: {=IF($G58="","",IFERROR(INDEX(Ангилал!$G$5:$G$16,MATCH(TRUE(),INDEX(ISNUMBER(SEARCH(Ангилал!$H$5:$H$16,$G58&" "&$D58&" "&$E58))+ISNUMBER(SEARCH(Ангилал!$I$5:$I$16,$G58&" "&$D58&" "&$E58))+ISNUMBER(SEARCH(Ангилал!$J$5:$J$16,$G58&" "&$D58&" "&$E58))+ISNUMBER(SEARCH(Ангилал!$K$5:$K$16,$G58&" "&$D58&" "&$E58))>0,0),0)),"Ерөнхий нийт"))} -> Ерөнхий нийт | R58: =IF($G58="","",IF($Q58<>"",$Q58,$P58)) -> Ерөнхий нийт
A59: 44 | B59: 2026.06.12 | D59: Эмийн санч насанд хүрэгчийн тунгаар андуурч эм өгсөнөөс болж нярай хорлогод оржээ | E59: Эмийн жорд “5 мг” гэж хүүхдийн тунгаар бичсэн байхад 100 мг савлагаатай эм олгож, эмийг нярайд өгсний дараа түүний амь насанд аюултай тархины цусан хангамжийн алдагдлын хүнд хэлбэр, эрүүл тархины цусан хангамжийн алдагдлын хүнд хэлбэр, тархины эмгэгшил үүсэж эрүүл мэндэд нь хүнд хохирол учирсан гэж үзсэн байна. | G59: Эрүүл мэндээ хамгаалуулах, эмнэлгийн чанартай тусламж авах эрх, Аюулгүй байх, гэм хор учруулахгүй байх эрх, | H59: Эмийн санч “Ё” | I59: Эмийн санч Ё нь ...ХХК-тай байгуулсан хөдөлмөрийн гэрээгээр ажиллаж байхдаа бусдад гэм хор учруулсан байх тул тус компанийг иргэний хариуцагчаар татан оролцуулжээ. Хохирогчоос нэхэмжилсэн мөнгийг төлсөн байх тул иргэний хариуцагчаас гаргуулах гэм хорын төлбөргүй гэж шүүх дүгнэсэн байна. | J59: isee.mn | K59: https://isee.mn/n/91946 | M59: {=IF($G59="","",IFERROR(INDEX(Ангилал!$A$5:$A$22,MATCH(TRUE(),INDEX(ISNUMBER(SEARCH(Ангилал!$B$5:$B$22,$G59&" "&$D59))+ISNUMBER(SEARCH(Ангилал!$C$5:$C$22,$G59&" "&$D59))+IF(Ангилал!$D$5:$D$22="",0,ISNUMBER(SEARCH(Ангилал!$D$5:$D$22,$G59&" "&$D59)))+IF(Ангилал!$E$5:$E$22="",0,ISNUMBER(SEARCH(Ангилал!$E$5:$E$22,$G59&" "&$D59)))>0,0),0)),"Бусад"))} -> Амьд явах, халдашгүй байх эрх | O59: =IF($G59="","",IF($N59<>"",$N59,$M59)) -> Амьд явах, халдашгүй байх эрх | P59: {=IF($G59="","",IFERROR(INDEX(Ангилал!$G$5:$G$16,MATCH(TRUE(),INDEX(ISNUMBER(SEARCH(Ангилал!$H$5:$H$16,$G59&" "&$D59&" "&$E59))+ISNUMBER(SEARCH(Ангилал!$I$5:$I$16,$G59&" "&$D59&" "&$E59))+ISNUMBER(SEARCH(Ангилал!$J$5:$J$16,$G59&" "&$D59&" "&$E59))+ISNUMBER(SEARCH(Ангилал!$K$5:$K$16,$G59&" "&$D59&" "&$E59))>0,0),0)),"Ерөнхий нийт"))} -> Хүүхэд | R59: =IF($G59="","",IF($Q59<>"",$Q59,$P59)) -> Хүүхэд
A60: 45 | B60: 2026.06.11 | C60: 2024 он | D60: Есөн настай хүүг хойд эх нь амбаарт түгжин шатаажээ | E60: 2024 оны арванхоёрдугаар сард гарсан энэ харамсалтай хэргийн улмаас 9 настай хүү 80 хувийн хөдөлмөрийн чадвараа алдаж, хүний байнгын асаргаанд орсон байна. Түүнийг аавынхаа гэрт байхад амбаараас “гутал хайх” нэрийдлээр оруулсны дараа хойд эх нь гал тавьсан бөгөөд өнөөдрийг хүртэл хэн ч хариуцлага хүлээгээгүй байна. Хүүгийн хамгийн их гомддог хүн аав н | G60: Амьд явах, амьд явахаа хамгаалуулах эрх, Хүчирхийлэл, харгислал, эрүүдэн шүүхээс ангид байх эрх, | J60: zarig.mn | K60: https://zarig.mn/1ijn | M60: {=IF($G60="","",IFERROR(INDEX(Ангилал!$A$5:$A$22,MATCH(TRUE(),INDEX(ISNUMBER(SEARCH(Ангилал!$B$5:$B$22,$G60&" "&$D60))+ISNUMBER(SEARCH(Ангилал!$C$5:$C$22,$G60&" "&$D60))+IF(Ангилал!$D$5:$D$22="",0,ISNUMBER(SEARCH(Ангилал!$D$5:$D$22,$G60&" "&$D60)))+IF(Ангилал!$E$5:$E$22="",0,ISNUMBER(SEARCH(Ангилал!$E$5:$E$22,$G60&" "&$D60)))>0,0),0)),"Бусад"))} -> Эрүүдэн шүүлт, хүнлэг бус харьцаа | O60: =IF($G60="","",IF($N60<>"",$N60,$M60)) -> Эрүүдэн шүүлт, хүнлэг бус харьцаа | P60: {=IF($G60="","",IFERROR(INDEX(Ангилал!$G$5:$G$16,MATCH(TRUE(),INDEX(ISNUMBER(SEARCH(Ангилал!$H$5:$H$16,$G60&" "&$D60&" "&$E60))+ISNUMBER(SEARCH(Ангилал!$I$5:$I$16,$G60&" "&$D60&" "&$E60))+ISNUMBER(SEARCH(Ангилал!$J$5:$J$16,$G60&" "&$D60&" "&$E60))+ISNUMBER(SEARCH(Ангилал!$K$5:$K$16,$G60&" "&$D60&" "&$E60))>0,0),0)),"Ерөнхий нийт"))} -> Ерөнхий нийт | R60: =IF($G60="","",IF($Q60<>"",$Q60,$P60)) -> Ерөнхий нийт
A61: 2026.06.15-06.22 | M61: {=IF($G61="","",IFERROR(INDEX(Ангилал!$A$5:$A$22,MATCH(TRUE(),INDEX(ISNUMBER(SEARCH(Ангилал!$B$5:$B$22,$G61&" "&$D61))+ISNUMBER(SEARCH(Ангилал!$C$5:$C$22,$G61&" "&$D61))+IF(Ангилал!$D$5:$D$22="",0,ISNUMBER(SEARCH(Ангилал!$D$5:$D$22,$G61&" "&$D61)))+IF(Ангилал!$E$5:$E$22="",0,ISNUMBER(SEARCH(Ангилал!$E$5:$E$22,$G61&" "&$D61)))>0,0),0)),"Бусад"))} | O61: =IF($G61="","",IF($N61<>"",$N61,$M61)) | P61: {=IF($G61="","",IFERROR(INDEX(Ангилал!$G$5:$G$16,MATCH(TRUE(),INDEX(ISNUMBER(SEARCH(Ангилал!$H$5:$H$16,$G61&" "&$D61&" "&$E61))+ISNUMBER(SEARCH(Ангилал!$I$5:$I$16,$G61&" "&$D61&" "&$E61))+ISNUMBER(SEARCH(Ангилал!$J$5:$J$16,$G61&" "&$D61&" "&$E61))+ISNUMBER(SEARCH(Ангилал!$K$5:$K$16,$G61&" "&$D61&" "&$E61))>0,0),0)),"Ерөнхий нийт"))} | R61: =IF($G61="","",IF($Q61<>"",$Q61,$P61))
A62: 46 | B62: 2026.06.15 | C62: 2026.06.15 | D62: 15 настай хүүхэд барилгын ажил хийж яваад амь насаа алдсан. Тэгвэл Эрдэнэтэд хамгаалах хэрэгсэлгүй, насанд хүрээгүй байж магадгүй хүүхэд дээврийн ажил хийгээд хийж байна гэдэг мэдээлэл ирлээ. | E62: 15 настай хүүхэд барилгын ажил хийж яваад амь насаа алдсан. Тэгвэл Эрдэнэтэд хамгаалах хэрэгсэлгүй, насанд хүрээгүй байж магадгүй хүүхэд дээврийн ажил хийгээд хийж байна гэдэг мэдээлэл ирлээ. Ажил олгогчид хямдыг нь бодож хүүхэд ажиллуулдаг. Журмаар барилга уул уурхай, баяжуулах үйлдвэрт хүүхэд ажиллуулах хориотой. Та бүхэн энэ мэт эрсдэлтэй нөхцлийн талаарх мэдээллээ өгч байгаарай. Бид шуурхай арга хэмжээ авна. Өгсөн дуудлага мэдээллийн дагуу цагдаагийн алба хаагчид газар дээр нь очиход Орхон аймаг Баян-Өндөр сумын Согоот баг 6-13 дугаар байрны дээврийн засвар хийхдээ ХАБ-ын журам зөрчиж хамгаалах хэрэгсэлгүй, 18 насанд хүрээгүй хүн ажиллуулж байсан нь тогтоогджээ. | F62: Орхон аймаг Баян-Өндөр сумын Согоот баг 6-13 дугаар байрны дээвэр | G62: Амьд явах эрх, Аюулгүй, эрүүл орчинд ажиллах эрх, Хүүхдийг эдийн засгийн мөлжлөгөөс хамгаалуулах эрх, Эрүүл мэндээ хамгаалуулах эрх | H62: Барилгын компани, ХАБ-ын ажилтан | I62: Засварын ажлыг зогсоож арга хэмжээ авахуулахаар эрх бүхий байгууллагад шилжүүлсэн байна. | J62: twitter Хуульч О.Батхүү | K62: https://x.com/batkhuu_lw/status/2066440433182646473?s=46 | M62: {=IF($G62="","",IFERROR(INDEX(Ангилал!$A$5:$A$22,MATCH(TRUE(),INDEX(ISNUMBER(SEARCH(Ангилал!$B$5:$B$22,$G62&" "&$D62))+ISNUMBER(SEARCH(Ангилал!$C$5:$C$22,$G62&" "&$D62))+IF(Ангилал!$D$5:$D$22="",0,ISNUMBER(SEARCH(Ангилал!$D$5:$D$22,$G62&" "&$D62)))+IF(Ангилал!$E$5:$E$22="",0,ISNUMBER(SEARCH(Ангилал!$E$5:$E$22,$G62&" "&$D62)))>0,0),0)),"Бусад"))} -> Хүүхдийн эрх | O62: =IF($G62="","",IF($N62<>"",$N62,$M62)) -> Хүүхдийн эрх | P62: {=IF($G62="","",IFERROR(INDEX(Ангилал!$G$5:$G$16,MATCH(TRUE(),INDEX(ISNUMBER(SEARCH(Ангилал!$H$5:$H$16,$G62&" "&$D62&" "&$E62))+ISNUMBER(SEARCH(Ангилал!$I$5:$I$16,$G62&" "&$D62&" "&$E62))+ISNUMBER(SEARCH(Ангилал!$J$5:$J$16,$G62&" "&$D62&" "&$E62))+ISNUMBER(SEARCH(Ангилал!$K$5:$K$16,$G62&" "&$D62&" "&$E62))>0,0),0)),"Ерөнхий нийт"))} -> Хүүхэд | R62: =IF($G62="","",IF($Q62<>"",$Q62,$P62)) -> Хүүхэд
A63: 47 | B63: 2026.06.15 | C63: 2026.06.15 | D63: ХЭҮК энэ хүний эрхийн зөрчил мөн үү? мөн бол танайх ийм үйлдэлтэй хүмүүст ямар хари уцлага тооцдог вэ? | E63: Н.Тэгшбаяр: Үр хүүхэд нь уул уурхайд ажиллдаг хүмүүс уул уурхайн төслүүдийг эсэргүүцээд яваад байгаа тохиолдолд хүүхдийг нь ажлаас чөлөөлөхийг уриалж байна. Энэ хүний хүүхэд ОТ- д ажилладаг. Тэгсэн хирнээ эцэн эх нь уул уурхайн төсөл эсэргүүцдэг. Ийм байж болох юм уу? Тэгээд хүүхдээ өөрөө тэжээх хэрэгтэй. | F63: Улсын хэмжээнд | G63: Хөдөлмөрлөх, үзэл бодлоо чөлөөтэй илэрхийлэх | H63: Физикийн ухааны доктор, Арбитрч Н.Тэгшбаяр | J63: twiiter | K63: https://x.com/batzorig2012/status/2066430318337515965 | M63: {=IF($G63="","",IFERROR(INDEX(Ангилал!$A$5:$A$22,MATCH(TRUE(),INDEX(ISNUMBER(SEARCH(Ангилал!$B$5:$B$22,$G63&" "&$D63))+ISNUMBER(SEARCH(Ангилал!$C$5:$C$22,$G63&" "&$D63))+IF(Ангилал!$D$5:$D$22="",0,ISNUMBER(SEARCH(Ангилал!$D$5:$D$22,$G63&" "&$D63)))+IF(Ангилал!$E$5:$E$22="",0,ISNUMBER(SEARCH(Ангилал!$E$5:$E$22,$G63&" "&$D63)))>0,0),0)),"Бусад"))} -> Үзэл бодлоо илэрхийлэх, мэдээллийн эрх | O63: =IF($G63="","",IF($N63<>"",$N63,$M63)) -> Үзэл бодлоо илэрхийлэх, мэдээллийн эрх | P63: {=IF($G63="","",IFERROR(INDEX(Ангилал!$G$5:$G$16,MATCH(TRUE(),INDEX(ISNUMBER(SEARCH(Ангилал!$H$5:$H$16,$G63&" "&$D63&" "&$E63))+ISNUMBER(SEARCH(Ангилал!$I$5:$I$16,$G63&" "&$D63&" "&$E63))+ISNUMBER(SEARCH(Ангилал!$J$5:$J$16,$G63&" "&$D63&" "&$E63))+ISNUMBER(SEARCH(Ангилал!$K$5:$K$16,$G63&" "&$D63&" "&$E63))>0,0),0)),"Ерөнхий нийт"))} -> Хүүхэд | R63: =IF($G63="","",IF($Q63<>"",$Q63,$P63)) -> Хүүхэд
A64: 48 | B64: 2026.06.18 | C64: 2026.06.18 | D64: Б.Октябрь:Ийм зүйл ярих нь ёстой нөгөө Үндэсний аюулгүй байдал шүү дээ. | E64: Нотолгоо баталгаагүй яс үндэс нийгмийн гарал үүслээр нь ялгаварлан, хооронд нь хагарлдуулсан мэдээ мэдээлэл тараах нь УИХ гишүүн хүний хувьд маш буруу шүү. Гэмт хэрэг болно. | F64: Улсын хэмжээнд | G64: Яс үндсээр нь ялгаврлах гадуурхагдахгүй байх | H64: Зарим иргэд, төрийн өндөр албан тушаалтнууд, ялангуяа УИХ-ын гишүүн М.Нарантуяа | J64: Fb twitter | K64: #VALUE! | L64: #VALUE! | M64: {=IF($G64="","",IFERROR(INDEX(Ангилал!$A$5:$A$22,MATCH(TRUE(),INDEX(ISNUMBER(SEARCH(Ангилал!$B$5:$B$22,$G64&" "&$D64))+ISNUMBER(SEARCH(Ангилал!$C$5:$C$22,$G64&" "&$D64))+IF(Ангилал!$D$5:$D$22="",0,ISNUMBER(SEARCH(Ангилал!$D$5:$D$22,$G64&" "&$D64)))+IF(Ангилал!$E$5:$E$22="",0,ISNUMBER(SEARCH(Ангилал!$E$5:$E$22,$G64&" "&$D64)))>0,0),0)),"Бусад"))} -> Бусад | O64: =IF($G64="","",IF($N64<>"",$N64,$M64)) -> Бусад | P64: {=IF($G64="","",IFERROR(INDEX(Ангилал!$G$5:$G$16,MATCH(TRUE(),INDEX(ISNUMBER(SEARCH(Ангилал!$H$5:$H$16,$G64&" "&$D64&" "&$E64))+ISNUMBER(SEARCH(Ангилал!$I$5:$I$16,$G64&" "&$D64&" "&$E64))+ISNUMBER(SEARCH(Ангилал!$J$5:$J$16,$G64&" "&$D64&" "&$E64))+ISNUMBER(SEARCH(Ангилал!$K$5:$K$16,$G64&" "&$D64&" "&$E64))>0,0),0)),"Ерөнхий нийт"))} -> Ерөнхий нийт | R64: =IF($G64="","",IF($Q64<>"",$Q64,$P64)) -> Ерөнхий нийт
A65: 49 | B65: 2026.06.19 | D65: Хувийн сургуульд суралцаж буй хүүхдийг ялгаварлан гадуурхах, сүрдүүлэх нь хууль бус үйлдэл мөн | E65: Боловсрол бол хүүхдийн суурь эрх бөгөөд хувийн сургуулийн төлбөр төлж буй явдал нь багш нарт хүүхдийг ялгаварлах, эрхшээлдээ оруулах эрх олгодоггүй гэдгийг хатуу анхаарах шаардлагатай. Хүүхдийнхээ сурч боловсрох эрхийг тууштай хамгаалцгаая! | F65: Улсын хэмжээнд | G65: Хүүхэд сургуулийн орчинд аливаа ялгаварлан гадуурхалт, сэтгэл санааны дарамт, хүчирхийллээс ангид байх | H65: Зарим хувийн сургууль | J65: FB | K65: https://www.facebook.com/share/p/1BcANJWDA7/ | M65: {=IF($G65="","",IFERROR(INDEX(Ангилал!$A$5:$A$22,MATCH(TRUE(),INDEX(ISNUMBER(SEARCH(Ангилал!$B$5:$B$22,$G65&" "&$D65))+ISNUMBER(SEARCH(Ангилал!$C$5:$C$22,$G65&" "&$D65))+IF(Ангилал!$D$5:$D$22="",0,ISNUMBER(SEARCH(Ангилал!$D$5:$D$22,$G65&" "&$D65)))+IF(Ангилал!$E$5:$E$22="",0,ISNUMBER(SEARCH(Ангилал!$E$5:$E$22,$G65&" "&$D65)))>0,0),0)),"Бусад"))} -> Хүүхдийн эрх | O65: =IF($G65="","",IF($N65<>"",$N65,$M65)) -> Хүүхдийн эрх | P65: {=IF($G65="","",IFERROR(INDEX(Ангилал!$G$5:$G$16,MATCH(TRUE(),INDEX(ISNUMBER(SEARCH(Ангилал!$H$5:$H$16,$G65&" "&$D65&" "&$E65))+ISNUMBER(SEARCH(Ангилал!$I$5:$I$16,$G65&" "&$D65&" "&$E65))+ISNUMBER(SEARCH(Ангилал!$J$5:$J$16,$G65&" "&$D65&" "&$E65))+ISNUMBER(SEARCH(Ангилал!$K$5:$K$16,$G65&" "&$D65&" "&$E65))>0,0),0)),"Ерөнхий нийт"))} -> Хүүхэд | R65: =IF($G65="","",IF($Q65<>"",$Q65,$P65)) -> Хүүхэд
A66: 50 | B66: 2026.06.21 | D66: Ажлын байрны дарамт газар авсны бодит илрэл | E66: Төрийн байгууллага болон хууль хүчний байгууллагуудын зарим албан хаагчид #ажлын_ачааллаасаа_бус дарга, удирдлагынхаа дарамт, ёс зүйгүй харилцаа хандлагаас халширч, ажилдаа биш даргынхаа ааш аяганд санаа зовинон ажилладаг болсон гэх мэдээлэл, гомдол тасрахгүй байна. | F66: Төрийн байгууллага | G66: Хөдөлмөрдөх, үзэл бодлоо чөлөөтэй илэрхийлэх ялгаварлан гадуурхалтаас ангид байх | H66: Төрийн байгууллагын удирдлага, ТАЗ | J66: Өмгөөлөгч Р.Булгамаа | K66: https://www.facebook.com/share/p/1Es4qy6nzM/ | M66: {=IF($G66="","",IFERROR(INDEX(Ангилал!$A$5:$A$22,MATCH(TRUE(),INDEX(ISNUMBER(SEARCH(Ангилал!$B$5:$B$22,$G66&" "&$D66))+ISNUMBER(SEARCH(Ангилал!$C$5:$C$22,$G66&" "&$D66))+IF(Ангилал!$D$5:$D$22="",0,ISNUMBER(SEARCH(Ангилал!$D$5:$D$22,$G66&" "&$D66)))+IF(Ангилал!$E$5:$E$22="",0,ISNUMBER(SEARCH(Ангилал!$E$5:$E$22,$G66&" "&$D66)))>0,0),0)),"Бусад"))} -> Хүчирхийлэл, бэлгийн дарамтаас ангид байх | O66: =IF($G66="","",IF($N66<>"",$N66,$M66)) -> Хүчирхийлэл, бэлгийн дарамтаас ангид байх | P66: {=IF($G66="","",IFERROR(INDEX(Ангилал!$G$5:$G$16,MATCH(TRUE(),INDEX(ISNUMBER(SEARCH(Ангилал!$H$5:$H$16,$G66&" "&$D66&" "&$E66))+ISNUMBER(SEARCH(Ангилал!$I$5:$I$16,$G66&" "&$D66&" "&$E66))+ISNUMBER(SEARCH(Ангилал!$J$5:$J$16,$G66&" "&$D66&" "&$E66))+ISNUMBER(SEARCH(Ангилал!$K$5:$K$16,$G66&" "&$D66&" "&$E66))>0,0),0)),"Ерөнхий нийт"))} -> Ерөнхий нийт | R66: =IF($G66="","",IF($Q66<>"",$Q66,$P66)) -> Ерөнхий нийт
A67: 2026.06.29-07.03 | M67: {=IF($G67="","",IFERROR(INDEX(Ангилал!$A$5:$A$22,MATCH(TRUE(),INDEX(ISNUMBER(SEARCH(Ангилал!$B$5:$B$22,$G67&" "&$D67))+ISNUMBER(SEARCH(Ангилал!$C$5:$C$22,$G67&" "&$D67))+IF(Ангилал!$D$5:$D$22="",0,ISNUMBER(SEARCH(Ангилал!$D$5:$D$22,$G67&" "&$D67)))+IF(Ангилал!$E$5:$E$22="",0,ISNUMBER(SEARCH(Ангилал!$E$5:$E$22,$G67&" "&$D67)))>0,0),0)),"Бусад"))} | O67: =IF($G67="","",IF($N67<>"",$N67,$M67)) | P67: {=IF($G67="","",IFERROR(INDEX(Ангилал!$G$5:$G$16,MATCH(TRUE(),INDEX(ISNUMBER(SEARCH(Ангилал!$H$5:$H$16,$G67&" "&$D67&" "&$E67))+ISNUMBER(SEARCH(Ангилал!$I$5:$I$16,$G67&" "&$D67&" "&$E67))+ISNUMBER(SEARCH(Ангилал!$J$5:$J$16,$G67&" "&$D67&" "&$E67))+ISNUMBER(SEARCH(Ангилал!$K$5:$K$16,$G67&" "&$D67&" "&$E67))>0,0),0)),"Ерөнхий нийт"))} | R67: =IF($G67="","",IF($Q67<>"",$Q67,$P67))
A68: 51 | B68: 2026.07.01 | C68: 2026.06.09 | D68: 2026.06.09-нд болсон Марш тактикийн тэмцээний үеэр цэргүүд барьцаалагдсан иргэнийг аврах үзүүлэх тоглолт хийсэн. Энэ үеэр газар хэвтэж байсан хугацаат цэргийн 2 алба хаагчийг авто машинаар дайран гарчээ. | E68: Тэмцээний үеэр газар хэвтэж байсан хоёр алба хаагчийн дээгүүр тоглолтод ашиглаж байсан "Toyota Harrier" маркийн автомашин гарч дайрсан. Цэргүүдийн биеийн байдал хүнд, ялангуяа нэг байлдагч элэгний бяцралтын улмаас хагалгаанд орж, нөгөө цэрэг нь яаралтай тусламжийн тасагт эмчлүүлж байгаа талаар эх сурвалжууд мэдээлсэн. | F68: Төв аймгийн Алтанбулаг сумын Тавантолгой дахь Зэвсэгт хүчний 311 дүгээр ангийн Сургалтын нэгдсэн төв | G68: Амьд явах, Халдашгүй, чөлөөтэй байх, бие махбодын халдашгүй байдал, Эрүүл мэндээ хамгаалуулах, өдөлмөрлөх аюулгүй нөхцөлөөр хангуулах, Хугацаат цэргийн алба хаагчийн онцгой хамгаалалтын зарчим | H68: Зэвсэгт хүчний 311 дүгээр анги | I68: Төв аймгийн Цагдаагийн газраас мөрдөн шалгах ажиллагааг тал бүрээс нь явуулж, нотлох баримтыг цуглуулж байна | J68: facebook | K68: https://shorturl.at/ha7bg | M68: {=IF($G68="","",IFERROR(INDEX(Ангилал!$A$5:$A$22,MATCH(TRUE(),INDEX(ISNUMBER(SEARCH(Ангилал!$B$5:$B$22,$G68&" "&$D68))+ISNUMBER(SEARCH(Ангилал!$C$5:$C$22,$G68&" "&$D68))+IF(Ангилал!$D$5:$D$22="",0,ISNUMBER(SEARCH(Ангилал!$D$5:$D$22,$G68&" "&$D68)))+IF(Ангилал!$E$5:$E$22="",0,ISNUMBER(SEARCH(Ангилал!$E$5:$E$22,$G68&" "&$D68)))>0,0),0)),"Бусад"))} -> Амьд явах, халдашгүй байх эрх | O68: =IF($G68="","",IF($N68<>"",$N68,$M68)) -> Амьд явах, халдашгүй байх эрх | P68: {=IF($G68="","",IFERROR(INDEX(Ангилал!$G$5:$G$16,MATCH(TRUE(),INDEX(ISNUMBER(SEARCH(Ангилал!$H$5:$H$16,$G68&" "&$D68&" "&$E68))+ISNUMBER(SEARCH(Ангилал!$I$5:$I$16,$G68&" "&$D68&" "&$E68))+ISNUMBER(SEARCH(Ангилал!$J$5:$J$16,$G68&" "&$D68&" "&$E68))+ISNUMBER(SEARCH(Ангилал!$K$5:$K$16,$G68&" "&$D68&" "&$E68))>0,0),0)),"Ерөнхий нийт"))} -> Ерөнхий нийт | R68: =IF($G68="","",IF($Q68<>"",$Q68,$P68)) -> Ерөнхий нийт
A69: 52 | B69: 2026.06.29 | C69: 2026.06.28 | D69: Хамт архидан согтуурсан үедээ нэгнийхээ толгойн тус газар нь заазуурджээ | E69: Цагдаагийн байгууллагад "Биеийн олон хэсэгт хутгалуулсан хүн сууж байна, яаралтай тусламж явуулаарай" гэх дуудлага, мэдээлэл 2026.06.28-ны өдөр бүртгэгдсэн. Баянзүрх дүүрэгт оршин суух "Б" нь хамт архидан согтуурсан үедээ хоорондын таарамжгүй харилцаанаас үүдэн нэгнийхээ толгойн тус газарт нэг удаа заазуурдаж, гэмтэл учруулсан гэх мэдээллийг ЦЕГ-аас олон нийтэд танилцуулав. | F69: Улаанбаатар хот, Баянзүрх дүүрэг | G69: Амьд явах эрх, эрүүл, аюулгүй орчинд амьдрах эрх, халдашгүй, чөлөөтэй байх эрх | H69: Иргэн "Б" | I69: Баянзүрх дүүргийн цагдаагийн газрын Хоёрдугаар хэлтэс мөрдөн шалгах ажиллагаа явуулж байна | J69: Цагдаагийн ерөнхий газар | K69: https://police.gov.mn/a/8140 | M69: {=IF($G69="","",IFERROR(INDEX(Ангилал!$A$5:$A$22,MATCH(TRUE(),INDEX(ISNUMBER(SEARCH(Ангилал!$B$5:$B$22,$G69&" "&$D69))+ISNUMBER(SEARCH(Ангилал!$C$5:$C$22,$G69&" "&$D69))+IF(Ангилал!$D$5:$D$22="",0,ISNUMBER(SEARCH(Ангилал!$D$5:$D$22,$G69&" "&$D69)))+IF(Ангилал!$E$5:$E$22="",0,ISNUMBER(SEARCH(Ангилал!$E$5:$E$22,$G69&" "&$D69)))>0,0),0)),"Бусад"))} -> Амьд явах, халдашгүй байх эрх | O69: =IF($G69="","",IF($N69<>"",$N69,$M69)) -> Амьд явах, халдашгүй байх эрх | P69: {=IF($G69="","",IFERROR(INDEX(Ангилал!$G$5:$G$16,MATCH(TRUE(),INDEX(ISNUMBER(SEARCH(Ангилал!$H$5:$H$16,$G69&" "&$D69&" "&$E69))+ISNUMBER(SEARCH(Ангилал!$I$5:$I$16,$G69&" "&$D69&" "&$E69))+ISNUMBER(SEARCH(Ангилал!$J$5:$J$16,$G69&" "&$D69&" "&$E69))+ISNUMBER(SEARCH(Ангилал!$K$5:$K$16,$G69&" "&$D69&" "&$E69))>0,0),0)),"Ерөнхий нийт"))} -> Ерөнхий нийт | R69: =IF($G69="","",IF($Q69<>"",$Q69,$P69)) -> Ерөнхий нийт
A70: 53 | B70: 2026.06.30 | C70: 2026.06.30 | D70: УИХ: "Малчны тухай хуулийн хэрэгжилтийг дүгнэх" ерөнхий хяналтын сонсгол болов | E70: УИХ-ын түвшинд "Малчны тухай хуулийн хэрэгжилтийг дүгнэх, хууль тогтоомжийг хэрэгжүүлэх чиг үүрэг бүхий байгууллага, түүний удирдах албан тушаалтны үйл ажиллагаанд хяналт тавих, үнэлэх" сэдэвт ерөнхий хяналтын сонсголыг 2026.06.30-ны өдөр зохион байгуулав. Малчдын хөдөлмөр эрхлэлт, нийгмийн хамгааллын эрхийн хэрэгжилттэй шууд холбоотой хяналтын арга хэмжээ юм. | F70: Улаанбаатар хот, Төрийн ордон | G70: Хөдөлмөрлөх эрх, нийгмийн хамгааллын эрх (малчид) | H70: Хуулийн хэрэгжилтийг хангах чиг үүрэг бүхий төрийн байгууллага, албан тушаалтнууд | I70: УИХ ерөнхий хяналтын сонсгол зохион байгуулж, хэрэгжилтийг дүгнэж байна | J70: МҮОНРТ | K70: https://www.mnb.mn/i/348483 | M70: {=IF($G70="","",IFERROR(INDEX(Ангилал!$A$5:$A$22,MATCH(TRUE(),INDEX(ISNUMBER(SEARCH(Ангилал!$B$5:$B$22,$G70&" "&$D70))+ISNUMBER(SEARCH(Ангилал!$C$5:$C$22,$G70&" "&$D70))+IF(Ангилал!$D$5:$D$22="",0,ISNUMBER(SEARCH(Ангилал!$D$5:$D$22,$G70&" "&$D70)))+IF(Ангилал!$E$5:$E$22="",0,ISNUMBER(SEARCH(Ангилал!$E$5:$E$22,$G70&" "&$D70)))>0,0),0)),"Бусад"))} -> Хөдөлмөрлөх эрх | O70: =IF($G70="","",IF($N70<>"",$N70,$M70)) -> Хөдөлмөрлөх эрх | P70: {=IF($G70="","",IFERROR(INDEX(Ангилал!$G$5:$G$16,MATCH(TRUE(),INDEX(ISNUMBER(SEARCH(Ангилал!$H$5:$H$16,$G70&" "&$D70&" "&$E70))+ISNUMBER(SEARCH(Ангилал!$I$5:$I$16,$G70&" "&$D70&" "&$E70))+ISNUMBER(SEARCH(Ангилал!$J$5:$J$16,$G70&" "&$D70&" "&$E70))+ISNUMBER(SEARCH(Ангилал!$K$5:$K$16,$G70&" "&$D70&" "&$E70))>0,0),0)),"Ерөнхий нийт"))} -> Ажилчид, хөдөлмөр эрхлэгчид | R70: =IF($G70="","",IF($Q70<>"",$Q70,$P70)) -> Ажилчид, хөдөлмөр эрхлэгчид
A71: 54 | B71: 2026.06.30 | C71: 2026.06.30 | D71: ХӨСҮТ: Улаанбурхан өвчний батлагдсан тохиолдол 11-ээр нэмэгдэж, улсын хэмжээнд 15,505-д хүрэв | E71: ХӨСҮТ-ийн мэдээллээр 2026.06.30-ны байдлаар улаанбурхан өвчний батлагдсан тохиолдол 11-ээр нэмэгдэж, улсын хэмжээнд нийт 15,505 (нийслэлд 12,379, орон нутагт 3,124) болж, нас баралт 22 бүртгэгдээд байна. Эмнэлэгт 30 хүн хэвтэн эмчлүүлж байгаа бөгөөд өвчлөл 10-14 насны хүүхдүүдийн дунд хамгийн өндөр (5,499) байна. | F71: Улсын хэмжээнд | G71: Эрүүл мэндээ хамгаалуулах эрх, хүүхдийн эрх | H71: Халдварт өвчний дэгдэлт /дархлаажуулалтын хамралт хангалтгүй байдал/ | I71: ХӨСҮТ өдөр бүр нөхцөл байдлыг мэдээлж, иргэдийг улаанбурханы эсрэг вакцинд хамрагдахыг уриалж байна | J71: МҮОНРТ, ХӨСҮТ | K71: https://www.mnb.mn/i/348493 | M71: {=IF($G71="","",IFERROR(INDEX(Ангилал!$A$5:$A$22,MATCH(TRUE(),INDEX(ISNUMBER(SEARCH(Ангилал!$B$5:$B$22,$G71&" "&$D71))+ISNUMBER(SEARCH(Ангилал!$C$5:$C$22,$G71&" "&$D71))+IF(Ангилал!$D$5:$D$22="",0,ISNUMBER(SEARCH(Ангилал!$D$5:$D$22,$G71&" "&$D71)))+IF(Ангилал!$E$5:$E$22="",0,ISNUMBER(SEARCH(Ангилал!$E$5:$E$22,$G71&" "&$D71)))>0,0),0)),"Бусад"))} -> Хүүхдийн эрх | O71: =IF($G71="","",IF($N71<>"",$N71,$M71)) -> Хүүхдийн эрх | P71: {=IF($G71="","",IFERROR(INDEX(Ангилал!$G$5:$G$16,MATCH(TRUE(),INDEX(ISNUMBER(SEARCH(Ангилал!$H$5:$H$16,$G71&" "&$D71&" "&$E71))+ISNUMBER(SEARCH(Ангилал!$I$5:$I$16,$G71&" "&$D71&" "&$E71))+ISNUMBER(SEARCH(Ангилал!$J$5:$J$16,$G71&" "&$D71&" "&$E71))+ISNUMBER(SEARCH(Ангилал!$K$5:$K$16,$G71&" "&$D71&" "&$E71))>0,0),0)),"Ерөнхий нийт"))} -> Хүүхэд | R71: =IF($G71="","",IF($Q71<>"",$Q71,$P71)) -> Хүүхэд
A72: 55 | B72: 2026.07.01 | C72: 2026.07.01 | D72: Гэр бүлийн тухай хуулийн шинэчилсэн найруулгыг УИХ-д өргөн барихаар боллоо | E72: Засгийн газрын хуралдаанаар Гэр бүлийн тухай хуулийн шинэчилсэн найруулгын төслийг хэлэлцэж, УИХ-д өргөн барихаар шийдвэрлэв. 1999 онд батлагдсан одоогийн хууль гэрлэх, гэрлэлт цуцлах, хүүхдийн эрхийг хамгаалах, хууль ёсны ашиг сонирхлыг сэргээх харилцааг нарийвчлан зохицуулж чадахгүй байгаа тул гэр бүлийн гишүүд, хүүхдийн эрх ашгийг хамгаалах эрх зүйн шинэ орчин бүрдүүлэхийг зорьжээ. | F72: Улаанбаатар хот, Засгийн газрын хуралдаан | G72: Гэр бүлийн гишүүдийн эрх, хүүхдийн эрх, шударга шүүхээр хамгаалуулах эрх | H72: - | I72: Засгийн газар хуулийн төслийг хэлэлцэн, УИХ-д өргөн мэдүүлэхээр шийдвэрлэв | J72: inews.mn | K72: https://www.inews.mn/a/46748 | M72: {=IF($G72="","",IFERROR(INDEX(Ангилал!$A$5:$A$22,MATCH(TRUE(),INDEX(ISNUMBER(SEARCH(Ангилал!$B$5:$B$22,$G72&" "&$D72))+ISNUMBER(SEARCH(Ангилал!$C$5:$C$22,$G72&" "&$D72))+IF(Ангилал!$D$5:$D$22="",0,ISNUMBER(SEARCH(Ангилал!$D$5:$D$22,$G72&" "&$D72)))+IF(Ангилал!$E$5:$E$22="",0,ISNUMBER(SEARCH(Ангилал!$E$5:$E$22,$G72&" "&$D72)))>0,0),0)),"Бусад"))} -> Хүүхдийн эрх | O72: =IF($G72="","",IF($N72<>"",$N72,$M72)) -> Хүүхдийн эрх | P72: {=IF($G72="","",IFERROR(INDEX(Ангилал!$G$5:$G$16,MATCH(TRUE(),INDEX(ISNUMBER(SEARCH(Ангилал!$H$5:$H$16,$G72&" "&$D72&" "&$E72))+ISNUMBER(SEARCH(Ангилал!$I$5:$I$16,$G72&" "&$D72&" "&$E72))+ISNUMBER(SEARCH(Ангилал!$J$5:$J$16,$G72&" "&$D72&" "&$E72))+ISNUMBER(SEARCH(Ангилал!$K$5:$K$16,$G72&" "&$D72&" "&$E72))>0,0),0)),"Ерөнхий нийт"))} -> Хүүхэд | R72: =IF($G72="","",IF($Q72<>"",$Q72,$P72)) -> Хүүхэд
A73: 56 | B73: 2026.07.02 | C73: 2026.07.02 | D73: ХӨСҮТ: Улаанбурхан өвчний батлагдсан тохиолдол 15,512 болж, нас баралт 22 хэвээр байна | E73: ХӨСҮТ-ийн мэдээллээр 2026.07.02-ны байдлаар улаанбурхан өвчний батлагдсан тохиолдол 4-өөр нэмэгдэж, улсын хэмжээнд нийт 15,512 (нийслэлд 12,382, орон нутагт 3,128) болов. Эмнэлэгт 24 хүн хэвтэн эмчлүүлж байгаа бөгөөд өвчлөл 10-14 насны хүүхдүүдийн дунд хамгийн өндөр хэвээр байна. Дэгдэлт үргэлжилж буй нь хүүхдийн эрүүл мэндээ хамгаалуулах эрхэд сөргөөр нөлөөлсөөр байна. | F73: Улсын хэмжээнд | G73: Эрүүл мэндээ хамгаалуулах эрх, хүүхдийн эрх | H73: Халдварт өвчний дэгдэлт /дархлаажуулалтын хамралт хангалтгүй байдал/ | I73: ХӨСҮТ нөхцөл байдлыг өдөр бүр мэдээлж, вакцинд хамрагдсан мэдээллээ цахим бүртгэлд бүртгүүлэхийг уриалж байна | J73: МҮОНРТ, ХӨСҮТ | K73: https://www.mnb.mn/i/348632 | M73: {=IF($G73="","",IFERROR(INDEX(Ангилал!$A$5:$A$22,MATCH(TRUE(),INDEX(ISNUMBER(SEARCH(Ангилал!$B$5:$B$22,$G73&" "&$D73))+ISNUMBER(SEARCH(Ангилал!$C$5:$C$22,$G73&" "&$D73))+IF(Ангилал!$D$5:$D$22="",0,ISNUMBER(SEARCH(Ангилал!$D$5:$D$22,$G73&" "&$D73)))+IF(Ангилал!$E$5:$E$22="",0,ISNUMBER(SEARCH(Ангилал!$E$5:$E$22,$G73&" "&$D73)))>0,0),0)),"Бусад"))} -> Хүүхдийн эрх | O73: =IF($G73="","",IF($N73<>"",$N73,$M73)) -> Хүүхдийн эрх | P73: {=IF($G73="","",IFERROR(INDEX(Ангилал!$G$5:$G$16,MATCH(TRUE(),INDEX(ISNUMBER(SEARCH(Ангилал!$H$5:$H$16,$G73&" "&$D73&" "&$E73))+ISNUMBER(SEARCH(Ангилал!$I$5:$I$16,$G73&" "&$D73&" "&$E73))+ISNUMBER(SEARCH(Ангилал!$J$5:$J$16,$G73&" "&$D73&" "&$E73))+ISNUMBER(SEARCH(Ангилал!$K$5:$K$16,$G73&" "&$D73&" "&$E73))>0,0),0)),"Ерөнхий нийт"))} -> Хүүхэд | R73: =IF($G73="","",IF($Q73<>"",$Q73,$P73)) -> Хүүхэд
A74: 57 | B74: 2026.07.01 | C74: 2026.06.29-07.02 | D74: Цагдаагийн 102 тусгай дугаарт өдөрт дунджаар 2200 орчим дуудлага, мэдээлэл бүртгэгдэж байна | E74: ЦЕГ-ын өдөр тутмын мэдээгээр 2026.06.29-нд 2164, 06.30-нд 2203, 07.01-нд 2253, 07.02-нд 2212 дуудлага, мэдээлэл 102 тусгай дугаарт бүртгэгдэв. Тухайлбал, 06.30-ны өдрийн дуудлагаас 679 нь зөрчлийн шинжтэй байв. Гэмт хэргийн шинжтэй үйлдлүүдийг шуурхай илрүүлж, урьд өмнө бүртгэгдсэн хэргүүдийг нөхөн илрүүлсэн байна. | F74: Улсын хэмжээнд | G74: Амар тайван, аюулгүй орчинд амьдрах эрх, халдашгүй чөлөөтэй байх эрх | H74: Гэмт хэрэг, зөрчил үйлдсэн этгээдүүд | I74: Цагдаагийн байгууллага дуудлага тус бүрд шуурхай ажиллаж, гэмт хэрэг, зөрчлийг шалган шийдвэрлэж байна | J74: ЦЕГ, МҮОНРТ | K74: https://www.mnb.mn/i/348568 | M74: {=IF($G74="","",IFERROR(INDEX(Ангилал!$A$5:$A$22,MATCH(TRUE(),INDEX(ISNUMBER(SEARCH(Ангилал!$B$5:$B$22,$G74&" "&$D74))+ISNUMBER(SEARCH(Ангилал!$C$5:$C$22,$G74&" "&$D74))+IF(Ангилал!$D$5:$D$22="",0,ISNUMBER(SEARCH(Ангилал!$D$5:$D$22,$G74&" "&$D74)))+IF(Ангилал!$E$5:$E$22="",0,ISNUMBER(SEARCH(Ангилал!$E$5:$E$22,$G74&" "&$D74)))>0,0),0)),"Бусад"))} -> Амьд явах, халдашгүй байх эрх | O74: =IF($G74="","",IF($N74<>"",$N74,$M74)) -> Амьд явах, халдашгүй байх эрх | P74: {=IF($G74="","",IFERROR(INDEX(Ангилал!$G$5:$G$16,MATCH(TRUE(),INDEX(ISNUMBER(SEARCH(Ангилал!$H$5:$H$16,$G74&" "&$D74&" "&$E74))+ISNUMBER(SEARCH(Ангилал!$I$5:$I$16,$G74&" "&$D74&" "&$E74))+ISNUMBER(SEARCH(Ангилал!$J$5:$J$16,$G74&" "&$D74&" "&$E74))+ISNUMBER(SEARCH(Ангилал!$K$5:$K$16,$G74&" "&$D74&" "&$E74))>0,0),0)),"Ерөнхий нийт"))} -> Ерөнхий нийт | R74: =IF($G74="","",IF($Q74<>"",$Q74,$P74)) -> Ерөнхий нийт
A75: 58 | B75: 2026.07.02 | C75: 2026.07.02 | D75: Хурдан морины уралдаанч хүүхдийн аюулгүй байдлыг хангах чиглэлээр ажиллаж байна | E75: Наадам дөхөж буйтай холбогдуулан уралдаанч хүүхдийг зориулалтын хамгаалалтын хувцас, хэрэглэлгүй уралдуулах, зориулалтын бус гутал өмсгөх, гутлыг скочоор бэхэлж уралдаанд гаргах зэрэг хүүхдийн эрх, аюулгүй байдлын зөрчил цөөнгүй бүртгэгддэг болохыг ХГБХХЕГ мэдээлэв. Уралдааны зам, талбайд эрсдэлийн үнэлгээ хийж, зөвлөмжийг Наадмыг зохион байгуулах хороо, Хурдан морины салбар комисст хүргүүлж, MNS 6264:2026 стандартыг сурталчилж байна. | F75: Улсын хэмжээнд /наадмын хурдан морины уралдаан/ | G75: Хүүхдийн эрх, амьд явах эрх, эрүүл, аюулгүй орчинд байх эрх, хүүхдийг тэвчишгүй хөдөлмөрөөс хамгаалах | H75: Уяач, морь эзэмшигчид, уралдаан зохион байгуулагчид, эцэг эх, асран хамгаалагчид | I75: ХГБХХЕГ эрсдэлийн үнэлгээ хийж, зөвлөмж хүргүүлэн, стандартын хэрэгжилтэд хяналт тавин ажиллаж байна | J75: ХГБХХЕГ, МҮОНРТ | K75: https://www.mnb.mn/i/348642 | M75: {=IF($G75="","",IFERROR(INDEX(Ангилал!$A$5:$A$22,MATCH(TRUE(),INDEX(ISNUMBER(SEARCH(Ангилал!$B$5:$B$22,$G75&" "&$D75))+ISNUMBER(SEARCH(Ангилал!$C$5:$C$22,$G75&" "&$D75))+IF(Ангилал!$D$5:$D$22="",0,ISNUMBER(SEARCH(Ангилал!$D$5:$D$22,$G75&" "&$D75)))+IF(Ангилал!$E$5:$E$22="",0,ISNUMBER(SEARCH(Ангилал!$E$5:$E$22,$G75&" "&$D75)))>0,0),0)),"Бусад"))} -> Хүүхдийн эрх | O75: =IF($G75="","",IF($N75<>"",$N75,$M75)) -> Хүүхдийн эрх | P75: {=IF($G75="","",IFERROR(INDEX(Ангилал!$G$5:$G$16,MATCH(TRUE(),INDEX(ISNUMBER(SEARCH(Ангилал!$H$5:$H$16,$G75&" "&$D75&" "&$E75))+ISNUMBER(SEARCH(Ангилал!$I$5:$I$16,$G75&" "&$D75&" "&$E75))+ISNUMBER(SEARCH(Ангилал!$J$5:$J$16,$G75&" "&$D75&" "&$E75))+ISNUMBER(SEARCH(Ангилал!$K$5:$K$16,$G75&" "&$D75&" "&$E75))>0,0),0)),"Ерөнхий нийт"))} -> Хүүхэд | R75: =IF($G75="","",IF($Q75<>"",$Q75,$P75)) -> Хүүхэд
A76: 59 | B76: 2026.07.01 | C76: 2026.07.01 | D76: Нийгмийн даатгалын ерөнхий хуульд нэмэлт, өөрчлөлт оруулах тухай хууль батлагдлаа | E76: УИХ-ын чуулганы нэгдсэн хуралдаанаар Нийгмийн даатгалын ерөнхий хуульд нэмэлт, өөрчлөлт оруулах тухай хуулийг 2026.07.01-ний өдөр баталлаа. Иргэдийн нийгмийн даатгал, тэтгэвэр, тэтгэмжийн эрхийн хэрэгжилттэй шууд холбоотой хууль тогтоомжийн өөрчлөлт юм. | F76: Улаанбаатар хот, Төрийн ордон | G76: Нийгмийн хамгааллын эрх, тэтгэвэр, тэтгэмж авах эрх | H76: - | I76: УИХ хуулийг баталж, эрх зүйн орчныг шинэчлэв | J76: МҮОНРТ | K76: https://www.mnb.mn/i/348608 | M76: {=IF($G76="","",IFERROR(INDEX(Ангилал!$A$5:$A$22,MATCH(TRUE(),INDEX(ISNUMBER(SEARCH(Ангилал!$B$5:$B$22,$G76&" "&$D76))+ISNUMBER(SEARCH(Ангилал!$C$5:$C$22,$G76&" "&$D76))+IF(Ангилал!$D$5:$D$22="",0,ISNUMBER(SEARCH(Ангилал!$D$5:$D$22,$G76&" "&$D76)))+IF(Ангилал!$E$5:$E$22="",0,ISNUMBER(SEARCH(Ангилал!$E$5:$E$22,$G76&" "&$D76)))>0,0),0)),"Бусад"))} -> Нийгмийн хамгаалал, халамжийн эрх | O76: =IF($G76="","",IF($N76<>"",$N76,$M76)) -> Нийгмийн хамгаалал, халамжийн эрх | P76: {=IF($G76="","",IFERROR(INDEX(Ангилал!$G$5:$G$16,MATCH(TRUE(),INDEX(ISNUMBER(SEARCH(Ангилал!$H$5:$H$16,$G76&" "&$D76&" "&$E76))+ISNUMBER(SEARCH(Ангилал!$I$5:$I$16,$G76&" "&$D76&" "&$E76))+ISNUMBER(SEARCH(Ангилал!$J$5:$J$16,$G76&" "&$D76&" "&$E76))+ISNUMBER(SEARCH(Ангилал!$K$5:$K$16,$G76&" "&$D76&" "&$E76))>0,0),0)),"Ерөнхий нийт"))} -> Ерөнхий нийт | R76: =IF($G76="","",IF($Q76<>"",$Q76,$P76)) -> Ерөнхий нийт
A77: 60 | B77: 2026.07.02 | C77: 2026.07.02 | D77: Малын эмийг хууль бусаар худалдаалсан 189 сая төгрөгийн үнэ бүхий зөрчил илрүүлэв | E77: Хууль бусаар худалдаалсан 189 сая төгрөгийн үнэ бүхий малын эмийг эрх бүхий байгууллагаас илрүүлж, холбогдох арга хэмжээг авч байгааг мэдээлэв. Хяналтгүй, хууль бус эмийн эргэлт нь малын гаралтай хүнсний аюулгүй байдал, улмаар хүн амын эрүүл мэндэд эрсдэл учруулдаг. | F77: Улсын хэмжээнд | G77: Эрүүл мэндээ хамгаалуулах эрх, эрүүл, аюулгүй орчинд амьдрах эрх, хэрэглэгчийн эрх | H77: Малын эмийг хууль бусаар худалдаалсан этгээдүүд | I77: Эрх бүхий байгууллага зөрчлийг илрүүлж, шалган шийдвэрлэх ажиллагаа явуулж байна | J77: МҮОНРТ | K77: https://www.mnb.mn/i/348615 | M77: {=IF($G77="","",IFERROR(INDEX(Ангилал!$A$5:$A$22,MATCH(TRUE(),INDEX(ISNUMBER(SEARCH(Ангилал!$B$5:$B$22,$G77&" "&$D77))+ISNUMBER(SEARCH(Ангилал!$C$5:$C$22,$G77&" "&$D77))+IF(Ангилал!$D$5:$D$22="",0,ISNUMBER(SEARCH(Ангилал!$D$5:$D$22,$G77&" "&$D77)))+IF(Ангилал!$E$5:$E$22="",0,ISNUMBER(SEARCH(Ангилал!$E$5:$E$22,$G77&" "&$D77)))>0,0),0)),"Бусад"))} -> Эрүүл мэндийн эрх | O77: =IF($G77="","",IF($N77<>"",$N77,$M77)) -> Эрүүл мэндийн эрх | P77: {=IF($G77="","",IFERROR(INDEX(Ангилал!$G$5:$G$16,MATCH(TRUE(),INDEX(ISNUMBER(SEARCH(Ангилал!$H$5:$H$16,$G77&" "&$D77&" "&$E77))+ISNUMBER(SEARCH(Ангилал!$I$5:$I$16,$G77&" "&$D77&" "&$E77))+ISNUMBER(SEARCH(Ангилал!$J$5:$J$16,$G77&" "&$D77&" "&$E77))+ISNUMBER(SEARCH(Ангилал!$K$5:$K$16,$G77&" "&$D77&" "&$E77))>0,0),0)),"Ерөнхий нийт"))} -> Ерөнхий нийт | R77: =IF($G77="","",IF($Q77<>"",$Q77,$P77)) -> Ерөнхий нийт
A78: 61 | B78: 2026.07.02 | C78: 2026.07.02 | D78: Улс төрийн хилс хэрэгт хэлмэгдэгчдийг цагаатгах асуудлаар арга хэмжээ авч байна | E78: Улс төрийн хилс хэрэгт хэлмэгдэгчдийг цагаатгах, тэдэнд нөхөн олговор олгох чиглэлээр төрөөс авч хэрэгжүүлж буй арга хэмжээний талаар 2026.07.02-ны өдөр мэдээлэв. Хэлмэгдэгчдийн болон тэдний ар гэрийн цагаатгуулах, нөхөн сэргээлт хийлгэх эрхийн хэрэгжилттэй холбоотой асуудал юм. | F78: Улаанбаатар хот | G78: Шударга шүүхээр шүүлгэх эрх, цагаатгуулах, нөхөн олговор авах эрх | H78: - | I78: Төрөөс цагаатгал, нөхөн олговрын чиглэлээр арга хэмжээ хэрэгжүүлж байна | J78: МҮОНРТ | K78: https://www.mnb.mn/i/348648 | M78: {=IF($G78="","",IFERROR(INDEX(Ангилал!$A$5:$A$22,MATCH(TRUE(),INDEX(ISNUMBER(SEARCH(Ангилал!$B$5:$B$22,$G78&" "&$D78))+ISNUMBER(SEARCH(Ангилал!$C$5:$C$22,$G78&" "&$D78))+IF(Ангилал!$D$5:$D$22="",0,ISNUMBER(SEARCH(Ангилал!$D$5:$D$22,$G78&" "&$D78)))+IF(Ангилал!$E$5:$E$22="",0,ISNUMBER(SEARCH(Ангилал!$E$5:$E$22,$G78&" "&$D78)))>0,0),0)),"Бусад"))} -> Шударга шүүхээр шүүлгэх эрх | O78: =IF($G78="","",IF($N78<>"",$N78,$M78)) -> Шударга шүүхээр шүүлгэх эрх | P78: {=IF($G78="","",IFERROR(INDEX(Ангилал!$G$5:$G$16,MATCH(TRUE(),INDEX(ISNUMBER(SEARCH(Ангилал!$H$5:$H$16,$G78&" "&$D78&" "&$E78))+ISNUMBER(SEARCH(Ангилал!$I$5:$I$16,$G78&" "&$D78&" "&$E78))+ISNUMBER(SEARCH(Ангилал!$J$5:$J$16,$G78&" "&$D78&" "&$E78))+ISNUMBER(SEARCH(Ангилал!$K$5:$K$16,$G78&" "&$D78&" "&$E78))>0,0),0)),"Ерөнхий нийт"))} -> Ерөнхий нийт | R78: =IF($G78="","",IF($Q78<>"",$Q78,$P78)) -> Ерөнхий нийт
A79: 2026.07.06-07.09 | M79: {=IF($G79="","",IFERROR(INDEX(Ангилал!$A$5:$A$22,MATCH(TRUE(),INDEX(ISNUMBER(SEARCH(Ангилал!$B$5:$B$22,$G79&" "&$D79))+ISNUMBER(SEARCH(Ангилал!$C$5:$C$22,$G79&" "&$D79))+IF(Ангилал!$D$5:$D$22="",0,ISNUMBER(SEARCH(Ангилал!$D$5:$D$22,$G79&" "&$D79)))+IF(Ангилал!$E$5:$E$22="",0,ISNUMBER(SEARCH(Ангилал!$E$5:$E$22,$G79&" "&$D79)))>0,0),0)),"Бусад"))} | O79: =IF($G79="","",IF($N79<>"",$N79,$M79)) | P79: {=IF($G79="","",IFERROR(INDEX(Ангилал!$G$5:$G$16,MATCH(TRUE(),INDEX(ISNUMBER(SEARCH(Ангилал!$H$5:$H$16,$G79&" "&$D79&" "&$E79))+ISNUMBER(SEARCH(Ангилал!$I$5:$I$16,$G79&" "&$D79&" "&$E79))+ISNUMBER(SEARCH(Ангилал!$J$5:$J$16,$G79&" "&$D79&" "&$E79))+ISNUMBER(SEARCH(Ангилал!$K$5:$K$16,$G79&" "&$D79&" "&$E79))>0,0),0)),"Ерөнхий нийт"))} | R79: =IF($G79="","",IF($Q79<>"",$Q79,$P79))
A80: 62 | B80: 2026.07.06 | C80: Одоогоос жил гаруй өмнө (2025 оны эхээр эсвэл 2024 оны сүүлээр) болсон. | D80: Үе тэнгийн дээрэлхэлтээс болж тархины хавдартай болсон хүү өвчиндөө шаналж байна | E80: М.Амарсайхан гэртээ харихаар явж байхад 10 гаруй хүүхэд бүлэглэн зодсон. Зодуулсны улмаас хүнд гэмтэл авч, тархины боргоцой булчирхайн гүний хавдартай болсон гэж эмч нар тайлбарласан. | F80: Улаанбаатар хот | G80: амьд явах, бие махбодын бүрэн бүтэн байдлыг хамгаалах, сурч боловсрох, аюулгүй орчинд амьдрах, хүчирхийллээс хамгаалуулах, буруута этгээдүүд хариуцлага хүлээгээгүй нь шударга шүүх, хууль ёсны хамгаалалт авах эрхийг зөрчсөн | H80: - | I80: - | J80: twitter | K80: https://x.com/mn_zarig/status/2073979269739639111?s=12 | M80: {=IF($G80="","",IFERROR(INDEX(Ангилал!$A$5:$A$22,MATCH(TRUE(),INDEX(ISNUMBER(SEARCH(Ангилал!$B$5:$B$22,$G80&" "&$D80))+ISNUMBER(SEARCH(Ангилал!$C$5:$C$22,$G80&" "&$D80))+IF(Ангилал!$D$5:$D$22="",0,ISNUMBER(SEARCH(Ангилал!$D$5:$D$22,$G80&" "&$D80)))+IF(Ангилал!$E$5:$E$22="",0,ISNUMBER(SEARCH(Ангилал!$E$5:$E$22,$G80&" "&$D80)))>0,0),0)),"Бусад"))} -> Амьд явах, халдашгүй байх эрх | O80: =IF($G80="","",IF($N80<>"",$N80,$M80)) -> Амьд явах, халдашгүй байх эрх | P80: {=IF($G80="","",IFERROR(INDEX(Ангилал!$G$5:$G$16,MATCH(TRUE(),INDEX(ISNUMBER(SEARCH(Ангилал!$H$5:$H$16,$G80&" "&$D80&" "&$E80))+ISNUMBER(SEARCH(Ангилал!$I$5:$I$16,$G80&" "&$D80&" "&$E80))+ISNUMBER(SEARCH(Ангилал!$J$5:$J$16,$G80&" "&$D80&" "&$E80))+ISNUMBER(SEARCH(Ангилал!$K$5:$K$16,$G80&" "&$D80&" "&$E80))>0,0),0)),"Ерөнхий нийт"))} -> Өвчтөн, эмчлүүлэгч | R80: =IF($G80="","",IF($Q80<>"",$Q80,$P80)) -> Өвчтөн, эмчлүүлэгч
A81: 63 | B81: 2026.07.08 | D81: Ч.Ууганбаяр: Хоол ундаа газар хийх нь бага насны хүүхэд түлэгдэх шалтгаан болж байна | E81: Эмнэлгийн байгууллагын мэдээллээр бага насны хүүхдүүд гэрийн орчинд халуун хоол, ундааг шалан дээр тавьснаас болж түлэгдэх тохиолдол олон гарч байна. | F81: Улсын хэмжээнд (ахуйн орчин) | G81: Хүүхдийн эрүүл мэндээ хамгаалуулах, аюулгүй орчинд амьдрах | H81: Эцэг эх, асран хамгаалагчийн хяналт, ахуйн аюулгүй байдлын дутагдал | I81: Эрүүл мэндийн байгууллагаас мэдээлэл, зөвлөмж хүргэсэн | J81: ikon.mn | K81: https://ikon.mn/n/3ouo | M81: {=IF($G81="","",IFERROR(INDEX(Ангилал!$A$5:$A$22,MATCH(TRUE(),INDEX(ISNUMBER(SEARCH(Ангилал!$B$5:$B$22,$G81&" "&$D81))+ISNUMBER(SEARCH(Ангилал!$C$5:$C$22,$G81&" "&$D81))+IF(Ангилал!$D$5:$D$22="",0,ISNUMBER(SEARCH(Ангилал!$D$5:$D$22,$G81&" "&$D81)))+IF(Ангилал!$E$5:$E$22="",0,ISNUMBER(SEARCH(Ангилал!$E$5:$E$22,$G81&" "&$D81)))>0,0),0)),"Бусад"))} -> Хүүхдийн эрх | O81: =IF($G81="","",IF($N81<>"",$N81,$M81)) -> Хүүхдийн эрх | P81: {=IF($G81="","",IFERROR(INDEX(Ангилал!$G$5:$G$16,MATCH(TRUE(),INDEX(ISNUMBER(SEARCH(Ангилал!$H$5:$H$16,$G81&" "&$D81&" "&$E81))+ISNUMBER(SEARCH(Ангилал!$I$5:$I$16,$G81&" "&$D81&" "&$E81))+ISNUMBER(SEARCH(Ангилал!$J$5:$J$16,$G81&" "&$D81&" "&$E81))+ISNUMBER(SEARCH(Ангилал!$K$5:$K$16,$G81&" "&$D81&" "&$E81))>0,0),0)),"Ерөнхий нийт"))} -> Хүүхэд | R81: =IF($G81="","",IF($Q81<>"",$Q81,$P81)) -> Хүүхэд
A82: 2026.07.10-07.24 | M82: {=IF($G82="","",IFERROR(INDEX(Ангилал!$A$5:$A$22,MATCH(TRUE(),INDEX(ISNUMBER(SEARCH(Ангилал!$B$5:$B$22,$G82&" "&$D82))+ISNUMBER(SEARCH(Ангилал!$C$5:$C$22,$G82&" "&$D82))+IF(Ангилал!$D$5:$D$22="",0,ISNUMBER(SEARCH(Ангилал!$D$5:$D$22,$G82&" "&$D82)))+IF(Ангилал!$E$5:$E$22="",0,ISNUMBER(SEARCH(Ангилал!$E$5:$E$22,$G82&" "&$D82)))>0,0),0)),"Бусад"))} | O82: =IF($G82="","",IF($N82<>"",$N82,$M82)) | P82: {=IF($G82="","",IFERROR(INDEX(Ангилал!$G$5:$G$16,MATCH(TRUE(),INDEX(ISNUMBER(SEARCH(Ангилал!$H$5:$H$16,$G82&" "&$D82&" "&$E82))+ISNUMBER(SEARCH(Ангилал!$I$5:$I$16,$G82&" "&$D82&" "&$E82))+ISNUMBER(SEARCH(Ангилал!$J$5:$J$16,$G82&" "&$D82&" "&$E82))+ISNUMBER(SEARCH(Ангилал!$K$5:$K$16,$G82&" "&$D82&" "&$E82))>0,0),0)),"Ерөнхий нийт"))} | R82: =IF($G82="","",IF($Q82<>"",$Q82,$P82))
A83: 64 | B83: 2026.07.16 | C83: 2026.07.10-07.14 | D83: Наадмын өдрүүдэд зөрчлийн шинжтэй 3,227, гэмт хэргийн шинжтэй 488 дуудлага, мэдээлэл бүртгэгджээ | E83: Цагдаагийн байгууллагын 102 тусгай дугаарт Үндэсний их баяр наадмын өдрүүдэд нийт 9,446 дуудлага, мэдээлэл бүртгэгдсэн. Үүнээс зөрчлийн шинжтэй 3,227, гэмт хэргийн шинжтэй 488, залилах гэмт хэргийн 67, хүүхэд гэр бүлийн хүчирхийллийн 351, хулгайлах 79 дуудлага байна. Мөн согтуугаар тээврийн хэрэгсэл жолоодсон 317 тохиолдол гарч, 414 хүнийг эрүүлжүүлсэн. | F83: Улсын хэмжээнд | G83: Хүчирхийлэл, хэрцгий харьцаанаас ангид байх эрх, амьд явах эрх, эд хөрөнгийн эрх, хүүхдийн хамгаалуулах эрх | H83: Хувь хүн /гэр бүлийн гишүүн, бусад иргэн/ | I83: Цагдаагийн байгууллага дуудлага хүлээн авч шалгасан | J83: ikon.mn | K83: https://ikon.mn/n/3p09 | M83: {=IF($G83="","",IFERROR(INDEX(Ангилал!$A$5:$A$22,MATCH(TRUE(),INDEX(ISNUMBER(SEARCH(Ангилал!$B$5:$B$22,$G83&" "&$D83))+ISNUMBER(SEARCH(Ангилал!$C$5:$C$22,$G83&" "&$D83))+IF(Ангилал!$D$5:$D$22="",0,ISNUMBER(SEARCH(Ангилал!$D$5:$D$22,$G83&" "&$D83)))+IF(Ангилал!$E$5:$E$22="",0,ISNUMBER(SEARCH(Ангилал!$E$5:$E$22,$G83&" "&$D83)))>0,0),0)),"Бусад"))} -> Хүүхдийн эрх | O83: =IF($G83="","",IF($N83<>"",$N83,$M83)) -> Хүүхдийн эрх | P83: {=IF($G83="","",IFERROR(INDEX(Ангилал!$G$5:$G$16,MATCH(TRUE(),INDEX(ISNUMBER(SEARCH(Ангилал!$H$5:$H$16,$G83&" "&$D83&" "&$E83))+ISNUMBER(SEARCH(Ангилал!$I$5:$I$16,$G83&" "&$D83&" "&$E83))+ISNUMBER(SEARCH(Ангилал!$J$5:$J$16,$G83&" "&$D83&" "&$E83))+ISNUMBER(SEARCH(Ангилал!$K$5:$K$16,$G83&" "&$D83&" "&$E83))>0,0),0)),"Ерөнхий нийт"))} -> Хүүхэд | R83: =IF($G83="","",IF($Q83<>"",$Q83,$P83)) -> Хүүхэд
A84: 65 | B84: 2026.07.20 | C84: 2026.01.01-07.20 | D84: Усны ослын 30 орчим хувь нь эцэг эхийн хараа хяналт, архидан согтуурснаас үүдэлтэй | E84: 2026 он гарсаар долоодугаар сарын 20-ны байдлаар усны ослын 84 тохиолдол бүртгэгдэж, 50 хүн (31 том хүн, 19 хүүхэд) амь насаа алдсан. Өмнөх оны мөн үетэй харьцуулахад нас барсан хүний тоо 12 хувиар өссөн. Усны осол ихээр гардаг 399 хар цэг тэмдэглэсэн бөгөөд урьдчилан сэргийлэх хөдөлгөөнт эргүүлийг зургаадугаар сарын 15-наас эхлүүлсэн. | F84: Улсын хэмжээнд /Нийслэл, Сэлэнгэ, Хөвсгөл, Увс, Дорнод, Баян-Өлгий/ | G84: Амьд явах эрх, хүүхдийн хамгаалуулах эрх, аюулгүй орчинд амьдрах эрх | H84: Эцэг эх, асран хамгаалагч; орон нутгийн засаг захиргаа | I84: ОБЕГ-аас хар цэг тэмдэглэж, хөдөлгөөнт эргүүл ажиллуулсан | J84: arslan.mn | K84: https://www.arslan.mn/social/news/669929.shtml | M84: {=IF($G84="","",IFERROR(INDEX(Ангилал!$A$5:$A$22,MATCH(TRUE(),INDEX(ISNUMBER(SEARCH(Ангилал!$B$5:$B$22,$G84&" "&$D84))+ISNUMBER(SEARCH(Ангилал!$C$5:$C$22,$G84&" "&$D84))+IF(Ангилал!$D$5:$D$22="",0,ISNUMBER(SEARCH(Ангилал!$D$5:$D$22,$G84&" "&$D84)))+IF(Ангилал!$E$5:$E$22="",0,ISNUMBER(SEARCH(Ангилал!$E$5:$E$22,$G84&" "&$D84)))>0,0),0)),"Бусад"))} -> Хүүхдийн эрх | O84: =IF($G84="","",IF($N84<>"",$N84,$M84)) -> Хүүхдийн эрх | P84: {=IF($G84="","",IFERROR(INDEX(Ангилал!$G$5:$G$16,MATCH(TRUE(),INDEX(ISNUMBER(SEARCH(Ангилал!$H$5:$H$16,$G84&" "&$D84&" "&$E84))+ISNUMBER(SEARCH(Ангилал!$I$5:$I$16,$G84&" "&$D84&" "&$E84))+ISNUMBER(SEARCH(Ангилал!$J$5:$J$16,$G84&" "&$D84&" "&$E84))+ISNUMBER(SEARCH(Ангилал!$K$5:$K$16,$G84&" "&$D84&" "&$E84))>0,0),0)),"Ерөнхий нийт"))} -> Хүүхэд | R84: =IF($G84="","",IF($Q84<>"",$Q84,$P84)) -> Хүүхэд
A85: 66 | B85: 2026.07.24 | C85: 2026.07.24 | D85: Хүүхдүүд тоглох эрхээ булгаалгасан уу? | E85: Нарны хорооллын 141-р сургуулийн хөлбөмбөгийн талбайг хашаалчихаж ээ. Өргөтгөл барина гэнэ. Хүүхдүүдээсээ талбай булаадаг иргэдтэй улс Монголоос өөр байдаг болов уу? | F85: Баянгол дүүрэг | G85: Хүүхдийн эрүүл, аюулгүй орчинд амьдрах эрх Хүүхдийн амрах, чөлөөт цагаа зөв боловсон өнгөрүүлэх эрх Хүүхдийн тоглох, бие бялдраа хөгжүүлэх эрх Хүүхдийн боловсрол эзэмших эрх Хүүхдийн ашиг сонирхлоо хамгаалуулах эрх Нийтийн эзэмшлийн орон зайг ашиглах эрх | H85: - | I85: - | J85: ubn.mn | K85: https://www.facebook.com/reel/1561941138820371 | M85: {=IF($G85="","",IFERROR(INDEX(Ангилал!$A$5:$A$22,MATCH(TRUE(),INDEX(ISNUMBER(SEARCH(Ангилал!$B$5:$B$22,$G85&" "&$D85))+ISNUMBER(SEARCH(Ангилал!$C$5:$C$22,$G85&" "&$D85))+IF(Ангилал!$D$5:$D$22="",0,ISNUMBER(SEARCH(Ангилал!$D$5:$D$22,$G85&" "&$D85)))+IF(Ангилал!$E$5:$E$22="",0,ISNUMBER(SEARCH(Ангилал!$E$5:$E$22,$G85&" "&$D85)))>0,0),0)),"Бусад"))} -> Хүүхдийн эрх | O85: =IF($G85="","",IF($N85<>"",$N85,$M85)) -> Хүүхдийн эрх | P85: {=IF($G85="","",IFERROR(INDEX(Ангилал!$G$5:$G$16,MATCH(TRUE(),INDEX(ISNUMBER(SEARCH(Ангилал!$H$5:$H$16,$G85&" "&$D85&" "&$E85))+ISNUMBER(SEARCH(Ангилал!$I$5:$I$16,$G85&" "&$D85&" "&$E85))+ISNUMBER(SEARCH(Ангилал!$J$5:$J$16,$G85&" "&$D85&" "&$E85))+ISNUMBER(SEARCH(Ангилал!$K$5:$K$16,$G85&" "&$D85&" "&$E85))>0,0),0)),"Ерөнхий нийт"))} -> Хүүхэд | R85: =IF($G85="","",IF($Q85<>"",$Q85,$P85)) -> Хүүхэд
A86: 2026.07.27-07.31 | M86: {=IF($G86="","",IFERROR(INDEX(Ангилал!$A$5:$A$22,MATCH(TRUE(),INDEX(ISNUMBER(SEARCH(Ангилал!$B$5:$B$22,$G86&" "&$D86))+ISNUMBER(SEARCH(Ангилал!$C$5:$C$22,$G86&" "&$D86))+IF(Ангилал!$D$5:$D$22="",0,ISNUMBER(SEARCH(Ангилал!$D$5:$D$22,$G86&" "&$D86)))+IF(Ангилал!$E$5:$E$22="",0,ISNUMBER(SEARCH(Ангилал!$E$5:$E$22,$G86&" "&$D86)))>0,0),0)),"Бусад"))} | O86: =IF($G86="","",IF($N86<>"",$N86,$M86)) | P86: {=IF($G86="","",IFERROR(INDEX(Ангилал!$G$5:$G$16,MATCH(TRUE(),INDEX(ISNUMBER(SEARCH(Ангилал!$H$5:$H$16,$G86&" "&$D86&" "&$E86))+ISNUMBER(SEARCH(Ангилал!$I$5:$I$16,$G86&" "&$D86&" "&$E86))+ISNUMBER(SEARCH(Ангилал!$J$5:$J$16,$G86&" "&$D86&" "&$E86))+ISNUMBER(SEARCH(Ангилал!$K$5:$K$16,$G86&" "&$D86&" "&$E86))>0,0),0)),"Ерөнхий нийт"))} | R86: =IF($G86="","",IF($Q86<>"",$Q86,$P86))
A87: 67 | B87: 2026.07.29 | C87: 2026.07.28-07.30 | D87: Үерийн аюулаас сэрэмжлүүлж байна. | E87: 2026.07.29-ний байдлаар Тэрэлж, Туул /Лүн/, Сөгнөгөр, Байдраг /Бууцагаан сумын Баянбүрд баг/, Хөгшин Орхон, Хархираа /Тариалан сум/ голууд үерийн түвшинг 5-50 см давж хүчтэй үерлэсэн. Долдугаар сарын 30-нд Туул гол Улаанбаатар хот орчимд усны түвшин 65 см нэмэгдэж, үерийн түвшинг даван үерлэх төлөвтэй байгааг мэдээлж, гол мөрний сав дагуу амарч байгаа иргэдийг сэрэмжлүүлсэн. Мөн Туул голын салаанд хоёр автомашинтай иргэд боогдож, аврагдсан. | F87: Улсын хэмжээнд /Улаанбаатар, Төв, Өвөрхангай, Баянхонгор, Увс аймаг/ | G87: Амьд явах эрх, эрүүл, аюулгүй орчинд амьдрах эрх, өмч хөрөнгөө эзэмших, хамгаалуулах эрх | H87: Байгалийн гамшигт үзэгдэл; гамшгаас урьдчилан сэргийлэх, хамгаалах чиг үүрэг бүхий байгууллага, орон нутгийн засаг захиргаа | I87: ОБЕГ, аймаг, нийслэлийн Онцгой байдлын газраас сэрэмжлүүлэг хүргэж, хөдөлгөөнт болон завьт эргүүл ажиллуулсан. Нийслэл, дүүргийн шуурхай штабууд хүч, хэрэгслээ бэлэн байдалд шилжүүлж, борооны ус тогтсон байршлуудад ус соруулах ажиллагаа явуулсан. | J87: МҮОНРТ /MNB.mn/ | K87: https://www.mnb.mn/i/349859 | M87: {=IF($G87="","",IFERROR(INDEX(Ангилал!$A$5:$A$22,MATCH(TRUE(),INDEX(ISNUMBER(SEARCH(Ангилал!$B$5:$B$22,$G87&" "&$D87))+ISNUMBER(SEARCH(Ангилал!$C$5:$C$22,$G87&" "&$D87))+IF(Ангилал!$D$5:$D$22="",0,ISNUMBER(SEARCH(Ангилал!$D$5:$D$22,$G87&" "&$D87)))+IF(Ангилал!$E$5:$E$22="",0,ISNUMBER(SEARCH(Ангилал!$E$5:$E$22,$G87&" "&$D87)))>0,0),0)),"Бусад"))} -> Амьд явах, халдашгүй байх эрх | O87: =IF($G87="","",IF($N87<>"",$N87,$M87)) -> Амьд явах, халдашгүй байх эрх | P87: {=IF($G87="","",IFERROR(INDEX(Ангилал!$G$5:$G$16,MATCH(TRUE(),INDEX(ISNUMBER(SEARCH(Ангилал!$H$5:$H$16,$G87&" "&$D87&" "&$E87))+ISNUMBER(SEARCH(Ангилал!$I$5:$I$16,$G87&" "&$D87&" "&$E87))+ISNUMBER(SEARCH(Ангилал!$J$5:$J$16,$G87&" "&$D87&" "&$E87))+ISNUMBER(SEARCH(Ангилал!$K$5:$K$16,$G87&" "&$D87&" "&$E87))>0,0),0)),"Ерөнхий нийт"))} -> Ерөнхий нийт | R87: =IF($G87="","",IF($Q87<>"",$Q87,$P87)) -> Ерөнхий нийт
A88: 68 | B88: 2026.07.30 | C88: 2026.07.29-30-нд шилжих шөнө | D88: Голден парк хотхоны гадаа зодолдсон гэх мэдээллийг шалгаж байна | E88: “Баянгол дүүргийн Голден парк хотхоны гадаа залуус зодолдоод байна” гэх дуудлага цагдаагийн байгууллагад бүртгэгдсэн. Мөн согтуугаар автомашины цонх цохиж, иргэдийн амгалан тайван байдлыг алдагдуулж, хоорондоо зодолдсон гэх агуулга бүхий бичлэг цахим орчинд тархсан. | F88: Баянгол дүүрэг | G88: Амьд явах эрх, халдашгүй чөлөөтэй байх эрх, бие махбодын болон сэтгэцийн халдашгүй байдал, аюулгүй, амар тайван орчинд амьдрах эрх | H88: Хувь хүн /зодоонд оролцсон иргэд/ | I88: Цагдаагийн байгууллага шуурхай шалгалтын ажиллагаа явуулж, холбогдогчдыг олж тогтоон саатуулж, шалгалт үргэлжилж байна. | J88: ЦЕГ-ын Хэвлэл, мэдээллийн төв; МҮОНРТ | K88: https://www.mnb.mn/i/349916 | M88: {=IF($G88="","",IFERROR(INDEX(Ангилал!$A$5:$A$22,MATCH(TRUE(),INDEX(ISNUMBER(SEARCH(Ангилал!$B$5:$B$22,$G88&" "&$D88))+ISNUMBER(SEARCH(Ангилал!$C$5:$C$22,$G88&" "&$D88))+IF(Ангилал!$D$5:$D$22="",0,ISNUMBER(SEARCH(Ангилал!$D$5:$D$22,$G88&" "&$D88)))+IF(Ангилал!$E$5:$E$22="",0,ISNUMBER(SEARCH(Ангилал!$E$5:$E$22,$G88&" "&$D88)))>0,0),0)),"Бусад"))} -> Амьд явах, халдашгүй байх эрх | O88: =IF($G88="","",IF($N88<>"",$N88,$M88)) -> Амьд явах, халдашгүй байх эрх | P88: {=IF($G88="","",IFERROR(INDEX(Ангилал!$G$5:$G$16,MATCH(TRUE(),INDEX(ISNUMBER(SEARCH(Ангилал!$H$5:$H$16,$G88&" "&$D88&" "&$E88))+ISNUMBER(SEARCH(Ангилал!$I$5:$I$16,$G88&" "&$D88&" "&$E88))+ISNUMBER(SEARCH(Ангилал!$J$5:$J$16,$G88&" "&$D88&" "&$E88))+ISNUMBER(SEARCH(Ангилал!$K$5:$K$16,$G88&" "&$D88&" "&$E88))>0,0),0)),"Ерөнхий нийт"))} -> Ерөнхий нийт | R88: =IF($G88="","",IF($Q88<>"",$Q88,$P88)) -> Ерөнхий нийт
A89: 69 | B89: 2026.07.30 | C89: 2026.07.20-07.31 | D89: Шатахууны хомсдол үүсч, иргэдэд буруу мэдээлэл өгсөн гэх шүүмжлэл гарав | E89: Дотоодын зах зээлд шатахууны хомсдол үүссэнтэй холбогдуулан “Бензиний үнэ нэмэгдэхгүй, олон хоногийн нөөцтэй гэж иргэдэд худал мэдээлэл өгсөн сайд нарт хэзээ хариуцлага тооцох вэ” гэсэн шүүмжлэл олон нийтийн зүгээс гарав. Ашигт малтмал, хүнд үйлдвэрийн салбарын албан тушаалтан гурван сарын хэрэгцээний агуулах сав барьсан бол нөөцийн хомсдол үүсэхгүй байсныг хүлээн зөвшөөрсөн. | F89: Улсын хэмжээнд | G89: Үнэн зөв мэдээлэл авах эрх, төрийн байгууллагын үйл ажиллагаа ил тод байх, зохистой амьжиргааны түвшинд амьдрах эрх, чөлөөтэй зорчих эрх | H89: Холбогдох яам, албан тушаалтнууд /нөөц бүрдүүлэлт, олон нийтэд мэдээлэл өгөх үүргээ зохих ёсоор биелүүлээгүй байж болзошгүй/ | I89: БНХАУ-аас 6,000 тонн АИ-92, АИ-95 автобензин авах хэлцэл хийж, БНСУ-аас шатахуун нийлүүлэхээр болсон. Арав хоногийн дотор хэвийн нөөцөд хүргэнэ гэж мэдэгдэж, төв зам дагуух аймгуудад шатахуун түгээх станцуудын ажиллагааг зохицуулав. | J89: iKon.mn, МҮОНРТ | K89: https://ikon.mn/n/3pa1 https://www.mnb.mn/i/349949 | M89: {=IF($G89="","",IFERROR(INDEX(Ангилал!$A$5:$A$22,MATCH(TRUE(),INDEX(ISNUMBER(SEARCH(Ангилал!$B$5:$B$22,$G89&" "&$D89))+ISNUMBER(SEARCH(Ангилал!$C$5:$C$22,$G89&" "&$D89))+IF(Ангилал!$D$5:$D$22="",0,ISNUMBER(SEARCH(Ангилал!$D$5:$D$22,$G89&" "&$D89)))+IF(Ангилал!$E$5:$E$22="",0,ISNUMBER(SEARCH(Ангилал!$E$5:$E$22,$G89&" "&$D89)))>0,0),0)),"Бусад"))} -> Үзэл бодлоо илэрхийлэх, мэдээллийн эрх | O89: =IF($G89="","",IF($N89<>"",$N89,$M89)) -> Үзэл бодлоо илэрхийлэх, мэдээллийн эрх | P89: {=IF($G89="","",IFERROR(INDEX(Ангилал!$G$5:$G$16,MATCH(TRUE(),INDEX(ISNUMBER(SEARCH(Ангилал!$H$5:$H$16,$G89&" "&$D89&" "&$E89))+ISNUMBER(SEARCH(Ангилал!$I$5:$I$16,$G89&" "&$D89&" "&$E89))+ISNUMBER(SEARCH(Ангилал!$J$5:$J$16,$G89&" "&$D89&" "&$E89))+ISNUMBER(SEARCH(Ангилал!$K$5:$K$16,$G89&" "&$D89&" "&$E89))>0,0),0)),"Ерөнхий нийт"))} -> Ерөнхий нийт | R89: =IF($G89="","",IF($Q89<>"",$Q89,$P89)) -> Ерөнхий нийт
A90: 70 | B90: 2026.07.30 | C90: 2026.07.30 | D90: Зөвшөөрөлгүй ус ашиглаж, олборлолт хийж байсан ААН-ийн үйл ажиллагааг зогсоожээ | E90: Зөвшөөрөлгүйгээр ус ашиглаж, олборлолтын үйл ажиллагаа явуулж байсан аж ахуйн нэгжийн үйл ажиллагааг эрх бүхий байгууллагаас зогсоосон. | F90: Улсын хэмжээнд | G90: Эрүүл, аюулгүй орчинд амьдрах эрх, цэвэр ус хүртээмжтэй байх эрх | H90: Зөвшөөрөлгүй ус ашиглаж, олборлолт хийсэн аж ахуйн нэгж | I90: Эрх бүхий байгууллага үйл ажиллагааг нь зогсоож, хариуцлага тооцох ажиллагаа явуулж байна. | J90: iKon.mn | K90: https://ikon.mn/n/3pa2 | M90: {=IF($G90="","",IFERROR(INDEX(Ангилал!$A$5:$A$22,MATCH(TRUE(),INDEX(ISNUMBER(SEARCH(Ангилал!$B$5:$B$22,$G90&" "&$D90))+ISNUMBER(SEARCH(Ангилал!$C$5:$C$22,$G90&" "&$D90))+IF(Ангилал!$D$5:$D$22="",0,ISNUMBER(SEARCH(Ангилал!$D$5:$D$22,$G90&" "&$D90)))+IF(Ангилал!$E$5:$E$22="",0,ISNUMBER(SEARCH(Ангилал!$E$5:$E$22,$G90&" "&$D90)))>0,0),0)),"Бусад"))} -> Эрүүл, аюулгүй орчинд амьдрах эрх | O90: =IF($G90="","",IF($N90<>"",$N90,$M90)) -> Эрүүл, аюулгүй орчинд амьдрах эрх | P90: {=IF($G90="","",IFERROR(INDEX(Ангилал!$G$5:$G$16,MATCH(TRUE(),INDEX(ISNUMBER(SEARCH(Ангилал!$H$5:$H$16,$G90&" "&$D90&" "&$E90))+ISNUMBER(SEARCH(Ангилал!$I$5:$I$16,$G90&" "&$D90&" "&$E90))+ISNUMBER(SEARCH(Ангилал!$J$5:$J$16,$G90&" "&$D90&" "&$E90))+ISNUMBER(SEARCH(Ангилал!$K$5:$K$16,$G90&" "&$D90&" "&$E90))>0,0),0)),"Ерөнхий нийт"))} -> Ерөнхий нийт | R90: =IF($G90="","",IF($Q90<>"",$Q90,$P90)) -> Ерөнхий нийт
A91: 71 | B91: 2026.07.29 | C91: 2026.06-2026.07 | D91: “Үерийн ус орж ирдэг Сэлбэ голд тохижилт хийснээр урсаж таарна. Төлөвлөлт буруу хийгдсэн” | E91: Сэлбэ гол дагуу зүлэг, явган хүний чулуун зам зэрэг тохижилтын ажил 80 гаруй хувьтай хийгдсэн боловч үерийн ус орж ирдэг гол дээр хийсэн уг төлөвлөлт буруу бөгөөд үерийн үед эвдрэх, иргэдэд эрсдэл учруулах магадлалтай талаар шүүмжлэл гарав. | F91: Улаанбаатар хот, Сэлбэ гол дагуу | G91: Эрүүл, аюулгүй орчинд амьдрах эрх, төрийн байгууллагаас чанартай үйлчилгээ авах эрх, төсвийн хөрөнгө үр ашигтай зарцуулагдах нийтийн ашиг сонирхол | H91: Хот төлөвлөлт, тохижилтын ажлыг захиалагч, гүйцэтгэгч байгууллага | I91: Мэдээлэлд төрийн байгууллагаас албан ёсны хариу арга хэмжээ авсан талаар дурдаагүй. | J91: iKon.mn | K91: https://ikon.mn/n/3p9c | M91: {=IF($G91="","",IFERROR(INDEX(Ангилал!$A$5:$A$22,MATCH(TRUE(),INDEX(ISNUMBER(SEARCH(Ангилал!$B$5:$B$22,$G91&" "&$D91))+ISNUMBER(SEARCH(Ангилал!$C$5:$C$22,$G91&" "&$D91))+IF(Ангилал!$D$5:$D$22="",0,ISNUMBER(SEARCH(Ангилал!$D$5:$D$22,$G91&" "&$D91)))+IF(Ангилал!$E$5:$E$22="",0,ISNUMBER(SEARCH(Ангилал!$E$5:$E$22,$G91&" "&$D91)))>0,0),0)),"Бусад"))} -> Эрүүл, аюулгүй орчинд амьдрах эрх | O91: =IF($G91="","",IF($N91<>"",$N91,$M91)) -> Эрүүл, аюулгүй орчинд амьдрах эрх | P91: {=IF($G91="","",IFERROR(INDEX(Ангилал!$G$5:$G$16,MATCH(TRUE(),INDEX(ISNUMBER(SEARCH(Ангилал!$H$5:$H$16,$G91&" "&$D91&" "&$E91))+ISNUMBER(SEARCH(Ангилал!$I$5:$I$16,$G91&" "&$D91&" "&$E91))+ISNUMBER(SEARCH(Ангилал!$J$5:$J$16,$G91&" "&$D91&" "&$E91))+ISNUMBER(SEARCH(Ангилал!$K$5:$K$16,$G91&" "&$D91&" "&$E91))>0,0),0)),"Ерөнхий нийт"))} -> Ерөнхий нийт | R91: =IF($G91="","",IF($Q91<>"",$Q91,$P91)) -> Ерөнхий нийт
A92: 72 | B92: 2026.07.30 | C92: 2026.07.29 | D92: Цагдаагийн байгууллагын 102 тусгай дугаарт өчигдөр бүртгэгдсэн дуудлага, мэдээлэл | E92: Цагдаагийн байгууллагын 102 тусгай дугаарт 2166 дуудлага мэдээлэл бүртгэгдсэнээс 68 нь гэр бүл, хүүхдийн хүчирхийллийн дуудлага, мэдээлэл байна. Мөн согтуугаар тээврийн хэрэгсэл жолоодсон 74 зөрчил гарсан. | F92: Улсын хэмжээнд | G92: Амар тайван, аюулгүй орчинд амьдрах эрх, амьд явах эрх, халдашгүй чөлөөтэй байх эрх | H92: Гэмт хэрэг, зөрчил үйлдсэн этгээдүүд | I92: Цагдаагийн байгууллага дуудлага бүрд шуурхай ажиллаж, зөрчлийг илрүүлэн хариуцлага тооцож байна. | J92: МҮОНРТ, ЦЕГ | K92: https://www.mnb.mn/i/349892 https://www.mnb.mn/i/349893 | M92: {=IF($G92="","",IFERROR(INDEX(Ангилал!$A$5:$A$22,MATCH(TRUE(),INDEX(ISNUMBER(SEARCH(Ангилал!$B$5:$B$22,$G92&" "&$D92))+ISNUMBER(SEARCH(Ангилал!$C$5:$C$22,$G92&" "&$D92))+IF(Ангилал!$D$5:$D$22="",0,ISNUMBER(SEARCH(Ангилал!$D$5:$D$22,$G92&" "&$D92)))+IF(Ангилал!$E$5:$E$22="",0,ISNUMBER(SEARCH(Ангилал!$E$5:$E$22,$G92&" "&$D92)))>0,0),0)),"Бусад"))} -> Амьд явах, халдашгүй байх эрх | O92: =IF($G92="","",IF($N92<>"",$N92,$M92)) -> Амьд явах, халдашгүй байх эрх | P92: {=IF($G92="","",IFERROR(INDEX(Ангилал!$G$5:$G$16,MATCH(TRUE(),INDEX(ISNUMBER(SEARCH(Ангилал!$H$5:$H$16,$G92&" "&$D92&" "&$E92))+ISNUMBER(SEARCH(Ангилал!$I$5:$I$16,$G92&" "&$D92&" "&$E92))+ISNUMBER(SEARCH(Ангилал!$J$5:$J$16,$G92&" "&$D92&" "&$E92))+ISNUMBER(SEARCH(Ангилал!$K$5:$K$16,$G92&" "&$D92&" "&$E92))>0,0),0)),"Ерөнхий нийт"))} -> Хүүхэд | R92: =IF($G92="","",IF($Q92<>"",$Q92,$P92)) -> Хүүхэд
A93: 73 | B93: 2026.07.30 | C93: 2023, 2024, 2025 он | D93: Улсын хилээр мансууруулах эм, сэтгэцэд нөлөөт бодис нэвтрүүлэх оролдлого илрэв | E93: Улсын хилээр мансууруулах эм, сэтгэцэд нөлөөт бодис нэвтрүүлэх оролдлогыг эрх бүхий байгууллагаас илрүүлсэн тухай мэдээлэв. | F93: Улсын хилийн боомт | G93: Эрүүл мэндээ хамгаалуулах эрх, хүүхэд, залуучуудыг хамгаалах эрх, аюулгүй байдал | H93: Хууль бусаар мансууруулах бодис нэвтрүүлэхийг завдсан этгээд | I93: Хил хамгаалах болон гаалийн байгууллага илрүүлж, хууль хяналтын байгууллагад шилжүүлэн шалгаж байна. | J93: МҮОНРТ | K93: https://www.mnb.mn/i/349909 | M93: {=IF($G93="","",IFERROR(INDEX(Ангилал!$A$5:$A$22,MATCH(TRUE(),INDEX(ISNUMBER(SEARCH(Ангилал!$B$5:$B$22,$G93&" "&$D93))+ISNUMBER(SEARCH(Ангилал!$C$5:$C$22,$G93&" "&$D93))+IF(Ангилал!$D$5:$D$22="",0,ISNUMBER(SEARCH(Ангилал!$D$5:$D$22,$G93&" "&$D93)))+IF(Ангилал!$E$5:$E$22="",0,ISNUMBER(SEARCH(Ангилал!$E$5:$E$22,$G93&" "&$D93)))>0,0),0)),"Бусад"))} -> Эрүүл мэндийн эрх | O93: =IF($G93="","",IF($N93<>"",$N93,$M93)) -> Эрүүл мэндийн эрх | P93: {=IF($G93="","",IFERROR(INDEX(Ангилал!$G$5:$G$16,MATCH(TRUE(),INDEX(ISNUMBER(SEARCH(Ангилал!$H$5:$H$16,$G93&" "&$D93&" "&$E93))+ISNUMBER(SEARCH(Ангилал!$I$5:$I$16,$G93&" "&$D93&" "&$E93))+ISNUMBER(SEARCH(Ангилал!$J$5:$J$16,$G93&" "&$D93&" "&$E93))+ISNUMBER(SEARCH(Ангилал!$K$5:$K$16,$G93&" "&$D93&" "&$E93))>0,0),0)),"Ерөнхий нийт"))} -> Ерөнхий нийт | R93: =IF($G93="","",IF($Q93<>"",$Q93,$P93)) -> Ерөнхий нийт
A94: 2026.08.03-08.07 | M94: {=IF($G94="","",IFERROR(INDEX(Ангилал!$A$5:$A$22,MATCH(TRUE(),INDEX(ISNUMBER(SEARCH(Ангилал!$B$5:$B$22,$G94&" "&$D94))+ISNUMBER(SEARCH(Ангилал!$C$5:$C$22,$G94&" "&$D94))+IF(Ангилал!$D$5:$D$22="",0,ISNUMBER(SEARCH(Ангилал!$D$5:$D$22,$G94&" "&$D94)))+IF(Ангилал!$E$5:$E$22="",0,ISNUMBER(SEARCH(Ангилал!$E$5:$E$22,$G94&" "&$D94)))>0,0),0)),"Бусад"))} | O94: =IF($G94="","",IF($N94<>"",$N94,$M94)) | P94: {=IF($G94="","",IFERROR(INDEX(Ангилал!$G$5:$G$16,MATCH(TRUE(),INDEX(ISNUMBER(SEARCH(Ангилал!$H$5:$H$16,$G94&" "&$D94&" "&$E94))+ISNUMBER(SEARCH(Ангилал!$I$5:$I$16,$G94&" "&$D94&" "&$E94))+ISNUMBER(SEARCH(Ангилал!$J$5:$J$16,$G94&" "&$D94&" "&$E94))+ISNUMBER(SEARCH(Ангилал!$K$5:$K$16,$G94&" "&$D94&" "&$E94))>0,0),0)),"Ерөнхий нийт"))} | R94: =IF($G94="","",IF($Q94<>"",$Q94,$P94))
A95: 74 | B95: 2026.08.05 | C95: 2026.08.05 | D95: Би Монгол Улсын иргэн биш !!! | E95: Яг галзуурлаа. Би одоо яах юм бэ? Давааням даргаа. Би ч өөрөө Улсын Бүртгэлийн ерөнхий газар хэсэгхэн хугацаанд ажиллаж байсан. Ажил ихтэй, иргэдийн мэдлэггүй байдлаас болж асуудлууд хүндэрдгийг мэднэ. Гэхдээ энэ удаа намайг яаж байгаан бэ? Нотариатоор итгэмжлэх бичиж батлуулах гэсэн чинь хяналтын байцаагч Батсүх гэж хүн надад шалтгаан, тайлбар өгөхгүйгээр, ямар нэгэн байдлаар надад мэдэгдэлгүйгээр миний 16 онд сунгалт хийлгэж, 35 он болтол хүчинтэй байсан иргэний үнэмлэхийг хүчингүй болгосон байна. Ямар шалтгаантайгаа ч мэдэгдээгүй. Гэтэл би энэ 7 хоногтоо итгэмжлэх бичиж, нотариат орж, баталгаат орчуулга хийлгэж, апостиль авах ёстой. Яг одоо би Монгол улсын иргэн биш, төрийн үйлчилгээ авах боломжгүй, эрх зүйн ямар ч чадамжгүй, өөрийгөө ч нотариат дээр нотолж чадахгүй хүн болчихлоо. Элчингийн ярилцлага дээр хугацаа нь тулсан үед ийм юм байж болдог юм уу? 18 онд хүчингүй болгосон гэх. Гэтэл тэрнээс хойш би банк, банк бусууд дээр emongolia-гаас иргэний үнэмлэхийн лавлагаа, гадаад пасспорт захиалах, авахад хэвийн байсан, өөрийгөө төлөөлж чадаж байсан. Хамгийн наад захын юм нь би сонгуулиа өгч байсан, тэгэхэд хурууны хээгээр хүчингүй бол саналаа өгөх боломжгүй болно биздээ? Энэнээс болоод амьдрал сүйрч байна. Галзуурах нь. Ингэж болдог юм уу? | F95: Улаанбаатар хот, Улсын бүртгэлийн ерөнхий газар | G95: Иргэний үнэмлэх эзэмших, хүчинтэй иргэний үнэмлэхтэй байх эрх Хуульд заасан үндэслэл, журмын дагуу шийдвэр гаргуулах эрх Захиргааны байгууллагын шийдвэрийн талаар урьдчилан мэдэх эрх Захиргааны шийдвэртэй танилцах эрх Захиргааны шийдвэрт гомдол гаргах эрх Төрийн үйлчилгээ тэгш, саадгүй авах эрх Нотариатын үйлчилгээ авах эрх Итгэмжлэл үйлдэх, баталгаажуулах эрх Иргэний эрх зүйн хэлцэл хийх эрх Гадаад паспорт авах, сунгуулах эрх Хувийн мэдээлэл, улсын бүртгэлийн мэдээлэл үнэн зөв хадгалагдах эрх Эрх зүйн чадамжаа хэрэгжүүлэх боломжтой байх эрх Үр нөлөөтэй эрх зүйн хамгаалалт авах эрх Төрийн байгууллагын хууль ёсны, үндэслэл бүхий үйл ажиллагаагаар үйлчлүүлэх эрх Хууль ёсны итгэлээ хамгаалуулах эрх | H95: УБЕГ | I95: - | J95: Иргэн Б.Энх-Амгалан | K95: https://www.facebook.com/story.php?story_fbid=27764954223114874&id=100000810076475&mibextid=wwXIfr&rdid=BLxOpALXWyIjArCn# | L95: #VALUE! | M95: {=IF($G95="","",IFERROR(INDEX(Ангилал!$A$5:$A$22,MATCH(TRUE(),INDEX(ISNUMBER(SEARCH(Ангилал!$B$5:$B$22,$G95&" "&$D95))+ISNUMBER(SEARCH(Ангилал!$C$5:$C$22,$G95&" "&$D95))+IF(Ангилал!$D$5:$D$22="",0,ISNUMBER(SEARCH(Ангилал!$D$5:$D$22,$G95&" "&$D95)))+IF(Ангилал!$E$5:$E$22="",0,ISNUMBER(SEARCH(Ангилал!$E$5:$E$22,$G95&" "&$D95)))>0,0),0)),"Бусад"))} -> Хувийн нууц, халдашгүй байдал | O95: =IF($G95="","",IF($N95<>"",$N95,$M95)) -> Хувийн нууц, халдашгүй байдал | P95: {=IF($G95="","",IFERROR(INDEX(Ангилал!$G$5:$G$16,MATCH(TRUE(),INDEX(ISNUMBER(SEARCH(Ангилал!$H$5:$H$16,$G95&" "&$D95&" "&$E95))+ISNUMBER(SEARCH(Ангилал!$I$5:$I$16,$G95&" "&$D95&" "&$E95))+ISNUMBER(SEARCH(Ангилал!$J$5:$J$16,$G95&" "&$D95&" "&$E95))+ISNUMBER(SEARCH(Ангилал!$K$5:$K$16,$G95&" "&$D95&" "&$E95))>0,0),0)),"Ерөнхий нийт"))} -> Ерөнхий нийт | R95: =IF($G95="","",IF($Q95<>"",$Q95,$P95)) -> Ерөнхий нийт
A96: 75 | B96: 2026.08.05 | C96: 2022 оны сүүлээс хойш | D96: Цахим хөгжил, инновац, харилцаа холбооны сайд Ч.Номины хамаарал бүхий "Монгол ТВ" ажилчдынхаа цалингаас нийгмийн даатгалын шимтгэлийг нь суутган авдаг мөртлөө хоёр жил төлөөгүй талаар тус телевизийн ажилтан цахим сүлжээнд ийнхүү бичжээ. | E96: Нийгмийн даатгалын шимтгэлийн төлөлт 2022 оны сүүлээс хойш хийгдээгүй. Цалин цагтаа орсон тохиолдлыг сүүлийн гурван жил би хараагүй. Тоочоод бичвэл олон зүйл бий. Мэргэжилдээ дуртай, хамт олондоо дассан болохоор өнөөдрийг хүртэл ажиллаж байгаа ч арай дэндэж байна" | F96: Улаанбаатар хот, Монгол ТВ | G96: Хөдөлмөрлөх эрх Шударга, таатай хөдөлмөрийн нөхцөлөөр хангагдах эрх Шударга цалин хөлс авах эрх Цалин хөлсөө хугацаанд нь авах эрх Нийгмийн даатгалд хамрагдах эрх Нийгмийн хамгаалал хүртэх эрх Амьжиргааны зохистой түвшинд хүрэх эрх Өмчлөх эрх Үр дүнтэй эрх зүйн хамгаалалт авах эрх | H96: Монгол ТВ | J96: Сошиал сувгууд | K96: https://www.facebook.com/story.php?story_fbid=1556084686532647&id=100063933908097&mibextid=wwXIfr&rdid=3Fui2KnS1GeyFIE4# | L96: #VALUE! | M96: {=IF($G96="","",IFERROR(INDEX(Ангилал!$A$5:$A$22,MATCH(TRUE(),INDEX(ISNUMBER(SEARCH(Ангилал!$B$5:$B$22,$G96&" "&$D96))+ISNUMBER(SEARCH(Ангилал!$C$5:$C$22,$G96&" "&$D96))+IF(Ангилал!$D$5:$D$22="",0,ISNUMBER(SEARCH(Ангилал!$D$5:$D$22,$G96&" "&$D96)))+IF(Ангилал!$E$5:$E$22="",0,ISNUMBER(SEARCH(Ангилал!$E$5:$E$22,$G96&" "&$D96)))>0,0),0)),"Бусад"))} -> Хөдөлмөрлөх эрх | O96: =IF($G96="","",IF($N96<>"",$N96,$M96)) -> Хөдөлмөрлөх эрх | P96: {=IF($G96="","",IFERROR(INDEX(Ангилал!$G$5:$G$16,MATCH(TRUE(),INDEX(ISNUMBER(SEARCH(Ангилал!$H$5:$H$16,$G96&" "&$D96&" "&$E96))+ISNUMBER(SEARCH(Ангилал!$I$5:$I$16,$G96&" "&$D96&" "&$E96))+ISNUMBER(SEARCH(Ангилал!$J$5:$J$16,$G96&" "&$D96&" "&$E96))+ISNUMBER(SEARCH(Ангилал!$K$5:$K$16,$G96&" "&$D96&" "&$E96))>0,0),0)),"Ерөнхий нийт"))} -> Хөгжлийн бэрхшээлтэй иргэд | R96: =IF($G96="","",IF($Q96<>"",$Q96,$P96)) -> Хөгжлийн бэрхшээлтэй иргэд
A97: 2026.08.10-08.21 | M97: {=IF($G97="","",IFERROR(INDEX(Ангилал!$A$5:$A$22,MATCH(TRUE(),INDEX(ISNUMBER(SEARCH(Ангилал!$B$5:$B$22,$G97&" "&$D97))+ISNUMBER(SEARCH(Ангилал!$C$5:$C$22,$G97&" "&$D97))+IF(Ангилал!$D$5:$D$22="",0,ISNUMBER(SEARCH(Ангилал!$D$5:$D$22,$G97&" "&$D97)))+IF(Ангилал!$E$5:$E$22="",0,ISNUMBER(SEARCH(Ангилал!$E$5:$E$22,$G97&" "&$D97)))>0,0),0)),"Бусад"))} | O97: =IF($G97="","",IF($N97<>"",$N97,$M97)) | P97: {=IF($G97="","",IFERROR(INDEX(Ангилал!$G$5:$G$16,MATCH(TRUE(),INDEX(ISNUMBER(SEARCH(Ангилал!$H$5:$H$16,$G97&" "&$D97&" "&$E97))+ISNUMBER(SEARCH(Ангилал!$I$5:$I$16,$G97&" "&$D97&" "&$E97))+ISNUMBER(SEARCH(Ангилал!$J$5:$J$16,$G97&" "&$D97&" "&$E97))+ISNUMBER(SEARCH(Ангилал!$K$5:$K$16,$G97&" "&$D97&" "&$E97))>0,0),0)),"Ерөнхий нийт"))} | R97: =IF($G97="","",IF($Q97<>"",$Q97,$P97))
A98: 76 | B98: 2026.08.15 | D98: "Энгийн" иргэд нь нэг бол өвдөж түргэн дуудаж замын хөдөлгөөнд оролцоно Үгүй бол үхэж байж зөвшөөрөгдсөн тэргээр зөөвөрлөгдөнө. | E98: Улаанбаатар хот нийтдээ 1162км урт 400 гаруй уулзвар, 6300 гаруй камертайгаас хиймэл оюун ухаан суурил сан 4800 гаруй камерт 20000 төгрөгийн торгууль бичигдэх бол хэдэн камер өнгөрөхөд хэдэн төгрөг нь улсын төсөв бүрдүүлэлт болох вэ, ТӨР болон түүний албан хаагч нарт хуульд олгосон бүрэн эрхийн хүрээнд журам гаргахаас "ЭНГИЙН", "УЛНЫ" иргэд амьдарч байгаагийнх нь хувьд АМЬД ЯВАХ, ЧӨЛӨӨТЭЙ ЗОРЧИХ ЭРХ-ийг хязгаарласан журам батлах ёсгүй. Энэ бол хүний эрхийн асар том зөрчил шүү.Үнэхээр хөгийн ч юм даа. Олон улсын зочид чинь үнэндээ сошиал иргэд ингэж бухимдлаа илэрхийлж байгааг мэдэж байгаа шдээ | F98: Улаанбаатар хот | G98: Үндсэн хуулийн зөрчил: Иргэд Үндсэн хуулиар олгогдсон Монгол Улсын нутаг дэвсгэрт чөлөөтэй зорчих эрхийг хууль бусаар хязгаарлаж байна. Үндэслэлгүй торгууль: Бүсчлэл тодорхой бус байхад хотын захын хэсгүүдэд (Нисэх, Биокомбинат гэх мэт) камерын хяналтаар шууд торгууль ногдуулж байгаа нь иргэдийн амьжиргаа, эдийн засгийн эрх чөлөөнд халдаж байна. Хүүхдийн сурч боловсрох эрх: Хичээлийн шинэ жил эхлэх гэж буйтай холбогдуулан өглөөний 07:00 эсвэл 08:00 цагт хүүхдээ сургууль, цэцэрлэгт зөөхөд амьдралаас тасархай, хүнд сурталтай шийдвэр болсон. | H98: ЗГ, НЗД | J98: Хуульч ээж | K98: https://www.facebook.com/UBTCC/posts/%D0%BD%D0%B0%D0%B9%D0%BC%D0%B4%D1%83%D0%B3%D0%B0%D0%B0%D1%80-%D1%81%D0%B0%D1%80%D1%8B%D0%BD-15-%D0%BD%D0%B0%D0%B0%D1%81-%D0%B1%D1%83%D1%8E%D1%83-%D1%8D%D0%BD%D1%8D-%D0%B4%D0%BE%D0%BB%D0%BE%D0%BE-%D1%85%D0%BE%D0%BD%D0%BE%D0%B3%D0%B8%D0%B9%D0%BD-%D0%B1%D1%8F%D0%BC%D0%B1%D0%B0-%D0%B3%D0%B0%D1%80%D0%B0%D0%B3%D0%B0%D0%B0%D1%81-%D1%83%D0%BB%D1%81%D1%8B%D0%BD-%D0%B4%D1%83%D0%B3%D0%B0%D0%B0%D1%80%D1%8B%D0%BD-%D1%82/1339849014976453/ | M98: {=IF($G98="","",IFERROR(INDEX(Ангилал!$A$5:$A$22,MATCH(TRUE(),INDEX(ISNUMBER(SEARCH(Ангилал!$B$5:$B$22,$G98&" "&$D98))+ISNUMBER(SEARCH(Ангилал!$C$5:$C$22,$G98&" "&$D98))+IF(Ангилал!$D$5:$D$22="",0,ISNUMBER(SEARCH(Ангилал!$D$5:$D$22,$G98&" "&$D98)))+IF(Ангилал!$E$5:$E$22="",0,ISNUMBER(SEARCH(Ангилал!$E$5:$E$22,$G98&" "&$D98)))>0,0),0)),"Бусад"))} -> Хүүхдийн эрх | O98: =IF($G98="","",IF($N98<>"",$N98,$M98)) -> Хүүхдийн эрх | P98: {=IF($G98="","",IFERROR(INDEX(Ангилал!$G$5:$G$16,MATCH(TRUE(),INDEX(ISNUMBER(SEARCH(Ангилал!$H$5:$H$16,$G98&" "&$D98&" "&$E98))+ISNUMBER(SEARCH(Ангилал!$I$5:$I$16,$G98&" "&$D98&" "&$E98))+ISNUMBER(SEARCH(Ангилал!$J$5:$J$16,$G98&" "&$D98&" "&$E98))+ISNUMBER(SEARCH(Ангилал!$K$5:$K$16,$G98&" "&$D98&" "&$E98))>0,0),0)),"Ерөнхий нийт"))} -> Хүүхэд | R98: =IF($G98="","",IF($Q98<>"",$Q98,$P98)) -> Хүүхэд
A99: 77 | B99: 2026.08.15 | D99: Хэрээс хэтэрлээ. Лалын харгислал үйлдэгчидтэй адил үйлдэл бишүү | E99: Хэрээс хэтэрлээ. Лалын харгислал үйлдэгчидтэй адил үйлдэл бишүү. Хүний эрхийн зөрчил, гадны иргэдийн эрхэнд шууд халдсан үйлдэл. Хятад улс зүгээр хараад суух уу⁉️ анхаараачээ | F99: Сүхбаатар аймаг, Сүхбаатар сум, 5-р баг | G99: Хүний нэр төрийг гутаах, доромжлох, Ялгаварлан гадуурхалт, Хүчирхийлэл, айлган сүрдүүлэлт | H99: Г.Солонго, Г.Адилбиш | I99: Хууль бусаар халдаж, дураар авирласан гэх асуудалтай холбогдуулан Цагдаагийн байгууллагаас тэмцэгч Г.Солонго, Г.Адилбиш нарыг 48 цагийн хугацаатай саатуулж, шалгалтын ажиллагаа явуулж эхэлсэн. | J99: twitter | K99: https://x.com/abazarragchaa/status/2088588472709968059 | L99: #VALUE! | M99: {=IF($G99="","",IFERROR(INDEX(Ангилал!$A$5:$A$22,MATCH(TRUE(),INDEX(ISNUMBER(SEARCH(Ангилал!$B$5:$B$22,$G99&" "&$D99))+ISNUMBER(SEARCH(Ангилал!$C$5:$C$22,$G99&" "&$D99))+IF(Ангилал!$D$5:$D$22="",0,ISNUMBER(SEARCH(Ангилал!$D$5:$D$22,$G99&" "&$D99)))+IF(Ангилал!$E$5:$E$22="",0,ISNUMBER(SEARCH(Ангилал!$E$5:$E$22,$G99&" "&$D99)))>0,0),0)),"Бусад"))} -> Хүчирхийлэл, бэлгийн дарамтаас ангид байх | O99: =IF($G99="","",IF($N99<>"",$N99,$M99)) -> Хүчирхийлэл, бэлгийн дарамтаас ангид байх | P99: {=IF($G99="","",IFERROR(INDEX(Ангилал!$G$5:$G$16,MATCH(TRUE(),INDEX(ISNUMBER(SEARCH(Ангилал!$H$5:$H$16,$G99&" "&$D99&" "&$E99))+ISNUMBER(SEARCH(Ангилал!$I$5:$I$16,$G99&" "&$D99&" "&$E99))+ISNUMBER(SEARCH(Ангилал!$J$5:$J$16,$G99&" "&$D99&" "&$E99))+ISNUMBER(SEARCH(Ангилал!$K$5:$K$16,$G99&" "&$D99&" "&$E99))>0,0),0)),"Ерөнхий нийт"))} -> Ерөнхий нийт | R99: =IF($G99="","",IF($Q99<>"",$Q99,$P99)) -> Ерөнхий нийт
A100: 78 | B100: 2026.08.18 | C100: 2026.08 | D100: Сэтгүүлчийн мэргэжлийн үйл ажиллагаанд саад учруулсан төрийн албан тушаалтны үйлдэл | E100: Нийтийн эрх ашгийг хөндсөн тендерийн асуудлаар сурвалжилга хийж байсан сэтгүүлчийн биед халдаж, мэргэжлийн үйл ажиллагаанд нь саад учруулан, техник хэрэгслийг нь дур мэдэн хураан авсан гомдол бүртгэгдэв. | F100: Улаанбаатар хот, Чингэлтэй дүүрэг | G100: Үзэл бодлоо чөлөөтэй илэрхийлэх, үг хэлэх, хэвлэн нийтлэх эрх Мэдээлэл хайх, хүлээн авах, түгээх эрх, Мэргэжлийн халдашгүй байх эрх | H100: Төрийн өмчит байгууллагын хамгаалалтын алба, холбогдох албан тушаалтнууд | I100: Цагдаагийн байгууллагаас гомдлыг хүлээн авч, зөрчлийн хэрэг нээн шалгаж эхэлсэн. | J100: Монголын хэвлэл мэдээллийн зөвлөл | K100: https://presscouncil.mn | L100: Хяналтын камерийн бичлэг болон хохирогчийн өргөдөл | M100: {=IF($G100="","",IFERROR(INDEX(Ангилал!$A$5:$A$22,MATCH(TRUE(),INDEX(ISNUMBER(SEARCH(Ангилал!$B$5:$B$22,$G100&" "&$D100))+ISNUMBER(SEARCH(Ангилал!$C$5:$C$22,$G100&" "&$D100))+IF(Ангилал!$D$5:$D$22="",0,ISNUMBER(SEARCH(Ангилал!$D$5:$D$22,$G100&" "&$D100)))+IF(Ангилал!$E$5:$E$22="",0,ISNUMBER(SEARCH(Ангилал!$E$5:$E$22,$G100&" "&$D100)))>0,0),0)),"Бусад"))} -> Амьд явах, халдашгүй байх эрх | O100: =IF($G100="","",IF($N100<>"",$N100,$M100)) -> Амьд явах, халдашгүй байх эрх | P100: {=IF($G100="","",IFERROR(INDEX(Ангилал!$G$5:$G$16,MATCH(TRUE(),INDEX(ISNUMBER(SEARCH(Ангилал!$H$5:$H$16,$G100&" "&$D100&" "&$E100))+ISNUMBER(SEARCH(Ангилал!$I$5:$I$16,$G100&" "&$D100&" "&$E100))+ISNUMBER(SEARCH(Ангилал!$J$5:$J$16,$G100&" "&$D100&" "&$E100))+ISNUMBER(SEARCH(Ангилал!$K$5:$K$16,$G100&" "&$D100&" "&$E100))>0,0),0)),"Ерөнхий нийт"))} -> Сэтгүүлч, хүний эрхийн хамгаалагч | R100: =IF($G100="","",IF($Q100<>"",$Q100,$P100)) -> Сэтгүүлч, хүний эрхийн хамгаалагч
A101: 2026.08.24-08.28 | M101: {=IF($G101="","",IFERROR(INDEX(Ангилал!$A$5:$A$22,MATCH(TRUE(),INDEX(ISNUMBER(SEARCH(Ангилал!$B$5:$B$22,$G101&" "&$D101))+ISNUMBER(SEARCH(Ангилал!$C$5:$C$22,$G101&" "&$D101))+IF(Ангилал!$D$5:$D$22="",0,ISNUMBER(SEARCH(Ангилал!$D$5:$D$22,$G101&" "&$D101)))+IF(Ангилал!$E$5:$E$22="",0,ISNUMBER(SEARCH(Ангилал!$E$5:$E$22,$G101&" "&$D101)))>0,0),0)),"Бусад"))} | O101: =IF($G101="","",IF($N101<>"",$N101,$M101)) | P101: {=IF($G101="","",IFERROR(INDEX(Ангилал!$G$5:$G$16,MATCH(TRUE(),INDEX(ISNUMBER(SEARCH(Ангилал!$H$5:$H$16,$G101&" "&$D101&" "&$E101))+ISNUMBER(SEARCH(Ангилал!$I$5:$I$16,$G101&" "&$D101&" "&$E101))+ISNUMBER(SEARCH(Ангилал!$J$5:$J$16,$G101&" "&$D101&" "&$E101))+ISNUMBER(SEARCH(Ангилал!$K$5:$K$16,$G101&" "&$D101&" "&$E101))>0,0),0)),"Ерөнхий нийт"))} | R101: =IF($G101="","",IF($Q101<>"",$Q101,$P101))
...

Sheet Гадаад
C1: Хүний эрхийн зөрчилтэй холбоотой 7 хоног бүрийн мэдээ, мэдээллийн бүртгэлийн хүснэгт
E2: Олон улсын
A3: 2026.04.07 | J3: Улаанбаатар хот
A4: Д/д | B4: Мэдээллийн огноо | C4: Мэдээлэл дэх үйл явдал болсон хугацаа | D4: Мэдээллийн гарчиг | E4: Мэдээллийн товч утга | F4: Үйл явдал болсон байршил | G4: Хөндөгдсөн эрх | H4: Зөрчил үйлдсэн байж болзошгүй этгээд /хариуцагч/ | I4: Эх сурвалж /дэлгэрэнгүй/ | J4: Холбоос | L4: Эрхийн ангилал (авто) | M4: Эрх — гараар засах | N4: ЭРХИЙН АНГИЛАЛ | O4: Нийгмийн бүлэг (авто) | P4: Бүлэг — гараар засах | Q4: НИЙГМИЙН БҮЛЭГ
A5: 1 | B5: 2026.04.13 | C5: 2026.04.13 | D5: Sudan: Top UN aid official warns of ‘abandoned crisis’ as war enters fourth year | E5: Суданы дайн 4 дэх жилдээ үргэлжилж, энгийн иргэд амь үрэгдэж, дүрвэж, бэлгийн хүчирхийлэл их байгаа талаар Судан дахь НҮБ-ын хүмүүнлэгийн зохицуулагч Denise Brown мэдээлжээ. | F5: Судан улс: Хартум, Дарфур хот | G5: Амьд явах, халдашгүй чөлөөтэй байх эрх | H5: Засгийн газар ба мөргөлдөгч тал | I5: UN news | J5: Sudan: Top UN aid official warns of ‘abandoned crisis’ as war enters fourth year | UN News | L5: {=IF($G5="","",IFERROR(INDEX(Ангилал!$A$5:$A$22,MATCH(TRUE(),INDEX(ISNUMBER(SEARCH(Ангилал!$B$5:$B$22,$G5&" "&$E5))+ISNUMBER(SEARCH(Ангилал!$C$5:$C$22,$G5&" "&$E5))+IF(Ангилал!$D$5:$D$22="",0,ISNUMBER(SEARCH(Ангилал!$D$5:$D$22,$G5&" "&$E5)))+IF(Ангилал!$E$5:$E$22="",0,ISNUMBER(SEARCH(Ангилал!$E$5:$E$22,$G5&" "&$E5)))>0,0),0)),"Бусад"))} -> Амьд явах, халдашгүй байх эрх | N5: =IF($G5="","",IF($M5<>"",$M5,$L5)) -> Амьд явах, халдашгүй байх эрх | O5: {=IF($G5="","",IFERROR(INDEX(Ангилал!$G$5:$G$16,MATCH(TRUE(),INDEX(ISNUMBER(SEARCH(Ангилал!$H$5:$H$16,$G5&" "&$E5))+ISNUMBER(SEARCH(Ангилал!$I$5:$I$16,$G5&" "&$E5))+ISNUMBER(SEARCH(Ангилал!$J$5:$J$16,$G5&" "&$E5))+ISNUMBER(SEARCH(Ангилал!$K$5:$K$16,$G5&" "&$E5))>0,0),0)),"Ерөнхий нийт"))} -> Ерөнхий нийт | Q5: =IF($G5="","",IF($P5<>"",$P5,$O5)) -> Ерөнхий нийт
A6: 2 | B6: 2026.04.13 | C6: 2026.02.28-аас хойш | D6: ‘Clock is ticking’: Hormuz disruption raises fears of global food crisis | E6: АНУ болон Ираны мөргөлдөөний улмаас газрын тос, хий дамждаг гол тээврийн зам болох Ормузын хоолой хаагдах эрсдэл үүссэн. | F6: Иран ба Оман улсын дунд байрладаг олон улсын усан тээврийн хоолой /international strait/ | G6: Улс орны эдийн засаг | H6: АНУ болон Ираны дайн | I6: UN news | J6: ‘Clock is ticking’: Hormuz disruption raises fears of global food crisis | UN News | L6: {=IF($G6="","",IFERROR(INDEX(Ангилал!$A$5:$A$22,MATCH(TRUE(),INDEX(ISNUMBER(SEARCH(Ангилал!$B$5:$B$22,$G6&" "&$E6))+ISNUMBER(SEARCH(Ангилал!$C$5:$C$22,$G6&" "&$E6))+IF(Ангилал!$D$5:$D$22="",0,ISNUMBER(SEARCH(Ангилал!$D$5:$D$22,$G6&" "&$E6)))+IF(Ангилал!$E$5:$E$22="",0,ISNUMBER(SEARCH(Ангилал!$E$5:$E$22,$G6&" "&$E6)))>0,0),0)),"Бусад"))} -> Хүнс, ус, орон сууцны эрх | N6: =IF($G6="","",IF($M6<>"",$M6,$L6)) -> Хүнс, ус, орон сууцны эрх | O6: {=IF($G6="","",IFERROR(INDEX(Ангилал!$G$5:$G$16,MATCH(TRUE(),INDEX(ISNUMBER(SEARCH(Ангилал!$H$5:$H$16,$G6&" "&$E6))+ISNUMBER(SEARCH(Ангилал!$I$5:$I$16,$G6&" "&$E6))+ISNUMBER(SEARCH(Ангилал!$J$5:$J$16,$G6&" "&$E6))+ISNUMBER(SEARCH(Ангилал!$K$5:$K$16,$G6&" "&$E6))>0,0),0)),"Ерөнхий нийт"))} -> Ерөнхий нийт | Q6: =IF($G6="","",IF($P6<>"",$P6,$O6)) -> Ерөнхий нийт
A7: 3 | B7: 2026.04.13 | C7: 2026.04 | D7: Tech gaps and budget cuts threaten global efforts to track and help the vulnerable | E7: Технологийн цоорхой болон санхүүжилтийн хомсдол нь дэлхий даяарх эмзэг бүлгийн хүмүүст шаардлагатай тусламж үзүүлэхэд саад хийж байна. | F7: Нигери улс | G7: Эмзэг бүлгийн хүмүүсийн эрх | I7: UN news | J7: Tech gaps and budget cuts threaten global efforts to track and help the vulnerable | UN News | L7: {=IF($G7="","",IFERROR(INDEX(Ангилал!$A$5:$A$22,MATCH(TRUE(),INDEX(ISNUMBER(SEARCH(Ангилал!$B$5:$B$22,$G7&" "&$E7))+ISNUMBER(SEARCH(Ангилал!$C$5:$C$22,$G7&" "&$E7))+IF(Ангилал!$D$5:$D$22="",0,ISNUMBER(SEARCH(Ангилал!$D$5:$D$22,$G7&" "&$E7)))+IF(Ангилал!$E$5:$E$22="",0,ISNUMBER(SEARCH(Ангилал!$E$5:$E$22,$G7&" "&$E7)))>0,0),0)),"Бусад"))} -> Бусад | N7: =IF($G7="","",IF($M7<>"",$M7,$L7)) -> Бусад | O7: {=IF($G7="","",IFERROR(INDEX(Ангилал!$G$5:$G$16,MATCH(TRUE(),INDEX(ISNUMBER(SEARCH(Ангилал!$H$5:$H$16,$G7&" "&$E7))+ISNUMBER(SEARCH(Ангилал!$I$5:$I$16,$G7&" "&$E7))+ISNUMBER(SEARCH(Ангилал!$J$5:$J$16,$G7&" "&$E7))+ISNUMBER(SEARCH(Ангилал!$K$5:$K$16,$G7&" "&$E7))>0,0),0)),"Ерөнхий нийт"))} -> Ерөнхий нийт | Q7: =IF($G7="","",IF($P7<>"",$P7,$O7)) -> Ерөнхий нийт
A8: 4 | B8: 2026.04.15 | C8: 2026.03 сараас хойш | D8: MIDDLE EAST LIVE 15 April: Civilian dangers intensify as Israel expands Lebanon evacuation orders | E8: Израйлийн цэргийн ажиллагаа Ливан улсад үргэлжилсээр байгаагаас үүдэн олон Ливан иргэд амь үрэгдэж байна. | F8: Ливан улс | G8: Амьд явах, халдашгүй чөлөөтэй байх эрх | H8: Израйль | I8: UN news | J8: https://news.un.org/en/story/2026/04/1167302 | L8: {=IF($G8="","",IFERROR(INDEX(Ангилал!$A$5:$A$22,MATCH(TRUE(),INDEX(ISNUMBER(SEARCH(Ангилал!$B$5:$B$22,$G8&" "&$E8))+ISNUMBER(SEARCH(Ангилал!$C$5:$C$22,$G8&" "&$E8))+IF(Ангилал!$D$5:$D$22="",0,ISNUMBER(SEARCH(Ангилал!$D$5:$D$22,$G8&" "&$E8)))+IF(Ангилал!$E$5:$E$22="",0,ISNUMBER(SEARCH(Ангилал!$E$5:$E$22,$G8&" "&$E8)))>0,0),0)),"Бусад"))} -> Амьд явах, халдашгүй байх эрх | N8: =IF($G8="","",IF($M8<>"",$M8,$L8)) -> Амьд явах, халдашгүй байх эрх | O8: {=IF($G8="","",IFERROR(INDEX(Ангилал!$G$5:$G$16,MATCH(TRUE(),INDEX(ISNUMBER(SEARCH(Ангилал!$H$5:$H$16,$G8&" "&$E8))+ISNUMBER(SEARCH(Ангилал!$I$5:$I$16,$G8&" "&$E8))+ISNUMBER(SEARCH(Ангилал!$J$5:$J$16,$G8&" "&$E8))+ISNUMBER(SEARCH(Ангилал!$K$5:$K$16,$G8&" "&$E8))>0,0),0)),"Ерөнхий нийт"))} -> Ерөнхий нийт | Q8: =IF($G8="","",IF($P8<>"",$P8,$O8)) -> Ерөнхий нийт
A9: 5 | B9: 2026.04.17 | C9: 2026.04.16 | D9: The Epstein files: Rights experts demand accountability, call for probe into trafficking allegations | E9: НҮБ-ын хүний эрхийн хараат бус экспертүүд “Эпштейний файлууд”-д дурдагдсан зохион байгуулалттай хүний наймааны хэрэгт хариуцлага тооцохыг уриаллаа. | F9: Женев хот, Швейцар улс | G9: Халдашгүй чөлөөтэй байх эрх | H9: Жеффри Эпштэйн болон хамаарал бүхий хүмүүс | I9: UN news | J9: https://news.un.org/en/story/2026/04/1167314 https://www.ohchr.org/en/press-releases/2026/04/un-experts-demand-accountability-trafficking-allegations-epstein-files-warn | L9: {=IF($G9="","",IFERROR(INDEX(Ангилал!$A$5:$A$22,MATCH(TRUE(),INDEX(ISNUMBER(SEARCH(Ангилал!$B$5:$B$22,$G9&" "&$E9))+ISNUMBER(SEARCH(Ангилал!$C$5:$C$22,$G9&" "&$E9))+IF(Ангилал!$D$5:$D$22="",0,ISNUMBER(SEARCH(Ангилал!$D$5:$D$22,$G9&" "&$E9)))+IF(Ангилал!$E$5:$E$22="",0,ISNUMBER(SEARCH(Ангилал!$E$5:$E$22,$G9&" "&$E9)))>0,0),0)),"Бусад"))} -> Амьд явах, халдашгүй байх эрх | N9: =IF($G9="","",IF($M9<>"",$M9,$L9)) -> Амьд явах, халдашгүй байх эрх | O9: {=IF($G9="","",IFERROR(INDEX(Ангилал!$G$5:$G$16,MATCH(TRUE(),INDEX(ISNUMBER(SEARCH(Ангилал!$H$5:$H$16,$G9&" "&$E9))+ISNUMBER(SEARCH(Ангилал!$I$5:$I$16,$G9&" "&$E9))+ISNUMBER(SEARCH(Ангилал!$J$5:$J$16,$G9&" "&$E9))+ISNUMBER(SEARCH(Ангилал!$K$5:$K$16,$G9&" "&$E9))>0,0),0)),"Ерөнхий нийт"))} -> Ерөнхий нийт | Q9: =IF($G9="","",IF($P9<>"",$P9,$O9)) -> Ерөнхий нийт
A10: 6 | B10: 2026.04.17 | C10: 2026.04.13 | D10: Sex Testing All Women Athletes is a Discriminatory Rights Violation | E10: Спортын байгууллагууд тестостерон дааврын хэмжээ ердийн хүнийхээс өндөр байдаг эмэгтэйчүүдийг спортод оруулдаг гэж үзэн, Олон улсын олимпын хорооноос эмэгтэй тамирчдыг генетикийн хүйсийн шинжилгээнд хамруулахаа мэдэгдэв. Энэ нь "эмэгтэй" гэх ангиллыг хамгаалах зорилготой гэх боловч хүнийг хүйсээр ялгаварлан гадуурхсан, шинжлэх ухаанаар нотлогдоогүй шийдвэр ажээ. | G10: Ялгаварлан гадуурхалтаас ангид байх, халдашгүй чөлөөтэй байх | H10: Олон улсын олимпын хороо | I10: Human rights watch | J10: https://www.hrw.org/news/2026/04/13/sex-testing-all-women-athletes-is-a-discriminatory-rights-violation https://www.olympics.com/ioc/news/international-olympic-committee-announces-new-policy-on-the-protection-of-the-female-women-s-category-in-olympic-sport | L10: {=IF($G10="","",IFERROR(INDEX(Ангилал!$A$5:$A$22,MATCH(TRUE(),INDEX(ISNUMBER(SEARCH(Ангилал!$B$5:$B$22,$G10&" "&$E10))+ISNUMBER(SEARCH(Ангилал!$C$5:$C$22,$G10&" "&$E10))+IF(Ангилал!$D$5:$D$22="",0,ISNUMBER(SEARCH(Ангилал!$D$5:$D$22,$G10&" "&$E10)))+IF(Ангилал!$E$5:$E$22="",0,ISNUMBER(SEARCH(Ангилал!$E$5:$E$22,$G10&" "&$E10)))>0,0),0)),"Бусад"))} -> Амьд явах, халдашгүй байх эрх | N10: =IF($G10="","",IF($M10<>"",$M10,$L10)) -> Амьд явах, халдашгүй байх эрх | O10: {=IF($G10="","",IFERROR(INDEX(Ангилал!$G$5:$G$16,MATCH(TRUE(),INDEX(ISNUMBER(SEARCH(Ангилал!$H$5:$H$16,$G10&" "&$E10))+ISNUMBER(SEARCH(Ангилал!$I$5:$I$16,$G10&" "&$E10))+ISNUMBER(SEARCH(Ангилал!$J$5:$J$16,$G10&" "&$E10))+ISNUMBER(SEARCH(Ангилал!$K$5:$K$16,$G10&" "&$E10))>0,0),0)),"Ерөнхий нийт"))} -> Эмэгтэйчүүд | Q10: =IF($G10="","",IF($P10<>"",$P10,$O10)) -> Эмэгтэйчүүд
A11: 7 | B11: 2026.04.17 | C11: 2026.04.16 | D11: Andrea Bolaños Vargas appointed UN Special Rapporteur on the situation of human rights defenders by the UN Human Rights Council | E11: Хүний эрх хамгаалагчдын асуудлаарх НҮБ-ын тусгай илтгэгчээр Andrea Bolaños Vargas томилогджээ. | I11: civicus | J11: https://www.civicus.org/index.php/media-resources/news/8253-andrea-bolanos-vargas-appointed-un-special-rapporteur-on-the-situation-of-human-rights-defenders-by-the-un-human-rights-council | L11: {=IF($G11="","",IFERROR(INDEX(Ангилал!$A$5:$A$22,MATCH(TRUE(),INDEX(ISNUMBER(SEARCH(Ангилал!$B$5:$B$22,$G11&" "&$E11))+ISNUMBER(SEARCH(Ангилал!$C$5:$C$22,$G11&" "&$E11))+IF(Ангилал!$D$5:$D$22="",0,ISNUMBER(SEARCH(Ангилал!$D$5:$D$22,$G11&" "&$E11)))+IF(Ангилал!$E$5:$E$22="",0,ISNUMBER(SEARCH(Ангилал!$E$5:$E$22,$G11&" "&$E11)))>0,0),0)),"Бусад"))} | N11: =IF($G11="","",IF($M11<>"",$M11,$L11)) | O11: {=IF($G11="","",IFERROR(INDEX(Ангилал!$G$5:$G$16,MATCH(TRUE(),INDEX(ISNUMBER(SEARCH(Ангилал!$H$5:$H$16,$G11&" "&$E11))+ISNUMBER(SEARCH(Ангилал!$I$5:$I$16,$G11&" "&$E11))+ISNUMBER(SEARCH(Ангилал!$J$5:$J$16,$G11&" "&$E11))+ISNUMBER(SEARCH(Ангилал!$K$5:$K$16,$G11&" "&$E11))>0,0),0)),"Ерөнхий нийт"))} | Q11: =IF($G11="","",IF($P11<>"",$P11,$O11))
A12: 2026.04.20-24 | L12: {=IF($G12="","",IFERROR(INDEX(Ангилал!$A$5:$A$22,MATCH(TRUE(),INDEX(ISNUMBER(SEARCH(Ангилал!$B$5:$B$22,$G12&" "&$E12))+ISNUMBER(SEARCH(Ангилал!$C$5:$C$22,$G12&" "&$E12))+IF(Ангилал!$D$5:$D$22="",0,ISNUMBER(SEARCH(Ангилал!$D$5:$D$22,$G12&" "&$E12)))+IF(Ангилал!$E$5:$E$22="",0,ISNUMBER(SEARCH(Ангилал!$E$5:$E$22,$G12&" "&$E12)))>0,0),0)),"Бусад"))} | N12: =IF($G12="","",IF($M12<>"",$M12,$L12)) | O12: {=IF($G12="","",IFERROR(INDEX(Ангилал!$G$5:$G$16,MATCH(TRUE(),INDEX(ISNUMBER(SEARCH(Ангилал!$H$5:$H$16,$G12&" "&$E12))+ISNUMBER(SEARCH(Ангилал!$I$5:$I$16,$G12&" "&$E12))+ISNUMBER(SEARCH(Ангилал!$J$5:$J$16,$G12&" "&$E12))+ISNUMBER(SEARCH(Ангилал!$K$5:$K$16,$G12&" "&$E12))>0,0),0)),"Ерөнхий нийт"))} | Q12: =IF($G12="","",IF($P12<>"",$P12,$O12))
A13: 8 | B13: 2026.04.16 | C13: 2026.04.15 | D13: Туркийн сургуульд хоёр өдрийн дотор гарсан хоёр дахь зэвсэгт халдлагын үеэр есөн хүн амиа алджээ | E13: Турк улсын өмнөд хэсэгт оршдог ерөнхий боловсролын сургуульд өчигдөр зэвсэгт халдлага гарсны улмаас найман сурагч, нэг багш алагдаж, хэд хэдэн хүн шархадсан тухай тус улсын дотоод хэргийн сайд Мустафа Чифчи мэдээлжээ. | F13: Турк улсын Кахраманмараш мужийн Айсер Чалик сургууль | G13: Амьд явах, халдашгүй чөлөөтэй байх эрх | H13: Халдлагыг 14 настай хүүхэд үйлджээ. | I13: IKON | J13: https://ikon.mn/n/3mtg | L13: {=IF($G13="","",IFERROR(INDEX(Ангилал!$A$5:$A$22,MATCH(TRUE(),INDEX(ISNUMBER(SEARCH(Ангилал!$B$5:$B$22,$G13&" "&$E13))+ISNUMBER(SEARCH(Ангилал!$C$5:$C$22,$G13&" "&$E13))+IF(Ангилал!$D$5:$D$22="",0,ISNUMBER(SEARCH(Ангилал!$D$5:$D$22,$G13&" "&$E13)))+IF(Ангилал!$E$5:$E$22="",0,ISNUMBER(SEARCH(Ангилал!$E$5:$E$22,$G13&" "&$E13)))>0,0),0)),"Бусад"))} -> Хүүхдийн эрх | N13: =IF($G13="","",IF($M13<>"",$M13,$L13)) -> Хүүхдийн эрх | O13: {=IF($G13="","",IFERROR(INDEX(Ангилал!$G$5:$G$16,MATCH(TRUE(),INDEX(ISNUMBER(SEARCH(Ангилал!$H$5:$H$16,$G13&" "&$E13))+ISNUMBER(SEARCH(Ангилал!$I$5:$I$16,$G13&" "&$E13))+ISNUMBER(SEARCH(Ангилал!$J$5:$J$16,$G13&" "&$E13))+ISNUMBER(SEARCH(Ангилал!$K$5:$K$16,$G13&" "&$E13))>0,0),0)),"Ерөнхий нийт"))} -> Хүүхэд | Q13: =IF($G13="","",IF($P13<>"",$P13,$O13)) -> Хүүхэд
A14: 9 | B14: 2026.04.17 | C14: 2026.04.16 | D14: Орос улс энэ оны хамгийн том агаарын цохилтоо Украины гол хотууд руу чиглүүлсний улмаас 18 хүний амь үрэгдэв. | E14: Орос улс энэ оны хамгийн олон нисгэгчгүй онгоц, пуужин оролцуулсан агаарын цохилтоо явуулсны улмаас Украин даяар 18 хүний амь үрэгдэж, 118 хүн шархадсаныг Киевийн эрх баригчид Пүрэв гарагт /2026.04.16/ мэдээлжээ. | F14: Украйн улс | G14: Амьд явах, халдашгүй чөлөөтэй байх эрх | H14: ОХУ | I14: IKON | J14: https://ikon.mn/n/3mul | L14: {=IF($G14="","",IFERROR(INDEX(Ангилал!$A$5:$A$22,MATCH(TRUE(),INDEX(ISNUMBER(SEARCH(Ангилал!$B$5:$B$22,$G14&" "&$E14))+ISNUMBER(SEARCH(Ангилал!$C$5:$C$22,$G14&" "&$E14))+IF(Ангилал!$D$5:$D$22="",0,ISNUMBER(SEARCH(Ангилал!$D$5:$D$22,$G14&" "&$E14)))+IF(Ангилал!$E$5:$E$22="",0,ISNUMBER(SEARCH(Ангилал!$E$5:$E$22,$G14&" "&$E14)))>0,0),0)),"Бусад"))} -> Амьд явах, халдашгүй байх эрх | N14: =IF($G14="","",IF($M14<>"",$M14,$L14)) -> Амьд явах, халдашгүй байх эрх | O14: {=IF($G14="","",IFERROR(INDEX(Ангилал!$G$5:$G$16,MATCH(TRUE(),INDEX(ISNUMBER(SEARCH(Ангилал!$H$5:$H$16,$G14&" "&$E14))+ISNUMBER(SEARCH(Ангилал!$I$5:$I$16,$G14&" "&$E14))+ISNUMBER(SEARCH(Ангилал!$J$5:$J$16,$G14&" "&$E14))+ISNUMBER(SEARCH(Ангилал!$K$5:$K$16,$G14&" "&$E14))>0,0),0)),"Ерөнхий нийт"))} -> Ерөнхий нийт | Q14: =IF($G14="","",IF($P14<>"",$P14,$O14)) -> Ерөнхий нийт
A15: 10 | B15: 2026.04.19 | C15: 2026.04.18 | D15: Киев хотод зэвсэгт халдлага гарсны улмаас зургаан хүний амь үрэгджээ. | E15: Киевийн гудамжинд зургаан хүний амийг хөнөөсөн зэвсэгт халдлага гарсан тухай Украины албаныхан мэдээлжээ. | F15: Украйн улс, Киев хот | G15: Амьд явах, халдашгүй чөлөөтэй байх эрх | H15: 1968 онд төрсөн, ОХУ-ын Москва хотын уугуул нэгэн | I15: IKON | J15: https://ikon.mn/n/3mw0 | L15: {=IF($G15="","",IFERROR(INDEX(Ангилал!$A$5:$A$22,MATCH(TRUE(),INDEX(ISNUMBER(SEARCH(Ангилал!$B$5:$B$22,$G15&" "&$E15))+ISNUMBER(SEARCH(Ангилал!$C$5:$C$22,$G15&" "&$E15))+IF(Ангилал!$D$5:$D$22="",0,ISNUMBER(SEARCH(Ангилал!$D$5:$D$22,$G15&" "&$E15)))+IF(Ангилал!$E$5:$E$22="",0,ISNUMBER(SEARCH(Ангилал!$E$5:$E$22,$G15&" "&$E15)))>0,0),0)),"Бусад"))} -> Амьд явах, халдашгүй байх эрх | N15: =IF($G15="","",IF($M15<>"",$M15,$L15)) -> Амьд явах, халдашгүй байх эрх | O15: {=IF($G15="","",IFERROR(INDEX(Ангилал!$G$5:$G$16,MATCH(TRUE(),INDEX(ISNUMBER(SEARCH(Ангилал!$H$5:$H$16,$G15&" "&$E15))+ISNUMBER(SEARCH(Ангилал!$I$5:$I$16,$G15&" "&$E15))+ISNUMBER(SEARCH(Ангилал!$J$5:$J$16,$G15&" "&$E15))+ISNUMBER(SEARCH(Ангилал!$K$5:$K$16,$G15&" "&$E15))>0,0),0)),"Ерөнхий нийт"))} -> Ерөнхий нийт | Q15: =IF($G15="","",IF($P15<>"",$P15,$O15)) -> Ерөнхий нийт
A16: 11 | B16: 2026.04.20 | D16: АНУ-ын эрх баригчид Ираны зэвсгийг Суданд нийлүүлж байсан иран гаралтай эмэгтэйг баривчилжээ | E16: АНУ-ын холбооны прокурорууд Ням гарагт Лос-Анжелесын олон улсын нисэх буудалд Тегераны засгийн газрын өмнөөс Суданд зэр зэвсэг нийлүүлж байсан иран гаралтай эмэгтэйг баривчилжээ. | F16: АНУ, Лос-Анжелес хот | H16: 2016 онд АНУ-д байнга оршин суух хууль ёсны эрх авсан Ираны иргэн 44 настай Шамим Мафи | I16: IKON | J16: https://ikon.mn/n/3mwe | L16: {=IF($G16="","",IFERROR(INDEX(Ангилал!$A$5:$A$22,MATCH(TRUE(),INDEX(ISNUMBER(SEARCH(Ангилал!$B$5:$B$22,$G16&" "&$E16))+ISNUMBER(SEARCH(Ангилал!$C$5:$C$22,$G16&" "&$E16))+IF(Ангилал!$D$5:$D$22="",0,ISNUMBER(SEARCH(Ангилал!$D$5:$D$22,$G16&" "&$E16)))+IF(Ангилал!$E$5:$E$22="",0,ISNUMBER(SEARCH(Ангилал!$E$5:$E$22,$G16&" "&$E16)))>0,0),0)),"Бусад"))} | N16: =IF($G16="","",IF($M16<>"",$M16,$L16)) | O16: {=IF($G16="","",IFERROR(INDEX(Ангилал!$G$5:$G$16,MATCH(TRUE(),INDEX(ISNUMBER(SEARCH(Ангилал!$H$5:$H$16,$G16&" "&$E16))+ISNUMBER(SEARCH(Ангилал!$I$5:$I$16,$G16&" "&$E16))+ISNUMBER(SEARCH(Ангилал!$J$5:$J$16,$G16&" "&$E16))+ISNUMBER(SEARCH(Ангилал!$K$5:$K$16,$G16&" "&$E16))>0,0),0)),"Ерөнхий нийт"))} | Q16: =IF($G16="","",IF($P16<>"",$P16,$O16))
A17: 12 | B17: 2026.04.21 | D17: Мексикт жуулчид руу гал нээжээ. | E17: Мехико хотоос холгүй орших жуулчдын очих дуртай түүхэн дурсгалт газар болох Теотиуаканы пирамидуудын орчимд зэвсэглэсэн этгээд гал нээсний улмаас Канадын нэг иргэн амиа алдаж, 13 хүн шархадсан тухай "Al Jazeera" суваг мэдээлжээ. | F17: Мексик улс, Мехико хот | G17: Амьд явах, халдашгүй чөлөөтэй байх эрх | H17: Мексикийн иргэн Хулио Сезар Жассо Рамирез | I17: Монцамэ | J17: https://www.montsame.mn/mn/read/396734 | L17: {=IF($G17="","",IFERROR(INDEX(Ангилал!$A$5:$A$22,MATCH(TRUE(),INDEX(ISNUMBER(SEARCH(Ангилал!$B$5:$B$22,$G17&" "&$E17))+ISNUMBER(SEARCH(Ангилал!$C$5:$C$22,$G17&" "&$E17))+IF(Ангилал!$D$5:$D$22="",0,ISNUMBER(SEARCH(Ангилал!$D$5:$D$22,$G17&" "&$E17)))+IF(Ангилал!$E$5:$E$22="",0,ISNUMBER(SEARCH(Ангилал!$E$5:$E$22,$G17&" "&$E17)))>0,0),0)),"Бусад"))} -> Амьд явах, халдашгүй байх эрх | N17: =IF($G17="","",IF($M17<>"",$M17,$L17)) -> Амьд явах, халдашгүй байх эрх | O17: {=IF($G17="","",IFERROR(INDEX(Ангилал!$G$5:$G$16,MATCH(TRUE(),INDEX(ISNUMBER(SEARCH(Ангилал!$H$5:$H$16,$G17&" "&$E17))+ISNUMBER(SEARCH(Ангилал!$I$5:$I$16,$G17&" "&$E17))+ISNUMBER(SEARCH(Ангилал!$J$5:$J$16,$G17&" "&$E17))+ISNUMBER(SEARCH(Ангилал!$K$5:$K$16,$G17&" "&$E17))>0,0),0)),"Ерөнхий нийт"))} -> Ерөнхий нийт | Q17: =IF($G17="","",IF($P17<>"",$P17,$O17)) -> Ерөнхий нийт
A18: 13 | B18: 2026.04.22 | D18: Extreme heat pushing global food systems to the brink, UN agencies warn | E18: хэт халуун нь дэлхийн хүнс, газар тариалангийн системийг сүйрлийн ирмэгт хүргэж, тэрбум гаруй хүний ​​амьжиргаанд заналхийлж байна. Учир нь температур нэмэгдэж, халууны давтамж нэмэгдэж байгаа нь дэлхий даяар хүнс үйлдвэрлэх аргыг дахин тодорхойлод хүргэж байна. | F18: Дэлхий даяар | G18: зохистой хоол, хүнсээр хангагдах эрх | I18: UN news | J18: https://news.un.org/en/story/2026/04/1167352 | L18: {=IF($G18="","",IFERROR(INDEX(Ангилал!$A$5:$A$22,MATCH(TRUE(),INDEX(ISNUMBER(SEARCH(Ангилал!$B$5:$B$22,$G18&" "&$E18))+ISNUMBER(SEARCH(Ангилал!$C$5:$C$22,$G18&" "&$E18))+IF(Ангилал!$D$5:$D$22="",0,ISNUMBER(SEARCH(Ангилал!$D$5:$D$22,$G18&" "&$E18)))+IF(Ангилал!$E$5:$E$22="",0,ISNUMBER(SEARCH(Ангилал!$E$5:$E$22,$G18&" "&$E18)))>0,0),0)),"Бусад"))} -> Хүнс, ус, орон сууцны эрх | N18: =IF($G18="","",IF($M18<>"",$M18,$L18)) -> Хүнс, ус, орон сууцны эрх | O18: {=IF($G18="","",IFERROR(INDEX(Ангилал!$G$5:$G$16,MATCH(TRUE(),INDEX(ISNUMBER(SEARCH(Ангилал!$H$5:$H$16,$G18&" "&$E18))+ISNUMBER(SEARCH(Ангилал!$I$5:$I$16,$G18&" "&$E18))+ISNUMBER(SEARCH(Ангилал!$J$5:$J$16,$G18&" "&$E18))+ISNUMBER(SEARCH(Ангилал!$K$5:$K$16,$G18&" "&$E18))>0,0),0)),"Ерөнхий нийт"))} -> Ерөнхий нийт | Q18: =IF($G18="","",IF($P18<>"",$P18,$O18)) -> Ерөнхий нийт
A19: 14 | B19: 2026.04.23 | D19: World News in Brief: Civilians at risk in Gaza and West Bank, Duterte to go on trial in ICC, Yemen detainees update | E19: Газын орон сууцны хорооллуудад үргэлжилсэн цохилт, их буу, буун дуу нь иргэдийн аюулгүй байдалд заналхийлж байгааг НҮБ-ын тусламжийн зохицуулах алба (OCHA) анхааруулав. | F19: Газын зурвас | G19: Амьд явах, халдашгүй чөлөөтэй байх эрх | I19: UN news | J19: https://news.un.org/en/story/2026/04/1167373 | L19: {=IF($G19="","",IFERROR(INDEX(Ангилал!$A$5:$A$22,MATCH(TRUE(),INDEX(ISNUMBER(SEARCH(Ангилал!$B$5:$B$22,$G19&" "&$E19))+ISNUMBER(SEARCH(Ангилал!$C$5:$C$22,$G19&" "&$E19))+IF(Ангилал!$D$5:$D$22="",0,ISNUMBER(SEARCH(Ангилал!$D$5:$D$22,$G19&" "&$E19)))+IF(Ангилал!$E$5:$E$22="",0,ISNUMBER(SEARCH(Ангилал!$E$5:$E$22,$G19&" "&$E19)))>0,0),0)),"Бусад"))} -> Амьд явах, халдашгүй байх эрх | N19: =IF($G19="","",IF($M19<>"",$M19,$L19)) -> Амьд явах, халдашгүй байх эрх | O19: {=IF($G19="","",IFERROR(INDEX(Ангилал!$G$5:$G$16,MATCH(TRUE(),INDEX(ISNUMBER(SEARCH(Ангилал!$H$5:$H$16,$G19&" "&$E19))+ISNUMBER(SEARCH(Ангилал!$I$5:$I$16,$G19&" "&$E19))+ISNUMBER(SEARCH(Ангилал!$J$5:$J$16,$G19&" "&$E19))+ISNUMBER(SEARCH(Ангилал!$K$5:$K$16,$G19&" "&$E19))>0,0),0)),"Ерөнхий нийт"))} -> Ерөнхий нийт | Q19: =IF($G19="","",IF($P19<>"",$P19,$O19)) -> Ерөнхий нийт
A20: 2026.04.25-05.01 | L20: {=IF($G20="","",IFERROR(INDEX(Ангилал!$A$5:$A$22,MATCH(TRUE(),INDEX(ISNUMBER(SEARCH(Ангилал!$B$5:$B$22,$G20&" "&$E20))+ISNUMBER(SEARCH(Ангилал!$C$5:$C$22,$G20&" "&$E20))+IF(Ангилал!$D$5:$D$22="",0,ISNUMBER(SEARCH(Ангилал!$D$5:$D$22,$G20&" "&$E20)))+IF(Ангилал!$E$5:$E$22="",0,ISNUMBER(SEARCH(Ангилал!$E$5:$E$22,$G20&" "&$E20)))>0,0),0)),"Бусад"))} | N20: =IF($G20="","",IF($M20<>"",$M20,$L20)) | O20: {=IF($G20="","",IFERROR(INDEX(Ангилал!$G$5:$G$16,MATCH(TRUE(),INDEX(ISNUMBER(SEARCH(Ангилал!$H$5:$H$16,$G20&" "&$E20))+ISNUMBER(SEARCH(Ангилал!$I$5:$I$16,$G20&" "&$E20))+ISNUMBER(SEARCH(Ангилал!$J$5:$J$16,$G20&" "&$E20))+ISNUMBER(SEARCH(Ангилал!$K$5:$K$16,$G20&" "&$E20))>0,0),0)),"Ерөнхий нийт"))} | Q20: =IF($G20="","",IF($P20<>"",$P20,$O20))
A21: 15 | B21: 2026.04.24 | D21: Two-thirds of global hunger concentrated in 10 conflict-hit countries | E21: Дэлхийн өлсгөлөнгийн эзлэх хувь зэвсэгт мөргөлдөөнд нэрвэгдсэн цөөн тооны орнуудад улам бүр нэмэгдэж байгаа бөгөөд хүнсний хомсдолд орсон хүмүүсийн гуравны хоёр нь ердөө 10 улсад төвлөрч байгааг анхааруулж байна. | G21: Зохистой хоол хүнсээр хангагдах эрх | I21: UN news | J21: https://news.un.org/en/story/2026/04/1167374 | L21: {=IF($G21="","",IFERROR(INDEX(Ангилал!$A$5:$A$22,MATCH(TRUE(),INDEX(ISNUMBER(SEARCH(Ангилал!$B$5:$B$22,$G21&" "&$E21))+ISNUMBER(SEARCH(Ангилал!$C$5:$C$22,$G21&" "&$E21))+IF(Ангилал!$D$5:$D$22="",0,ISNUMBER(SEARCH(Ангилал!$D$5:$D$22,$G21&" "&$E21)))+IF(Ангилал!$E$5:$E$22="",0,ISNUMBER(SEARCH(Ангилал!$E$5:$E$22,$G21&" "&$E21)))>0,0),0)),"Бусад"))} -> Хүнс, ус, орон сууцны эрх | N21: =IF($G21="","",IF($M21<>"",$M21,$L21)) -> Хүнс, ус, орон сууцны эрх | O21: {=IF($G21="","",IFERROR(INDEX(Ангилал!$G$5:$G$16,MATCH(TRUE(),INDEX(ISNUMBER(SEARCH(Ангилал!$H$5:$H$16,$G21&" "&$E21))+ISNUMBER(SEARCH(Ангилал!$I$5:$I$16,$G21&" "&$E21))+ISNUMBER(SEARCH(Ангилал!$J$5:$J$16,$G21&" "&$E21))+ISNUMBER(SEARCH(Ангилал!$K$5:$K$16,$G21&" "&$E21))>0,0),0)),"Ерөнхий нийт"))} -> Ерөнхий нийт | Q21: =IF($G21="","",IF($P21<>"",$P21,$O21)) -> Ерөнхий нийт
A22: 16 | B22: 2026.04.27 | D22: As warheads proliferate, decades old nuclear weapons treaty must evolve, warns UN chief | E22: Дэлхийн тэргүүлэх дипломатчид НҮБ-ын төв байранд цугларч, 1970 оны Цөмийн зэвсгийг үл дэлгэрүүлэх тухай гэрээг хянан хэлэлцэж байх үеэр НҮБ-ын Ерөнхий нарийн бичгийн дарга уг гэрээ нь хиймэл оюун ухаан болон бусад шинэ технологийн эрин үед оршин тогтнохын тулд хувьсан өөрчлөгдөх шаардлагатайг анхааруулжээ. | F22: АНУ, Нью-Йорк дахь НҮБ-ын төв байр | I22: UN news | J22: https://news.un.org/en/story/2026/04/1167387 | L22: {=IF($G22="","",IFERROR(INDEX(Ангилал!$A$5:$A$22,MATCH(TRUE(),INDEX(ISNUMBER(SEARCH(Ангилал!$B$5:$B$22,$G22&" "&$E22))+ISNUMBER(SEARCH(Ангилал!$C$5:$C$22,$G22&" "&$E22))+IF(Ангилал!$D$5:$D$22="",0,ISNUMBER(SEARCH(Ангилал!$D$5:$D$22,$G22&" "&$E22)))+IF(Ангилал!$E$5:$E$22="",0,ISNUMBER(SEARCH(Ангилал!$E$5:$E$22,$G22&" "&$E22)))>0,0),0)),"Бусад"))} -> Бусад | N22: =IF($G22="","",IF($M22<>"",$M22,$L22)) -> Бусад | O22: {=IF($G22="","",IFERROR(INDEX(Ангилал!$G$5:$G$16,MATCH(TRUE(),INDEX(ISNUMBER(SEARCH(Ангилал!$H$5:$H$16,$G22&" "&$E22))+ISNUMBER(SEARCH(Ангилал!$I$5:$I$16,$G22&" "&$E22))+ISNUMBER(SEARCH(Ангилал!$J$5:$J$16,$G22&" "&$E22))+ISNUMBER(SEARCH(Ангилал!$K$5:$K$16,$G22&" "&$E22))>0,0),0)),"Ерөнхий нийт"))} -> Ерөнхий нийт | Q22: =IF($G22="","",IF($P22<>"",$P22,$O22)) -> Ерөнхий нийт
A23: 17 | B23: 2026.04.28 | D23: А.Гутерриш: Хиймэл оюун, квант тооцооллын технологиуд цөмийн аюулыг ойртуулж байна | E23: Хиймэл оюун, квант тооцоолол зэрэг шинэ технологиудын хурдацтай хөгжил нь цөмийн аюулгүй байдлыг улам хүндрүүлж байна гэж НҮБ-ын Ерөнхий нарийн бичгийн дарга Антонио Гуттереш мэдэгджээ. | F23: АНУ, Нью-Йорк дахь НҮБ-ын төв байр | I23: Монцамэ | J23: https://montsame.mn/mn/read/397382 | L23: {=IF($G23="","",IFERROR(INDEX(Ангилал!$A$5:$A$22,MATCH(TRUE(),INDEX(ISNUMBER(SEARCH(Ангилал!$B$5:$B$22,$G23&" "&$E23))+ISNUMBER(SEARCH(Ангилал!$C$5:$C$22,$G23&" "&$E23))+IF(Ангилал!$D$5:$D$22="",0,ISNUMBER(SEARCH(Ангилал!$D$5:$D$22,$G23&" "&$E23)))+IF(Ангилал!$E$5:$E$22="",0,ISNUMBER(SEARCH(Ангилал!$E$5:$E$22,$G23&" "&$E23)))>0,0),0)),"Бусад"))} -> Бусад | N23: =IF($G23="","",IF($M23<>"",$M23,$L23)) -> Бусад | O23: {=IF($G23="","",IFERROR(INDEX(Ангилал!$G$5:$G$16,MATCH(TRUE(),INDEX(ISNUMBER(SEARCH(Ангилал!$H$5:$H$16,$G23&" "&$E23))+ISNUMBER(SEARCH(Ангилал!$I$5:$I$16,$G23&" "&$E23))+ISNUMBER(SEARCH(Ангилал!$J$5:$J$16,$G23&" "&$E23))+ISNUMBER(SEARCH(Ангилал!$K$5:$K$16,$G23&" "&$E23))>0,0),0)),"Ерөнхий нийт"))} -> Ерөнхий нийт | Q23: =IF($G23="","",IF($P23<>"",$P23,$O23)) -> Ерөнхий нийт
A24: 18 | B24: 2026.04.28 | D24: Чад улсад худаг булаацалдсан үндэстэн хоорондын мөргөлдөөний үеэр 42 хүн алагджээ | E24: Сахарын цөлд оршдог төв Африкийн Чад улсад худаг булаацалдсан үндэстэн хоорондын мөргөлдөөн гарсны улмаас 42 хүн амиа алдаж, 10 хүн шархаджээ. | F24: Чад улс, Вади Фира муж | G24: Амьд явах, халдашгүй чөлөөтэй байх эрх | I24: IKON | J24: https://ikon.mn/n/3n3n | L24: {=IF($G24="","",IFERROR(INDEX(Ангилал!$A$5:$A$22,MATCH(TRUE(),INDEX(ISNUMBER(SEARCH(Ангилал!$B$5:$B$22,$G24&" "&$E24))+ISNUMBER(SEARCH(Ангилал!$C$5:$C$22,$G24&" "&$E24))+IF(Ангилал!$D$5:$D$22="",0,ISNUMBER(SEARCH(Ангилал!$D$5:$D$22,$G24&" "&$E24)))+IF(Ангилал!$E$5:$E$22="",0,ISNUMBER(SEARCH(Ангилал!$E$5:$E$22,$G24&" "&$E24)))>0,0),0)),"Бусад"))} -> Амьд явах, халдашгүй байх эрх | N24: =IF($G24="","",IF($M24<>"",$M24,$L24)) -> Амьд явах, халдашгүй байх эрх | O24: {=IF($G24="","",IFERROR(INDEX(Ангилал!$G$5:$G$16,MATCH(TRUE(),INDEX(ISNUMBER(SEARCH(Ангилал!$H$5:$H$16,$G24&" "&$E24))+ISNUMBER(SEARCH(Ангилал!$I$5:$I$16,$G24&" "&$E24))+ISNUMBER(SEARCH(Ангилал!$J$5:$J$16,$G24&" "&$E24))+ISNUMBER(SEARCH(Ангилал!$K$5:$K$16,$G24&" "&$E24))>0,0),0)),"Ерөнхий нийт"))} -> Цөөнх, үндэстэн ястан | Q24: =IF($G24="","",IF($P24<>"",$P24,$O24)) -> Цөөнх, үндэстэн ястан
A25: 19 | B25: 2026.04.28 | C25: 2026.04.23 | D25: A Deadline for the World to Act on Women’s Rights | E25: Афганистанд охидыг зургаадугаар ангиас дээш боловсрол эзэмшихийг хориглоод 1677 хоног өнгөрсөн бөгөөд ийнхүү эмэгтэйчүүд, охидын эрхийг системтэйгээр зөрчиж байгаа үйлдлүүд нь олон улсын эрх зүйн дагуу “хүйсийн үндсэн дээрх ялгаварлан гадуурхалт” төдийгүй “хүн төрөлхтний эсрэг гэмт хэрэг” гэж үзэгдэх үндэслэлтэй. Иймд улс орнууд мэдэгдэл гаргаж, санаа зовниж байгаагаа илэрхийлэхээс илүү зүйл хийх ёстой. | F25: Афганистан улс | G25: Жендэрийн эрх тэгш байдал, ялгаварлан гадуурхалтаас ангид байх | H25: Талибанчууд | I25: Human rights watch | J25: https://www.hrw.org/news/2026/04/28/a-deadline-for-the-world-to-act-on-womens-rights | L25: {=IF($G25="","",IFERROR(INDEX(Ангилал!$A$5:$A$22,MATCH(TRUE(),INDEX(ISNUMBER(SEARCH(Ангилал!$B$5:$B$22,$G25&" "&$E25))+ISNUMBER(SEARCH(Ангилал!$C$5:$C$22,$G25&" "&$E25))+IF(Ангилал!$D$5:$D$22="",0,ISNUMBER(SEARCH(Ангилал!$D$5:$D$22,$G25&" "&$E25)))+IF(Ангилал!$E$5:$E$22="",0,ISNUMBER(SEARCH(Ангилал!$E$5:$E$22,$G25&" "&$E25)))>0,0),0)),"Бусад"))} -> Ялгаварлан гадуурхалтаас ангид байх, тэгш эрх | N25: =IF($G25="","",IF($M25<>"",$M25,$L25)) -> Ялгаварлан гадуурхалтаас ангид байх, тэгш эрх | O25: {=IF($G25="","",IFERROR(INDEX(Ангилал!$G$5:$G$16,MATCH(TRUE(),INDEX(ISNUMBER(SEARCH(Ангилал!$H$5:$H$16,$G25&" "&$E25))+ISNUMBER(SEARCH(Ангилал!$I$5:$I$16,$G25&" "&$E25))+ISNUMBER(SEARCH(Ангилал!$J$5:$J$16,$G25&" "&$E25))+ISNUMBER(SEARCH(Ангилал!$K$5:$K$16,$G25&" "&$E25))>0,0),0)),"Ерөнхий нийт"))} -> Эмэгтэйчүүд | Q25: =IF($G25="","",IF($P25<>"",$P25,$O25)) -> Эмэгтэйчүүд
A26: 20 | B26: 2026.04.29 | C26: 2026.04.28 | D26: Оросын газрын тосны үйлдвэр дахин Украины халдлагад өртсөний улмаас томоохон гал гарч, иргэдийг нүүлгэн шилжүүлжээ | E26: Украины нисгэгчгүй онгоцны халдлагын улмаас Хар тэнгисийн эрэг дэх Оросын Туапсе хотын газрын тос боловсруулах үйлдвэрт томоохон гал гарч, ойролцоох барилгуудаас иргэдийг нүүлгэн шилжүүлсэн тухай орон нутгийн эрх баригчид Мягмар гарагт мэдээлжээ. | F26: ОХУ, Туапсе хот | G26: Амьд явах, халдашгүй чөлөөтэй байх эрх | H26: Украин улс | I26: IKON | J26: https://ikon.mn/n/3n4o | L26: {=IF($G26="","",IFERROR(INDEX(Ангилал!$A$5:$A$22,MATCH(TRUE(),INDEX(ISNUMBER(SEARCH(Ангилал!$B$5:$B$22,$G26&" "&$E26))+ISNUMBER(SEARCH(Ангилал!$C$5:$C$22,$G26&" "&$E26))+IF(Ангилал!$D$5:$D$22="",0,ISNUMBER(SEARCH(Ангилал!$D$5:$D$22,$G26&" "&$E26)))+IF(Ангилал!$E$5:$E$22="",0,ISNUMBER(SEARCH(Ангилал!$E$5:$E$22,$G26&" "&$E26)))>0,0),0)),"Бусад"))} -> Амьд явах, халдашгүй байх эрх | N26: =IF($G26="","",IF($M26<>"",$M26,$L26)) -> Амьд явах, халдашгүй байх эрх | O26: {=IF($G26="","",IFERROR(INDEX(Ангилал!$G$5:$G$16,MATCH(TRUE(),INDEX(ISNUMBER(SEARCH(Ангилал!$H$5:$H$16,$G26&" "&$E26))+ISNUMBER(SEARCH(Ангилал!$I$5:$I$16,$G26&" "&$E26))+ISNUMBER(SEARCH(Ангилал!$J$5:$J$16,$G26&" "&$E26))+ISNUMBER(SEARCH(Ангилал!$K$5:$K$16,$G26&" "&$E26))>0,0),0)),"Ерөнхий нийт"))} -> Ерөнхий нийт | Q26: =IF($G26="","",IF($P26<>"",$P26,$O26)) -> Ерөнхий нийт
A27: 21 | B27: 2026.04.29 | D27: Nepal: Transgender Rights Progress Stalls | E27: Балбын эрх баригчид трансжендер хүмүүсийн үнэмлэх дээрх хууль ёсны хүйсээ өөрчлөх өргөдлийг шийдвэрлэхээ зогсоосон нь олон жилийн ахиц дэвшилтэй ухарч, хуулийн өмнө хүлээн зөвшөөрөгдөх үндсэн эрхийг зөрчиж байна гэжээ. | F27: Непал | G27: Ялгаварлан гадуурхалтаас ангид байх, халдашгүй чөлөөтэй байх | I27: Human rights watch | J27: https://www.hrw.org/news/2026/04/29/nepal-transgender-rights-progress-stalls | L27: {=IF($G27="","",IFERROR(INDEX(Ангилал!$A$5:$A$22,MATCH(TRUE(),INDEX(ISNUMBER(SEARCH(Ангилал!$B$5:$B$22,$G27&" "&$E27))+ISNUMBER(SEARCH(Ангилал!$C$5:$C$22,$G27&" "&$E27))+IF(Ангилал!$D$5:$D$22="",0,ISNUMBER(SEARCH(Ангилал!$D$5:$D$22,$G27&" "&$E27)))+IF(Ангилал!$E$5:$E$22="",0,ISNUMBER(SEARCH(Ангилал!$E$5:$E$22,$G27&" "&$E27)))>0,0),0)),"Бусад"))} -> Амьд явах, халдашгүй байх эрх | N27: =IF($G27="","",IF($M27<>"",$M27,$L27)) -> Амьд явах, халдашгүй байх эрх | O27: {=IF($G27="","",IFERROR(INDEX(Ангилал!$G$5:$G$16,MATCH(TRUE(),INDEX(ISNUMBER(SEARCH(Ангилал!$H$5:$H$16,$G27&" "&$E27))+ISNUMBER(SEARCH(Ангилал!$I$5:$I$16,$G27&" "&$E27))+ISNUMBER(SEARCH(Ангилал!$J$5:$J$16,$G27&" "&$E27))+ISNUMBER(SEARCH(Ангилал!$K$5:$K$16,$G27&" "&$E27))>0,0),0)),"Ерөнхий нийт"))} -> Ерөнхий нийт | Q27: =IF($G27="","",IF($P27<>"",$P27,$O27)) -> Ерөнхий нийт
A28: 22 | B28: 2026.04.30 | D28: Hormuz crisis strangling global economy, Guterres warns, demanding solutions to end stalemate | E28: Ормузын хоолойн хурцадмал байдал нь хэдэн арван сая хүнийг ядууралд оруулж, дэлхийн өлсгөлөнг нэмэгдүүлж, тэр ч байтугай дэлхийг уналтад хүргэж болзошгүй гэж НҮБ-ын Ерөнхий нарийн бичгийн дарга пүрэв гарагт анхаарууллаа. | F28: НҮБ | H28: АНУ болон Ираны дайн | I28: UN news | J28: https://news.un.org/en/story/2026/04/1167411 | L28: {=IF($G28="","",IFERROR(INDEX(Ангилал!$A$5:$A$22,MATCH(TRUE(),INDEX(ISNUMBER(SEARCH(Ангилал!$B$5:$B$22,$G28&" "&$E28))+ISNUMBER(SEARCH(Ангилал!$C$5:$C$22,$G28&" "&$E28))+IF(Ангилал!$D$5:$D$22="",0,ISNUMBER(SEARCH(Ангилал!$D$5:$D$22,$G28&" "&$E28)))+IF(Ангилал!$E$5:$E$22="",0,ISNUMBER(SEARCH(Ангилал!$E$5:$E$22,$G28&" "&$E28)))>0,0),0)),"Бусад"))} -> Хүнс, ус, орон сууцны эрх | N28: =IF($G28="","",IF($M28<>"",$M28,$L28)) -> Хүнс, ус, орон сууцны эрх | O28: {=IF($G28="","",IFERROR(INDEX(Ангилал!$G$5:$G$16,MATCH(TRUE(),INDEX(ISNUMBER(SEARCH(Ангилал!$H$5:$H$16,$G28&" "&$E28))+ISNUMBER(SEARCH(Ангилал!$I$5:$I$16,$G28&" "&$E28))+ISNUMBER(SEARCH(Ангилал!$J$5:$J$16,$G28&" "&$E28))+ISNUMBER(SEARCH(Ангилал!$K$5:$K$16,$G28&" "&$E28))>0,0),0)),"Ерөнхий нийт"))} -> Ерөнхий нийт | Q28: =IF($G28="","",IF($P28<>"",$P28,$O28)) -> Ерөнхий нийт
A29: 23 | B29: 2026.04.30 | D29: Lebanon strikes deepen crisis as hunger rises and conditions worsen in Gaza | E29: Пүрэв гарагт Ливаны өмнөд хэсэгт дор хаяж есөн хүн амиа алдсан тухай мэдээлсэн бөгөөд мөргөлдөөнөөс үүдэн энгийн иргэдэд ноцтой хохирол учрах, өлсгөлөн нэмэгдэх, төрийн үйлчилгээний ачаалал хэтрэх зэргээр илэрч буй хямралыг улам даамжруулж байна. | F29: НҮБ | I29: UN news | J29: https://news.un.org/en/story/2026/04/1167418 | L29: {=IF($G29="","",IFERROR(INDEX(Ангилал!$A$5:$A$22,MATCH(TRUE(),INDEX(ISNUMBER(SEARCH(Ангилал!$B$5:$B$22,$G29&" "&$E29))+ISNUMBER(SEARCH(Ангилал!$C$5:$C$22,$G29&" "&$E29))+IF(Ангилал!$D$5:$D$22="",0,ISNUMBER(SEARCH(Ангилал!$D$5:$D$22,$G29&" "&$E29)))+IF(Ангилал!$E$5:$E$22="",0,ISNUMBER(SEARCH(Ангилал!$E$5:$E$22,$G29&" "&$E29)))>0,0),0)),"Бусад"))} -> Шашин шүтэх эрх | N29: =IF($G29="","",IF($M29<>"",$M29,$L29)) -> Шашин шүтэх эрх | O29: {=IF($G29="","",IFERROR(INDEX(Ангилал!$G$5:$G$16,MATCH(TRUE(),INDEX(ISNUMBER(SEARCH(Ангилал!$H$5:$H$16,$G29&" "&$E29))+ISNUMBER(SEARCH(Ангилал!$I$5:$I$16,$G29&" "&$E29))+ISNUMBER(SEARCH(Ангилал!$J$5:$J$16,$G29&" "&$E29))+ISNUMBER(SEARCH(Ангилал!$K$5:$K$16,$G29&" "&$E29))>0,0),0)),"Ерөнхий нийт"))} -> Ерөнхий нийт | Q29: =IF($G29="","",IF($P29<>"",$P29,$O29)) -> Ерөнхий нийт
A30: 2026.05.01-07 | L30: {=IF($G30="","",IFERROR(INDEX(Ангилал!$A$5:$A$22,MATCH(TRUE(),INDEX(ISNUMBER(SEARCH(Ангилал!$B$5:$B$22,$G30&" "&$E30))+ISNUMBER(SEARCH(Ангилал!$C$5:$C$22,$G30&" "&$E30))+IF(Ангилал!$D$5:$D$22="",0,ISNUMBER(SEARCH(Ангилал!$D$5:$D$22,$G30&" "&$E30)))+IF(Ангилал!$E$5:$E$22="",0,ISNUMBER(SEARCH(Ангилал!$E$5:$E$22,$G30&" "&$E30)))>0,0),0)),"Бусад"))} | N30: =IF($G30="","",IF($M30<>"",$M30,$L30)) | O30: {=IF($G30="","",IFERROR(INDEX(Ангилал!$G$5:$G$16,MATCH(TRUE(),INDEX(ISNUMBER(SEARCH(Ангилал!$H$5:$H$16,$G30&" "&$E30))+ISNUMBER(SEARCH(Ангилал!$I$5:$I$16,$G30&" "&$E30))+ISNUMBER(SEARCH(Ангилал!$J$5:$J$16,$G30&" "&$E30))+ISNUMBER(SEARCH(Ангилал!$K$5:$K$16,$G30&" "&$E30))>0,0),0)),"Ерөнхий нийт"))} | Q30: =IF($G30="","",IF($P30<>"",$P30,$O30))
A31: 24 | C31: 2026.04.30 | D31: 2026 World press freedom index | E31: Монгол Улс хэвлэлийн эрх чөлөөний индексээр 55.79 оноотой 180 орноос 85-т бичигдэж, өмнө жилээс 17 байр урагшилжээ. Гэсэн хэдий ч дэлхийн дундаж оноо түүхэндээ байгаагүйгээр доод түвшинд хүрсэн байна. | G31: Хэвлэлийн эрх чөлөө | I31: Reporters without borders | J31: https://rsf.org/en/index | L31: {=IF($G31="","",IFERROR(INDEX(Ангилал!$A$5:$A$22,MATCH(TRUE(),INDEX(ISNUMBER(SEARCH(Ангилал!$B$5:$B$22,$G31&" "&$E31))+ISNUMBER(SEARCH(Ангилал!$C$5:$C$22,$G31&" "&$E31))+IF(Ангилал!$D$5:$D$22="",0,ISNUMBER(SEARCH(Ангилал!$D$5:$D$22,$G31&" "&$E31)))+IF(Ангилал!$E$5:$E$22="",0,ISNUMBER(SEARCH(Ангилал!$E$5:$E$22,$G31&" "&$E31)))>0,0),0)),"Бусад"))} -> Бусад | N31: =IF($G31="","",IF($M31<>"",$M31,$L31)) -> Бусад | O31: {=IF($G31="","",IFERROR(INDEX(Ангилал!$G$5:$G$16,MATCH(TRUE(),INDEX(ISNUMBER(SEARCH(Ангилал!$H$5:$H$16,$G31&" "&$E31))+ISNUMBER(SEARCH(Ангилал!$I$5:$I$16,$G31&" "&$E31))+ISNUMBER(SEARCH(Ангилал!$J$5:$J$16,$G31&" "&$E31))+ISNUMBER(SEARCH(Ангилал!$K$5:$K$16,$G31&" "&$E31))>0,0),0)),"Ерөнхий нийт"))} -> Ерөнхий нийт | Q31: =IF($G31="","",IF($P31<>"",$P31,$O31)) -> Ерөнхий нийт
A32: 25 | C32: 2026.04.30 | D32: Abuse of women journalists made ‘easier and more damaging’ by AI | E32: Жил бүрийн 5 дугаар сарын 3-нд тэмдэглэдэг Дэлхийн хэвлэлийн эрх чөлөөний өдрийг угтан нийтэлсэн судалгаагаар 2020 оноос хойш эмэгтэй сэтгүүлчдийн эсрэг цахим хүчирхийллийн тохиолдол хоёр дахин нэмэгдсэн бөгөөд энэ нь тэдний эрүүл мэнд, сайн сайхан байдалд ноцтой сөрөг нөлөө үзүүлж байна. | F32: НҮБ | G32: Хэвлэлийн эрх чөлөө, халдашгүй чөлөөтэй байх эрх | I32: UN news | J32: https://news.un.org/en/story/2026/04/1167416 https://www.unwomen.org/sites/default/files/2026-04/tipping-point-online-violence-impacts-manifestations-and-redress-en.pdf | L32: {=IF($G32="","",IFERROR(INDEX(Ангилал!$A$5:$A$22,MATCH(TRUE(),INDEX(ISNUMBER(SEARCH(Ангилал!$B$5:$B$22,$G32&" "&$E32))+ISNUMBER(SEARCH(Ангилал!$C$5:$C$22,$G32&" "&$E32))+IF(Ангилал!$D$5:$D$22="",0,ISNUMBER(SEARCH(Ангилал!$D$5:$D$22,$G32&" "&$E32)))+IF(Ангилал!$E$5:$E$22="",0,ISNUMBER(SEARCH(Ангилал!$E$5:$E$22,$G32&" "&$E32)))>0,0),0)),"Бусад"))} -> Амьд явах, халдашгүй байх эрх | N32: =IF($G32="","",IF($M32<>"",$M32,$L32)) -> Амьд явах, халдашгүй байх эрх | O32: {=IF($G32="","",IFERROR(INDEX(Ангилал!$G$5:$G$16,MATCH(TRUE(),INDEX(ISNUMBER(SEARCH(Ангилал!$H$5:$H$16,$G32&" "&$E32))+ISNUMBER(SEARCH(Ангилал!$I$5:$I$16,$G32&" "&$E32))+ISNUMBER(SEARCH(Ангилал!$J$5:$J$16,$G32&" "&$E32))+ISNUMBER(SEARCH(Ангилал!$K$5:$K$16,$G32&" "&$E32))>0,0),0)),"Ерөнхий нийт"))} -> Эмэгтэйчүүд | Q32: =IF($G32="","",IF($P32<>"",$P32,$O32)) -> Эмэгтэйчүүд
A33: 26 | B33: 2026.04.30 | C33: 2026.04.29 | D33: Two Jewish men stabbed in London in what police call terrorist incident | E33: Лхагва гарагт Лондон хотын хойд хэсгийн навчит захын хороололд хоёр еврэй эрийг өдрийн цагаар хутгалсан хэрэг гарсныг цагдаа нэр террорист халдлага гэж тодорхойлжээ. | F33: Их Британи, Лондон | G33: Амьд явах эрх, ялгаварлан гадуурхалтаас ангид байх эрх | H33: Сэжигтэн 45 настай, Сомалид төрсөн, Британийн иргэн гэж цагдаагийн байгууллагаас мэдэгджээ. | I33: CNN | J33: https://edition.cnn.com/2026/04/29/uk/north-london-stabbing-jewish-community-intl | L33: {=IF($G33="","",IFERROR(INDEX(Ангилал!$A$5:$A$22,MATCH(TRUE(),INDEX(ISNUMBER(SEARCH(Ангилал!$B$5:$B$22,$G33&" "&$E33))+ISNUMBER(SEARCH(Ангилал!$C$5:$C$22,$G33&" "&$E33))+IF(Ангилал!$D$5:$D$22="",0,ISNUMBER(SEARCH(Ангилал!$D$5:$D$22,$G33&" "&$E33)))+IF(Ангилал!$E$5:$E$22="",0,ISNUMBER(SEARCH(Ангилал!$E$5:$E$22,$G33&" "&$E33)))>0,0),0)),"Бусад"))} -> Амьд явах, халдашгүй байх эрх | N33: =IF($G33="","",IF($M33<>"",$M33,$L33)) -> Амьд явах, халдашгүй байх эрх | O33: {=IF($G33="","",IFERROR(INDEX(Ангилал!$G$5:$G$16,MATCH(TRUE(),INDEX(ISNUMBER(SEARCH(Ангилал!$H$5:$H$16,$G33&" "&$E33))+ISNUMBER(SEARCH(Ангилал!$I$5:$I$16,$G33&" "&$E33))+ISNUMBER(SEARCH(Ангилал!$J$5:$J$16,$G33&" "&$E33))+ISNUMBER(SEARCH(Ангилал!$K$5:$K$16,$G33&" "&$E33))>0,0),0)),"Ерөнхий нийт"))} -> Ерөнхий нийт | Q33: =IF($G33="","",IF($P33<>"",$P33,$O33)) -> Ерөнхий нийт
A34: 27 | B34: 2026.05.02 | D34: What is the hantavirus that has been confirmed on an Atlantic cruise ship? | E34: Атлантын далайд аялж байсан аялалын хөлөг онгоцонд хантавирусын халдварын дэгдэлт гарсны улмаас гурван хүн нас барсан гэж Дэлхийн эрүүл мэндийн байгууллага (ДЭМБ) мэдэгдэв. | F34: ДЭМБ | G34: Амьд явах эрх | I34: ВВС | J34: https://www.bbc.com/news/articles/c8r8j1l6j0go | L34: {=IF($G34="","",IFERROR(INDEX(Ангилал!$A$5:$A$22,MATCH(TRUE(),INDEX(ISNUMBER(SEARCH(Ангилал!$B$5:$B$22,$G34&" "&$E34))+ISNUMBER(SEARCH(Ангилал!$C$5:$C$22,$G34&" "&$E34))+IF(Ангилал!$D$5:$D$22="",0,ISNUMBER(SEARCH(Ангилал!$D$5:$D$22,$G34&" "&$E34)))+IF(Ангилал!$E$5:$E$22="",0,ISNUMBER(SEARCH(Ангилал!$E$5:$E$22,$G34&" "&$E34)))>0,0),0)),"Бусад"))} -> Амьд явах, халдашгүй байх эрх | N34: =IF($G34="","",IF($M34<>"",$M34,$L34)) -> Амьд явах, халдашгүй байх эрх | O34: {=IF($G34="","",IFERROR(INDEX(Ангилал!$G$5:$G$16,MATCH(TRUE(),INDEX(ISNUMBER(SEARCH(Ангилал!$H$5:$H$16,$G34&" "&$E34))+ISNUMBER(SEARCH(Ангилал!$I$5:$I$16,$G34&" "&$E34))+ISNUMBER(SEARCH(Ангилал!$J$5:$J$16,$G34&" "&$E34))+ISNUMBER(SEARCH(Ангилал!$K$5:$K$16,$G34&" "&$E34))>0,0),0)),"Ерөнхий нийт"))} -> Ерөнхий нийт | Q34: =IF($G34="","",IF($P34<>"",$P34,$O34)) -> Ерөнхий нийт
A35: 28 | B35: 2026.05.04 | D35: Global rise of cyberattacks exposes limits of technical solutions | E35: Интернет дэлхийн өнцөг булан бүрт хүрч, эрүүл мэндийн систем, санхүүгийн зах зээлээс эхлээд төрийн үйлчилгээ, сонгуулийн зохион байгуулалт хүртэл бүх зүйлд чухал үүрэг гүйцэтгэдэг. Энэхүү эрчимтэй дэлхийн хэмжээний харилцан уялдаа холбоо нь мэдээж асар их ашиг тустай боловч кибер гэмт хэргийн тахал сая сая хүний ​​​​амь насыг эрсдэлд оруулж байна. | F35: НҮБ | G35: Цахим халдлага | I35: UN news | J35: https://news.un.org/en/story/2026/05/1167439 | L35: {=IF($G35="","",IFERROR(INDEX(Ангилал!$A$5:$A$22,MATCH(TRUE(),INDEX(ISNUMBER(SEARCH(Ангилал!$B$5:$B$22,$G35&" "&$E35))+ISNUMBER(SEARCH(Ангилал!$C$5:$C$22,$G35&" "&$E35))+IF(Ангилал!$D$5:$D$22="",0,ISNUMBER(SEARCH(Ангилал!$D$5:$D$22,$G35&" "&$E35)))+IF(Ангилал!$E$5:$E$22="",0,ISNUMBER(SEARCH(Ангилал!$E$5:$E$22,$G35&" "&$E35)))>0,0),0)),"Бусад"))} -> Эрүүл мэндийн эрх | N35: =IF($G35="","",IF($M35<>"",$M35,$L35)) -> Эрүүл мэндийн эрх | O35: {=IF($G35="","",IFERROR(INDEX(Ангилал!$G$5:$G$16,MATCH(TRUE(),INDEX(ISNUMBER(SEARCH(Ангилал!$H$5:$H$16,$G35&" "&$E35))+ISNUMBER(SEARCH(Ангилал!$I$5:$I$16,$G35&" "&$E35))+ISNUMBER(SEARCH(Ангилал!$J$5:$J$16,$G35&" "&$E35))+ISNUMBER(SEARCH(Ангилал!$K$5:$K$16,$G35&" "&$E35))>0,0),0)),"Ерөнхий нийт"))} -> Ерөнхий нийт | Q35: =IF($G35="","",IF($P35<>"",$P35,$O35)) -> Ерөнхий нийт
A36: 29 | B36: 2026.05.04 | D36: China: ‘Harmonization Plan’ Erasing Tibetan Language | E36: Human Rights Watch-ийн 2026 оны 5 дугаар сарын 4-ний тайланд дурдсанаар БНХАУ-ын эрх баригчид Төвөд хэлний хэрэглээг үе шаттайгаар багасгах зорилготой “хэлний уялдуулах” (harmonization) бодлого хэрэгжүүлж байна гэж анхааруулжээ. | G36: Үндэстний цөөнх | H36: БНХАУ-ын эрх баригчид | I36: Human rights watch | J36: https://www.hrw.org/news/2026/05/04/china-harmonization-plan-erasing-tibetan-language | L36: {=IF($G36="","",IFERROR(INDEX(Ангилал!$A$5:$A$22,MATCH(TRUE(),INDEX(ISNUMBER(SEARCH(Ангилал!$B$5:$B$22,$G36&" "&$E36))+ISNUMBER(SEARCH(Ангилал!$C$5:$C$22,$G36&" "&$E36))+IF(Ангилал!$D$5:$D$22="",0,ISNUMBER(SEARCH(Ангилал!$D$5:$D$22,$G36&" "&$E36)))+IF(Ангилал!$E$5:$E$22="",0,ISNUMBER(SEARCH(Ангилал!$E$5:$E$22,$G36&" "&$E36)))>0,0),0)),"Бусад"))} -> Бусад | N36: =IF($G36="","",IF($M36<>"",$M36,$L36)) -> Бусад | O36: {=IF($G36="","",IFERROR(INDEX(Ангилал!$G$5:$G$16,MATCH(TRUE(),INDEX(ISNUMBER(SEARCH(Ангилал!$H$5:$H$16,$G36&" "&$E36))+ISNUMBER(SEARCH(Ангилал!$I$5:$I$16,$G36&" "&$E36))+ISNUMBER(SEARCH(Ангилал!$J$5:$J$16,$G36&" "&$E36))+ISNUMBER(SEARCH(Ангилал!$K$5:$K$16,$G36&" "&$E36))>0,0),0)),"Ерөнхий нийт"))} -> Цөөнх, үндэстэн ястан | Q36: =IF($G36="","",IF($P36<>"",$P36,$O36)) -> Цөөнх, үндэстэн ястан
A37: 30 | B37: 2026.05.05 | D37: UN leads call to prepare ‘for when digital systems fail’ | E37: НҮБ дижитал системүүд доголдсон үед бэлэн байх шаардлагатайг анхааруулж, “дижитал тахал” үүсэх эрсдэлийн талаар дэлхий нийтийг сэрэмжлүүллээ. “Digital risks: From solar storms to extreme weather” нэртэй шинэ тайланд хиймэл дагуул, цахилгаан сүлжээ, банк санхүү, эрүүл мэнд, тээвэр, холбоо зэрэг харилцан уялдаатай системүүд нэгэн зэрэг доголдвол дэлхий даяар гинжин нөлөө бүхий хямрал үүсэж болзошгүйг онцолжээ. | F37: НҮБ | G37: Цахим технологи | I37: UN news | J37: https://news.un.org/en/story/2026/05/1167445 | L37: {=IF($G37="","",IFERROR(INDEX(Ангилал!$A$5:$A$22,MATCH(TRUE(),INDEX(ISNUMBER(SEARCH(Ангилал!$B$5:$B$22,$G37&" "&$E37))+ISNUMBER(SEARCH(Ангилал!$C$5:$C$22,$G37&" "&$E37))+IF(Ангилал!$D$5:$D$22="",0,ISNUMBER(SEARCH(Ангилал!$D$5:$D$22,$G37&" "&$E37)))+IF(Ангилал!$E$5:$E$22="",0,ISNUMBER(SEARCH(Ангилал!$E$5:$E$22,$G37&" "&$E37)))>0,0),0)),"Бусад"))} -> Эрүүл мэндийн эрх | N37: =IF($G37="","",IF($M37<>"",$M37,$L37)) -> Эрүүл мэндийн эрх | O37: {=IF($G37="","",IFERROR(INDEX(Ангилал!$G$5:$G$16,MATCH(TRUE(),INDEX(ISNUMBER(SEARCH(Ангилал!$H$5:$H$16,$G37&" "&$E37))+ISNUMBER(SEARCH(Ангилал!$I$5:$I$16,$G37&" "&$E37))+ISNUMBER(SEARCH(Ангилал!$J$5:$J$16,$G37&" "&$E37))+ISNUMBER(SEARCH(Ангилал!$K$5:$K$16,$G37&" "&$E37))>0,0),0)),"Ерөнхий нийт"))} -> Ерөнхий нийт | Q37: =IF($G37="","",IF($P37<>"",$P37,$O37)) -> Ерөнхий нийт
A38: 31 | B38: 2026.05.06 | D38: Hantavirus outbreak: Another passenger contracts disease | E38: Хантавирусын дэгдэлттэй холбоотой аяллын хөлөг онгоц дээр өөр нэг зорчигч уг өвчнөөр өвчилсөн нь батлагджээ. Уг өвчний улмаас онгоцонд байсан гурван хүний ​​аминд хүрч, ДЭМБ-аас бэлэн байдал зарлаад байна. | F38: НҮБ | G38: Эмнэлгийн тусламж үйлчилгээ авах | I38: UN news | J38: https://news.un.org/en/story/2026/05/1167449 | L38: {=IF($G38="","",IFERROR(INDEX(Ангилал!$A$5:$A$22,MATCH(TRUE(),INDEX(ISNUMBER(SEARCH(Ангилал!$B$5:$B$22,$G38&" "&$E38))+ISNUMBER(SEARCH(Ангилал!$C$5:$C$22,$G38&" "&$E38))+IF(Ангилал!$D$5:$D$22="",0,ISNUMBER(SEARCH(Ангилал!$D$5:$D$22,$G38&" "&$E38)))+IF(Ангилал!$E$5:$E$22="",0,ISNUMBER(SEARCH(Ангилал!$E$5:$E$22,$G38&" "&$E38)))>0,0),0)),"Бусад"))} -> Эрүүл мэндийн эрх | N38: =IF($G38="","",IF($M38<>"",$M38,$L38)) -> Эрүүл мэндийн эрх | O38: {=IF($G38="","",IFERROR(INDEX(Ангилал!$G$5:$G$16,MATCH(TRUE(),INDEX(ISNUMBER(SEARCH(Ангилал!$H$5:$H$16,$G38&" "&$E38))+ISNUMBER(SEARCH(Ангилал!$I$5:$I$16,$G38&" "&$E38))+ISNUMBER(SEARCH(Ангилал!$J$5:$J$16,$G38&" "&$E38))+ISNUMBER(SEARCH(Ангилал!$K$5:$K$16,$G38&" "&$E38))>0,0),0)),"Ерөнхий нийт"))} -> Ерөнхий нийт | Q38: =IF($G38="","",IF($P38<>"",$P38,$O38)) -> Ерөнхий нийт
A39: 32 | B39: 2026.05.05 | D39: BAHRAIN: Civil society urges world leaders to act against citizenship stripping and related human rights violations | E39: Бахрейны засгийн газрын иргэншил хураах бодлогыг олон улсын хүний эрхийн байгууллагууд шүүмжилж, дэлхийн удирдагчдыг арга хэмжээ авахыг уриалжээ. | F39: Бахрейн | G39: Иргэншилтэй байх, үзэл бодлоо илэрхийлэх эрх | H39: Бахрейн улсын Засгийн газар | I39: Сivicus | J39: https://www.civicus.org/index.php/media-resources/news/8302-bahrain-civil-society-urges-world-leaders-to-act-against-citizenship-stripping-and-related-human-rights-violations | L39: {=IF($G39="","",IFERROR(INDEX(Ангилал!$A$5:$A$22,MATCH(TRUE(),INDEX(ISNUMBER(SEARCH(Ангилал!$B$5:$B$22,$G39&" "&$E39))+ISNUMBER(SEARCH(Ангилал!$C$5:$C$22,$G39&" "&$E39))+IF(Ангилал!$D$5:$D$22="",0,ISNUMBER(SEARCH(Ангилал!$D$5:$D$22,$G39&" "&$E39)))+IF(Ангилал!$E$5:$E$22="",0,ISNUMBER(SEARCH(Ангилал!$E$5:$E$22,$G39&" "&$E39)))>0,0),0)),"Бусад"))} -> Үзэл бодлоо илэрхийлэх, мэдээллийн эрх | N39: =IF($G39="","",IF($M39<>"",$M39,$L39)) -> Үзэл бодлоо илэрхийлэх, мэдээллийн эрх | O39: {=IF($G39="","",IFERROR(INDEX(Ангилал!$G$5:$G$16,MATCH(TRUE(),INDEX(ISNUMBER(SEARCH(Ангилал!$H$5:$H$16,$G39&" "&$E39))+ISNUMBER(SEARCH(Ангилал!$I$5:$I$16,$G39&" "&$E39))+ISNUMBER(SEARCH(Ангилал!$J$5:$J$16,$G39&" "&$E39))+ISNUMBER(SEARCH(Ангилал!$K$5:$K$16,$G39&" "&$E39))>0,0),0)),"Ерөнхий нийт"))} -> Ерөнхий нийт | Q39: =IF($G39="","",IF($P39<>"",$P39,$O39)) -> Ерөнхий нийт
A40: 33 | B40: 2026.05.06 | C40: 2026.05.05 | D40: Russian strikes kill 27 in Ukraine ahead of rival ceasefires around Moscow’s Victory Day parade | E40: Мягмар гарагт Оросын халдлагын улмаас Украин даяар 20 гаруй хүн амь үрэгдсэн бөгөөд тэдний 12 нь энэ оны хамгийн олон хүний амь хохирсон халдлагуудын нэгэнд өртсөн байна. Энэ нь Киевээс санал болгосон хугацаагүй гал зогсоох хэлэлцээр шөнө дундаас хэрэгжиж эхлэхээс хэдхэн цагийн өмнө болсон юм. | F40: Украин улс | G40: Амьд явах, халдашгүй чөлөөтэй байх эрх | H40: ОХУ | I40: CNN | J40: https://edition.cnn.com/2026/05/05/europe/russia-strike-before-victory-day-parade-intl | L40: {=IF($G40="","",IFERROR(INDEX(Ангилал!$A$5:$A$22,MATCH(TRUE(),INDEX(ISNUMBER(SEARCH(Ангилал!$B$5:$B$22,$G40&" "&$E40))+ISNUMBER(SEARCH(Ангилал!$C$5:$C$22,$G40&" "&$E40))+IF(Ангилал!$D$5:$D$22="",0,ISNUMBER(SEARCH(Ангилал!$D$5:$D$22,$G40&" "&$E40)))+IF(Ангилал!$E$5:$E$22="",0,ISNUMBER(SEARCH(Ангилал!$E$5:$E$22,$G40&" "&$E40)))>0,0),0)),"Бусад"))} -> Амьд явах, халдашгүй байх эрх | N40: =IF($G40="","",IF($M40<>"",$M40,$L40)) -> Амьд явах, халдашгүй байх эрх | O40: {=IF($G40="","",IFERROR(INDEX(Ангилал!$G$5:$G$16,MATCH(TRUE(),INDEX(ISNUMBER(SEARCH(Ангилал!$H$5:$H$16,$G40&" "&$E40))+ISNUMBER(SEARCH(Ангилал!$I$5:$I$16,$G40&" "&$E40))+ISNUMBER(SEARCH(Ангилал!$J$5:$J$16,$G40&" "&$E40))+ISNUMBER(SEARCH(Ангилал!$K$5:$K$16,$G40&" "&$E40))>0,0),0)),"Ерөнхий нийт"))} -> Ерөнхий нийт | Q40: =IF($G40="","",IF($P40<>"",$P40,$O40)) -> Ерөнхий нийт
A41: 34 | B41: 2026.05.07 | D41: UN Guidance on Dismantling Gender Stereotypes | E41: НҮБ-ын Эмэгтэйчүүдийг алагчлах бүх хэлбэрийг устгах хорооноос жендэрийн хэвшмэл ойлголтын талаарх ерөнхий зөвлөмжийн төслийг боловсруулж байгааг сайшааж бйна. | G41: Жендэрийн эрх тэгш байдал, ялгаварлан гадуурхалтаас ангид байх | I41: Human rights watch | J41: https://www.hrw.org/news/2026/05/07/un-guidance-on-dismantling-gender-stereotypes Төсөл: https://www.ohchr.org/en/calls-for-input/2026/call-comments-draft-general-recommendation-gender-stereotypes | L41: {=IF($G41="","",IFERROR(INDEX(Ангилал!$A$5:$A$22,MATCH(TRUE(),INDEX(ISNUMBER(SEARCH(Ангилал!$B$5:$B$22,$G41&" "&$E41))+ISNUMBER(SEARCH(Ангилал!$C$5:$C$22,$G41&" "&$E41))+IF(Ангилал!$D$5:$D$22="",0,ISNUMBER(SEARCH(Ангилал!$D$5:$D$22,$G41&" "&$E41)))+IF(Ангилал!$E$5:$E$22="",0,ISNUMBER(SEARCH(Ангилал!$E$5:$E$22,$G41&" "&$E41)))>0,0),0)),"Бусад"))} -> Ялгаварлан гадуурхалтаас ангид байх, тэгш эрх | N41: =IF($G41="","",IF($M41<>"",$M41,$L41)) -> Ялгаварлан гадуурхалтаас ангид байх, тэгш эрх | O41: {=IF($G41="","",IFERROR(INDEX(Ангилал!$G$5:$G$16,MATCH(TRUE(),INDEX(ISNUMBER(SEARCH(Ангилал!$H$5:$H$16,$G41&" "&$E41))+ISNUMBER(SEARCH(Ангилал!$I$5:$I$16,$G41&" "&$E41))+ISNUMBER(SEARCH(Ангилал!$J$5:$J$16,$G41&" "&$E41))+ISNUMBER(SEARCH(Ангилал!$K$5:$K$16,$G41&" "&$E41))>0,0),0)),"Ерөнхий нийт"))} -> Эмэгтэйчүүд | Q41: =IF($G41="","",IF($P41<>"",$P41,$O41)) -> Эмэгтэйчүүд
A42: 2026.05.08-15 | L42: {=IF($G42="","",IFERROR(INDEX(Ангилал!$A$5:$A$22,MATCH(TRUE(),INDEX(ISNUMBER(SEARCH(Ангилал!$B$5:$B$22,$G42&" "&$E42))+ISNUMBER(SEARCH(Ангилал!$C$5:$C$22,$G42&" "&$E42))+IF(Ангилал!$D$5:$D$22="",0,ISNUMBER(SEARCH(Ангилал!$D$5:$D$22,$G42&" "&$E42)))+IF(Ангилал!$E$5:$E$22="",0,ISNUMBER(SEARCH(Ангилал!$E$5:$E$22,$G42&" "&$E42)))>0,0),0)),"Бусад"))} | N42: =IF($G42="","",IF($M42<>"",$M42,$L42)) | O42: {=IF($G42="","",IFERROR(INDEX(Ангилал!$G$5:$G$16,MATCH(TRUE(),INDEX(ISNUMBER(SEARCH(Ангилал!$H$5:$H$16,$G42&" "&$E42))+ISNUMBER(SEARCH(Ангилал!$I$5:$I$16,$G42&" "&$E42))+ISNUMBER(SEARCH(Ангилал!$J$5:$J$16,$G42&" "&$E42))+ISNUMBER(SEARCH(Ангилал!$K$5:$K$16,$G42&" "&$E42))>0,0),0)),"Ерөнхий нийт"))} | Q42: =IF($G42="","",IF($P42<>"",$P42,$O42))
A43: 35 | B43: 2026.05.08 | D43: Australia: 3 Alleged ISIS-Linked Women Face Serious Charges | E43: Human Rights Watch 2026 оны 5 дугаар сарын 7–8-нд Австралийн гурван эмэгтэйд ISIS (Islamic State буюу Islamic State of Iraq and Syria нь Ирак, Сирид үүссэн зэвсэгт хэт даврагч исламын бүлэглэл)-тэй холбоотой ноцтой гэмт хэрэгт холбогдуулан эрүүгийн хэрэг үүсгэсэнтэй холбоотойгоор шүүх ажиллагаа нь шударга шүүхийн болон хууль ёсны процессын бүх баталгааг бүрэн хангах ёстой гэж мэдэгдэв. Түүнчлэн энэ хэрэг нь Австрали улс 2002 онд баталсан олон улсын ноцтой гэмт хэргийг мөрдөн шалгах тухай хуулиа ашиглан хүн төрөлхтний эсрэг гэмт хэрэгт анх удаа ял тулгаж буй тохиолдол юм. | F43: Австрали улс | G43: Амьд явах, халдашгүй чөлөөтэй байх эрх | I43: Human rights watch | J43: https://www.hrw.org/news/2026/05/08/australia-3-alleged-isis-linked-women-face-serious-charges | L43: {=IF($G43="","",IFERROR(INDEX(Ангилал!$A$5:$A$22,MATCH(TRUE(),INDEX(ISNUMBER(SEARCH(Ангилал!$B$5:$B$22,$G43&" "&$E43))+ISNUMBER(SEARCH(Ангилал!$C$5:$C$22,$G43&" "&$E43))+IF(Ангилал!$D$5:$D$22="",0,ISNUMBER(SEARCH(Ангилал!$D$5:$D$22,$G43&" "&$E43)))+IF(Ангилал!$E$5:$E$22="",0,ISNUMBER(SEARCH(Ангилал!$E$5:$E$22,$G43&" "&$E43)))>0,0),0)),"Бусад"))} -> Амьд явах, халдашгүй байх эрх | N43: =IF($G43="","",IF($M43<>"",$M43,$L43)) -> Амьд явах, халдашгүй байх эрх | O43: {=IF($G43="","",IFERROR(INDEX(Ангилал!$G$5:$G$16,MATCH(TRUE(),INDEX(ISNUMBER(SEARCH(Ангилал!$H$5:$H$16,$G43&" "&$E43))+ISNUMBER(SEARCH(Ангилал!$I$5:$I$16,$G43&" "&$E43))+ISNUMBER(SEARCH(Ангилал!$J$5:$J$16,$G43&" "&$E43))+ISNUMBER(SEARCH(Ангилал!$K$5:$K$16,$G43&" "&$E43))>0,0),0)),"Ерөнхий нийт"))} -> Эмэгтэйчүүд | Q43: =IF($G43="","",IF($P43<>"",$P43,$O43)) -> Эмэгтэйчүүд
